Workbook
Name ARTICULO_2353: '2014'!$AU$25
Name ARTICULO_2354: '2014'!$AU$38
Name Tipo_de_via_principal: '2013'!$X$8:$X$1048576

Sheet 2013
AV1: ESTADO DEL PROCESO - FECHAS
AV2: Visita inicial | AY2: Visita de verificación 1 | BB2: Visita de verificación 2 | BE2: Visita de verificación 3 | BH2: Visita de verificación 4 | BK2: Acta de compromiso - comparecencia | BM2: Auto de inicio | BO2: Descargos | BQ2: Pruebas | BS2: Fallo - Decisión | BU2: Notificación - Remisión | BW2: Recurso de reposición | BY2: Notificación - Remisión | CA2: Capacitación | CC2: Remisión Hacienda | CE2: Auto de archivo | CG2: Archivo
A3: Conexo | B3: Consecutivo | C3: Radicado | D3: Recurso afectado | E3: Comparendo | F3: Codigo Infracción | G3: Predios y Otros documentos | H3: Asunto | I3: Quejoso | J3: Tipo de via principal | K3: N° via principal | L3: letra | M3: Cuadrante | N3: Generadora | O3: Letra | P3: Placa | Q3: Cuadrante | R3: Bloque | S3: Interior | T3: Dirección | U3: Cedula quejoso | V3: Telefono quejoso | W3: Infractor | X3: Tipo de via principal | Y3: N° via principal | Z3: letra | AA3: Cuadrante | AB3: Generadora | AC3: Letra | AD3: Placa | AE3: Cuadrante | AF3: Bloque | AG3: Interior | AH3: Direccion | AI3: Cedula Infractor | AJ3: Telefono Infractor | AK3: Lugar Infraccón Barrio | AL3: Vereda | AM3: Codigo Barrio | AN3: Manzana - Vereda | AO3: Predio | AP3: Zona | AQ3: Fecha de ingreso (dd/mm/aaaa) | AR3: Fecha de actuación inicial (dd(mm/aaaa) | AS3: Dias de atención | AT3: Destinación procedimental inical | AU3: Estado actual | AV3: Recibido - Asignado | AW3: Funcionario | AX3: Entregado | AY3: Recibido - Asignado | AZ3: Funcionario | BA3: Entregado | BB3: Recibido - Asignado | BC3: Funcionario | BD3: Entregado | BE3: Recibido - Asignado | BF3: Funcionario | BG3: Entregado | BH3: Recibido - Asignado | BI3: Funcionario | BJ3: Entregado | BK3: Recibido - Asignado | BL3: Entregado | BM3: Recibido - Asignado | BN3: Entregado | BO3: Recibido - Asignado | BP3: Entregado | BQ3: Recibido - Asignado | BR3: Entregado | BS3: Recibido - Asignado | BT3: Entregado | BU3: Recibido - Asignado | BV3: Entregado | BW3: Recibido - Asignado | BX3: Entregado | BY3: Recibido - Asignado | BZ3: Entregado | CA3: Recibido - Asignado | CB3: Entregado | CC3: Recibido - Asignado | CD3: Entregado | CE3: Recibido - Asignado | CF3: Entregado | CG3: Recibido - Asignado | CH3: Entregado
B4: 001-2013 | C4: 1300011 | D4: ESPACIOS PUBLICOS VERDES | E4: ESCOMBROS | F4: 3 | H4: Escombros arrojados en espacio público | I4: De Oficio | T4: =CONCATENATE(J4," ",K4," ",L4," ",M4," ",N4," ",O4," ",P4," ",Q4," ",R4," ",S4) | U4: no reporta | V4: no reporta | W4: John Camilo | X4: KR | Y4: 41 | Z4: - | AA4: - | AB4: 40 | AC4: G | AD4: 8 | AE4: SUR | AH4: =CONCATENATE(X4," ",Y4," ",Z4," ",AA4," ",AB4," ",AC4," ",AD4," ",AE4," ",AF4," ",AG4) -> KR 41 - - 40 G 8 SUR | AI4: no reporta | AJ4: no reporta | AK4: El Dorado | AL4: - | AM4: 013 | AN4: - | AP4: 9 | AQ4: 41278 | AT4: Acuerdo 020 de 2009 | AU4: Auto de inicio
B5: Operativo de control de fauna doméstica | C5: 1300010 | D5: ESPACIOS PUBLICOS VERDES | E5: ESCOMBROS | F5: 3 | H5: Escombros arrojados en espacio público | I5: Ana Quintero | J5: KR | K5: 24 | L5: F | N5: 40 | P5: 152 | Q5: SUR | T5: =CONCATENATE(J5," ",K5," ",L5," ",M5," ",N5," ",O5," ",P5," ",Q5," ",R5," ",S5) -> KR 24 F 40 152 SUR | U5: no reporta | V5: 3333280 | W5: Pedro Uribe | AC5: - | AH5: =CONCATENATE(X5," ",Y5," ",Z5," ",AA5," ",AB5," ",AC5," ",AD5," ",AE5," ",AF5," ",AG5) -> - | AI5: no reporta | AJ5: no reporta | AK5: El Salado | AP5: 6 | AQ5: 41278 | AR5: 41291 | AS5: =+AR5-AQ5 -> 13 | AT5: Acta de Compromiso | AU5: Auto de archivo
B6: 003-2013 | C6: 1300013 | D6: FAUNA DOMESTICA | H6: Ataque de mascota a otra | I6: Luis Enrique Restrepo | J6: CL | K6: 40 | L6: C | M6: SUR | N6: 42 | P6: 38 | S6: 202 | T6: =CONCATENATE(J6," ",K6," ",L6," ",M6," ",N6," ",O6," ",P6," ",Q6," ",R6," ",S6) -> CL 40 C SUR 42 38 202 | U6: no reporta | V6: 3332916 | W6: Por determinar | X6: KR | Y6: 43 | Z6: A | AB6: 41 | AC6: A | AD6: 20 | AE6: SUR | AG6: 101 | AH6: =CONCATENATE(X6," ",Y6," ",Z6," ",AA6," ",AB6," ",AC6," ",AD6," ",AE6," ",AF6," ",AG6) -> KR 43 A 41 A 20 SUR 101 | AI6: no reporta | AJ6: no reporta | AK6: El Dorado | AP6: 9 | AQ6: 41278 | AR6: 41286 | AS6: =+AR6-AQ6 -> 8 | AT6: Codigo de Policia | AU6: Auto de archivo | AV6: 41354 | AW6: L. Garcia | AX6: 41354 | BM6: 41286 | CE6: 41675
B7: 004-2013 | C7: 1300016 | D7: SUELO | E7: ESCOMBROS | F7: 5 | H7: Escombros y residuos de excavación en zona de retiro de la quebrada La Morgan. Comparendo 296. | I7: Inspección Palmas | T7: =CONCATENATE(J7," ",K7," ",L7," ",M7," ",N7," ",O7," ",P7," ",Q7," ",R7," ",S7) | U7: no reporta | V7: no reporta | W7: Maria Gelsen G | AH7: =CONCATENATE(X7," ",Y7," ",Z7," ",AA7," ",AB7," ",AC7," ",AD7," ",AE7," ",AF7," ",AG7) | AI7: no reporta | AJ7: 3860505 | AL7: Las Palmas | AP7: 12 | AQ7: 41282 | AR7: 41297 | AS7: =+AR7-AQ7 -> 15 | AT7: Acuerdo 020 de 2009 | AU7: Auto de archivo | AV7: 41282 | AW7: F. Villarraga | AX7: 41282 | BM7: 41297 | BN7: 41299 | BO7: 41299 | BP7: 41305 | BS7: 41305 | BT7: 41337 | BU7: 41337 | BV7: 41346 | CA7: 41393 | CB7: 41393 | CC7: 41396 | CD7: 41396 | CE7: 41438
B8: 005-2013 | C8: 1300023 | D8: FLORA | H8: Tala de arboles en retiro de la quebrada La Honda | I8: Cristina Arango | T8: =CONCATENATE(J8," ",K8," ",L8," ",M8," ",N8," ",O8," ",P8," ",Q8," ",R8," ",S8) | U8: no reporta | V8: 3566947 - 3127949205 | W8: Urbanización Puebla | AH8: =CONCATENATE(X8," ",Y8," ",Z8," ",AA8," ",AB8," ",AC8," ",AD8," ",AE8," ",AF8," ",AG8) | AI8: no reporta | AJ8: no reporta | AK8: El Esmeraldal | AP8: 4 | AQ8: 40916 | AS8: =+AR8-AQ8 -> -40916 | AT8: Acta de Compromiso | AU8: Auto de archivo
B9: 006-2013 | C9: 1300025 | D9: - | E9: RESIDUOS SOLIDOS | F9: 3 | H9: Sensibilización por residuos solidos | I9: De Oficio | T9: =CONCATENATE(J9," ",K9," ",L9," ",M9," ",N9," ",O9," ",P9," ",Q9," ",R9," ",S9) | W9: Ministerio Semilla de Fe | X9: KR | Y9: 40 | AB9: 39 | AC9: B | AD9: 20 | AE9: SUR | AH9: =CONCATENATE(X9," ",Y9," ",Z9," ",AA9," ",AB9," ",AC9," ",AD9," ",AE9," ",AF9," ",AG9) -> KR 40 39 B 20 SUR | AI9: no reporta | AJ9: 4442718 | AK9: El Dorado | AP9: 9 | AQ9: 41282 | AS9: =+AR9-AQ9 -> -41282 | AT9: Acta de Compromiso | AU9: Visitas técnicos
B10: 007-2013 | C10: 1300040 | D10: ESPACIOS PUBLICOS VERDES | E10: ESCOMBROS | F10: 3 | H10: Escombros y material de construcción en espacio público. Compendo N°292 | I10: De Oficio | T10: =CONCATENATE(J10," ",K10," ",L10," ",M10," ",N10," ",O10," ",P10," ",Q10," ",R10," ",S10) | U10: no reporta | V10: no reporta | W10: Diego A. Zapata Lopez | X10: KR | Y10: 40 | AB10: 47 | AD10: 44 | AE10: SUR | AH10: =CONCATENATE(X10," ",Y10," ",Z10," ",AA10," ",AB10," ",AC10," ",AD10," ",AE10," ",AF10," ",AG10) -> KR 40 47 44 SUR | AI10: no reporta | AJ10: no reporta | AK10: El Trianon | AP10: 7 | AQ10: 41283 | AR10: 41303 | AS10: =+AR10-AQ10 -> 20 | AT10: Acuerdo 020 de 2009 | AU10: Auto de archivo | BM10: 41290 | BN10: 41303 | BO10: 41311 | BS10: 41446 | BT10: 41506 | BW10: 41316 | CE10: 41517
A11: 753-2011 | B11: 008-2013 | C11: 1300041 - 1302828 - 1304346 - 1307826 | D11: FAUNA DOMESTICA | H11: Afectacion por mascotas que generan ruido y pasan a techos vecinos. | I11: Rafael Ochoa Villegas | J11: KR | K11: 26 | N11: 40 | O11: B | P11: 2 | Q11: SUR | S11: 102 | T11: =CONCATENATE(J11," ",K11," ",L11," ",M11," ",N11," ",O11," ",P11," ",Q11," ",R11," ",S11) -> KR 26 40 B 2 SUR 102 | U11: 98662945 | V11: 2764570 | W11: Lizabeth Montoya Santana | X11: KR | Y11: 26 | AB11: 40 | AC11: B | AE11: SUR | AF11: 2 | AG11: 120 | AH11: =CONCATENATE(X11," ",Y11," ",Z11," ",AA11," ",AB11," ",AC11," ",AD11," ",AE11," ",AF11," ",AG11) -> KR 26 40 B SUR 2 120 | AI11: no reporta | AJ11: 3131431 - 3312663 | AK11: La Mina | AP11: 6 | AQ11: 41283 | AR11: 41295 | AS11: =+AR11-AQ11 -> 12 | AT11: Codigo de Policia | AU11: Auto de archivo | AV11: 41295 | AW11: J. Guzman | AX11: 41295 | BM11: 41304 | BN11: 41306 | BO11: 41353 | CE11: 41675
B12: 009-2013 | C12: 1300042 - 1300606 | D12: ESPACIOS PUBLICOS VERDES | E12: ESCOMBROS | F12: 9 | H12: Escombros y materiales en espacio público. Comparendo N° 293. | I12: De Oficio | T12: =CONCATENATE(J12," ",K12," ",L12," ",M12," ",N12," ",O12," ",P12," ",Q12," ",R12," ",S12) | W12: Jose Gildardo Velasquez Restrepo | X12: KR | Y12: 40 | AB12: 47 | AD12: 2 | AE12: SUR | AG12: 101 | AH12: =CONCATENATE(X12," ",Y12," ",Z12," ",AA12," ",AB12," ",AC12," ",AD12," ",AE12," ",AF12," ",AG12) -> KR 40 47 2 SUR 101 | AI12: 70094458 | AJ12: 3147390992 | AK12: El Trianon | AP12: 7 | AQ12: 41283 | AR12: 41290 | AS12: =+AR12-AQ12 -> 7 | AT12: Acuerdo 020 de 2009 | AU12: Auto de archivo | AV12: 41283 | AW12: F. Villarraga | AX12: 41283 | BM12: 41290 | BN12: 41296 | BO12: 41296 | BP12: 41303 | BS12: 41303 | BT12: 41309 | BU12: 41309 | BV12: 41317 | BW12: 41327 | BX12: 41334 | BY12: 41334 | BZ12: 41340 | CC12: 41396 | CD12: 41396 | CE12: 41438
B13: 010-2013 | C13: 1300067 - 101594 | D13: AIRE | H13: Lote donde acumularon restos de animales que generan olores desagradables. | I13: Natalia Gonzalez | J13: KR | K13: 46 | N13: 48 | O13: C | P13: 92 | Q13: SUR | T13: =CONCATENATE(J13," ",K13," ",L13," ",M13," ",N13," ",O13," ",P13," ",Q13," ",R13," ",S13) -> KR 46 48 C 92 SUR | U13: 32242505 | V13: 4444664 | W13: Carlos Mariano Pruna Jaramillo | X13: KR | Y13: 46 | AB13: 48 | AC13: C | AD13: 99 | AE13: SUR | AG13: lt3a | AH13: =CONCATENATE(X13," ",Y13," ",Z13," ",AA13," ",AB13," ",AC13," ",AD13," ",AE13," ",AF13," ",AG13) -> KR 46 48 C 99 SUR lt3a | AI13: 8252416 | AJ13: 3124423 - 3136524974 | AK13: Primavera | AP13: 8 | AQ13: 41285 | AR13: 41289 | AS13: =+AR13-AQ13 -> 4 | AT13: Acta de Compromiso | AU13: Auto de archivo
B14: 011-2013 | C14: 1300052 | D14: - | E14: ESCOMBROS | F14: 3 | H14: Lote que es usado como botadero de escombros y disposición inadecuada cercana al sitio de otros residuos. | I14: Enviaseo | T14: =CONCATENATE(J14," ",K14," ",L14," ",M14," ",N14," ",O14," ",P14," ",Q14," ",R14," ",S14) | U14: no reporta | V14: no reporta | W14: Sergio | X14: CL | Y14: 39 | Z14: F | AA14: SUR | AB14: 24 | AC14: DD | AD14: 8 | AH14: =CONCATENATE(X14," ",Y14," ",Z14," ",AA14," ",AB14," ",AC14," ",AD14," ",AE14," ",AF14," ",AG14) -> CL 39 F SUR 24 DD 8 | AI14: no reporta | AJ14: no reporta | AK14: El Salado | AM14: 002 | AN14: 004 | AO14: 00020 | AP14: 6 | AQ14: 41284 | AR14: 41298 | AS14: =+AR14-AQ14 -> 14 | AT14: Acta de Compromiso | AU14: Auto de archivo | AV14: 41298 | AW14: L. Taborda | AX14: 41298 | AY14: 41355 | AZ14: J.Restrepo - S. Bustamante | BA14: 41355 | BB14: 41393 | BC14: C. Rojas - J. Restrepo | BD14: 41393 | CE14: 41393
B15: 012-2013 | C15: 1300057 | D15: AIRE | H15: Olores desagradables percibidos por heces fecales en jardines del parque principal. | I15: Luis Gonzaga Caro Porras | J15: TR | K15: 35 | L15: C | M15: SUR | N15: 30 | P15: 38 | S15: 301 | T15: =CONCATENATE(J15," ",K15," ",L15," ",M15," ",N15," ",O15," ",P15," ",Q15," ",R15," ",S15) -> TR 35 C SUR 30 38 301 | U15: 9058749 | V15: 3314450 | W15: Por determinar | AH15: =CONCATENATE(X15," ",Y15," ",Z15," ",AA15," ",AB15," ",AC15," ",AD15," ",AE15," ",AF15," ",AG15) | AI15: no reporta | AJ15: no reporta | AK15: Zona Centro | AP15: 9 | AQ15: 41284 | AS15: =+AR15-AQ15 -> -41284 | AT15: Remision u otros | AU15: Auto de archivo
B16: 013-2013 | C16: 1300058 | D16: ESPACIOS PUBLICOS VERDES | E16: RESIDUOS SOLIDOS | F16: 3 | H16: Disposición inadecuada de residuos sólidos | I16: Angelica Gonzalez | J16: KR | K16: 42 | L16: B | N16: 26 | P16: 50 | Q16: SUR | T16: =CONCATENATE(J16," ",K16," ",L16," ",M16," ",N16," ",O16," ",P16," ",Q16," ",R16," ",S16) -> KR 42 B 26 50 SUR | U16: 21656826 | V16: 2283045 | W16: Diego Merca Express | X16: KR | Y16: 42 | Z16: B | AB16: 26 | AD16: 47 | AE16: SUR | AH16: =CONCATENATE(X16," ",Y16," ",Z16," ",AA16," ",AB16," ",AC16," ",AD16," ",AE16," ",AF16," ",AG16) -> KR 42 B 26 47 SUR | AI16: no reporta | AJ16: no reporta | AK16: Las Orquideas | AM16: 035 | AN16: 003 | AO16: 00039 | AP16: 3 | AQ16: 41284 | AR16: 41298 | AS16: =+AR16-AQ16 -> 14 | AT16: Acta de Compromiso | AU16: Auto de archivo
B17: 014-2013 | C17: 1300068 | D17: ESPACIOS PUBLICOS VERDES | E17: RESIDUOS SOLIDOS | F17: 3 | H17: Disposición inadecuada de residuos sólidos | I17: Jesus Maria Tangarife | J17: KR | K17: 32 | L17: B | N17: 40 | O17: F | P17: 25 | Q17: SUR | T17: =CONCATENATE(J17," ",K17," ",L17," ",M17," ",N17," ",O17," ",P17," ",Q17," ",R17," ",S17) -> KR 32 B 40 F 25 SUR | U17: no reporta | V17: 3024516 | W17: Administración Flores de la Colina I | X17: KR | Y17: 32 | Z17: B | AB17: 40 | AC17: F | AD17: 25 | AE17: SUR | AH17: =CONCATENATE(X17," ",Y17," ",Z17," ",AA17," ",AB17," ",AC17," ",AD17," ",AE17," ",AF17," ",AG17) -> KR 32 B 40 F 25 SUR | AI17: no reporta | AJ17: 2701792 | AK17: El Dorado | AM17: 013 | AN17: 001 | AO17: 00074 | AP17: 9 | AQ17: 41285 | AR17: 41298 | AS17: =+AR17-AQ17 -> 13 | AT17: Acta de Compromiso | AU17: Auto de archivo
B18: 015-2013 | C18: 1300073 | D18: FAUNA DOMESTICA | H18: Ataque de mascota a persona | I18: Andres Lopez | J18: CL | K18: 37 | M18: SUR | N18: 28 | P18: 5 | S18: 125 | T18: =CONCATENATE(J18," ",K18," ",L18," ",M18," ",N18," ",O18," ",P18," ",Q18," ",R18," ",S18) -> CL 37 SUR 28 5 125 | U18: 79591727 | V18: 3335216 | W18: Cesar Segura | X18: CL | Y18: 37 | AA18: SUR | AB18: 28 | AD18: 5 | AF18: 4 | AG18: 220 | AH18: =CONCATENATE(X18," ",Y18," ",Z18," ",AA18," ",AB18," ",AC18," ",AD18," ",AE18," ",AF18," ",AG18) -> CL 37 SUR 28 5 4 220 | AI18: 76314430 | AJ18: 3027387 | AK18: La Pradera | AP18: 5 | AQ18: 41285 | AR18: 41295 | AS18: =+AR18-AQ18 -> 10 | AT18: Acta de Compromiso | AU18: Auto de archivo
B19: 016-2013 | C19: 1300091 | D19: AIRE | H19: Quema de residuos solidos que generan perjuicios en el sector. | I19: Maria Paulina Ramírez | J19: KR | K19: 27 | L19: D | N19: 27 | P19: 123 | Q19: SUR | T19: =CONCATENATE(J19," ",K19," ",L19," ",M19," ",N19," ",O19," ",P19," ",Q19," ",R19," ",S19) -> KR 27 D 27 123 SUR | U19: 1037571558 | V19: 4186925 | W19: Por determinar | X19: KR | Y19: 27 | Z19: D | AB19: 27 | AD19: 107 | AE19: SUR | AH19: =CONCATENATE(X19," ",Y19," ",Z19," ",AA19," ",AB19," ",AC19," ",AD19," ",AE19," ",AF19," ",AG19) -> KR 27 D 27 107 SUR | AI19: no reporta | AJ19: no reporta | AK19: El Esmeraldal | AP19: 4 | AQ19: 41289 | AS19: =+AR19-AQ19 -> -41289 | AT19: Acta de Compromiso | AU19: Visitas técnicos
B20: 017-2013 | C20: 1300097 | D20: FAUNA SILVESTRE | H20: Ataque con piedras a pajaros y ardillas | I20: Esperanza Londoño | J20: CL | K20: 41 | L20: A | M20: SUR | N20: 32 | P20: 13 | R20: 2.6 | S20: 401 | T20: =CONCATENATE(J20," ",K20," ",L20," ",M20," ",N20," ",O20," ",P20," ",Q20," ",R20," ",S20) -> CL 41 A SUR 32 13 2,6 401 | U20: 42865774 | V20: no reporta | W20: Miriam Maya | X20: CL | Y20: 41 | Z20: A | AA20: SUR | AB20: 32 | AD20: 13 | AF20: 2.3 | AG20: 103 | AH20: =CONCATENATE(X20," ",Y20," ",Z20," ",AA20," ",AB20," ",AC20," ",AD20," ",AE20," ",AF20," ",AG20) -> CL 41 A SUR 32 13 2,3 103 | AI20: no reporta | AJ20: no reporta | AK20: El Dorado | AM20: 013 | AN20: 039 | AO20: 00032 | AP20: 9 | AQ20: 41289 | AR20: 41298 | AS20: =+AR20-AQ20 -> 9 | AT20: Acta de Compromiso | AU20: Auto de archivo
A21: C951-2011 | B21: 018-2013 | C21: 1300092 | D21: HIDRICO | H21: Afectación por pozo septico a vecinos | I21: De Oficio | T21: =CONCATENATE(J21," ",K21," ",L21," ",M21," ",N21," ",O21," ",P21," ",Q21," ",R21," ",S21) | W21: Jose David Suarez Ochoa | X21: KR | Y21: 80 | AB21: 32 | AC21: EE | AD21: 61 | AG21: 301 | AH21: =CONCATENATE(X21," ",Y21," ",Z21," ",AA21," ",AB21," ",AC21," ",AD21," ",AE21," ",AF21," ",AG21) -> KR 80 32 EE 61 301 | AI21: no reporta | AJ21: 4110241 | AK21: Loma El Atravezado | AP21: 4 | AQ21: 41289 | AR21: 41295 | AS21: =+AR21-AQ21 -> 6 | AT21: Ley 142 de 1994 | AU21: Auto de archivo | BO21: 41446
B22: 019-2013 | C22: 1300103 | D22: FLORA | H22: Tala de bosque nativo | I22: Adriana Escobar | R22: lote 39A | T22: =CONCATENATE(J22," ",K22," ",L22," ",M22," ",N22," ",O22," ",P22," ",Q22," ",R22," ",S22) -> lote 39A | U22: 42974261 | V22: 2709754 | W22: Por determinar | AF22: caldas | AH22: =CONCATENATE(X22," ",Y22," ",Z22," ",AA22," ",AB22," ",AC22," ",AD22," ",AE22," ",AF22," ",AG22) -> caldas | AI22: no reporta | AJ22: no reporta | AL22: El Vallano | AP22: 11 | AQ22: 41289 | AS22: =+AR22-AQ22 -> -41289 | AT22: Remision u otros | AU22: Auto de archivo
B23: 020-2013 | C23: 1300112 | D23: - | E23: RESIDUOS SOLIDOS | F23: 3 | H23: Disposición inadecuada de residuos sólidos | I23: Miriam Ruiz | J23: TR | K23: 35 | M23: SUR | N23: 31 | P23: 28 | T23: =CONCATENATE(J23," ",K23," ",L23," ",M23," ",N23," ",O23," ",P23," ",Q23," ",R23," ",S23) -> TR 35 SUR 31 28 | U23: 42745526 | V23: 2700019 | W23: Por determinar | X23: TR | Y23: 35 | AA23: SUR | AB23: 31 | AD23: 28 | AH23: =CONCATENATE(X23," ",Y23," ",Z23," ",AA23," ",AB23," ",AC23," ",AD23," ",AE23," ",AF23," ",AG23) -> TR 35 SUR 31 28 | AI23: no reporta | AJ23: no reporta | AK23: Uribe Angel | AP23: 3 | AQ23: 41290 | AR23: 41325 | AS23: =+AR23-AQ23 -> 35 | AT23: Acta de Compromiso | AU23: Verificación
B24: 021-2013 | C24: 1300113 | D24: ESPACIOS PUBLICOS VERDES | E24: RESIDUOS SOLIDOS | F24: 3 | H24: Disposición inadecuada de residuos sólidos | I24: Resfa Garces | J24: CL | K24: 45 | L24: BB | M24: SUR | N24: 43 | O24: A | P24: 87 | T24: =CONCATENATE(J24," ",K24," ",L24," ",M24," ",N24," ",O24," ",P24," ",Q24," ",R24," ",S24) -> CL 45 BB SUR 43 A 87 | U24: 32449060 | V24: 3790746 | W24: Recicladores | X24: CL | Y24: 45 | Z24: BB | AA24: SUR | AB24: 43 | AC24: A | AD24: 87 | AF24: AL LADO | AH24: =CONCATENATE(X24," ",Y24," ",Z24," ",AA24," ",AB24," ",AC24," ",AD24," ",AE24," ",AF24," ",AG24) -> CL 45 BB SUR 43 A 87 AL LADO | AI24: no reporta | AJ24: no reporta | AK24: Alcala | AP24: 8 | AQ24: 41290 | AR24: 41320 | AS24: =+AR24-AQ24 -> 30 | AT24: Acta de Compromiso | AU24: Visitas patrulleros | AV24: 41320 | AW24: J. Alvarez - L. Garcia | AX24: 41320
B25: 022-2013 | C25: 1300122 | D25: - | E25: RESIDUOS SOLIDOS | F25: 3 | G25: LOTE SIN CERRAMIENTO | H25: Lote donde depositan residuos solidos frente a peticionario | I25: Julian Monroy | J25: KR | K25: 24 | L25: F | N25: 40 | P25: 142 | Q25: SUR | T25: =CONCATENATE(J25," ",K25," ",L25," ",M25," ",N25," ",O25," ",P25," ",Q25," ",R25," ",S25) -> KR 24 F 40 142 SUR | U25: 71174294 | V25: 2715023 | W25: Por determinar | AH25: =CONCATENATE(X25," ",Y25," ",Z25," ",AA25," ",AB25," ",AC25," ",AD25," ",AE25," ",AF25," ",AG25) | AI25: no reporta | AJ25: no reporta | AK25: - | AL25: El Vallano | AN25: 001 | AO25: 00452 | AP25: 11 | AQ25: 41291 | AR25: 41299 | AS25: =+AR25-AQ25 -> 8 | AT25: Acta de Compromiso | AU25: Auto de archivo
B26: 023-2013 | C26: 1300145 | D26: ESPACIOS PUBLICOS VERDES | E26: ESCOMBROS | F26: 3 | H26: Escombros en antejardin en zona pública. Comparendo 294 | I26: De Oficio | T26: =CONCATENATE(J26," ",K26," ",L26," ",M26," ",N26," ",O26," ",P26," ",Q26," ",R26," ",S26) | U26: no reporta | V26: no reporta | W26: Por determinar | X26: KR | Y26: 37 | AB26: 39 | AD26: 15 | AE26: SUR | AH26: =CONCATENATE(X26," ",Y26," ",Z26," ",AA26," ",AB26," ",AC26," ",AD26," ",AE26," ",AF26," ",AG26) -> KR 37 39 15 SUR | AI26: no reporta | AJ26: no reporta | AK26: Mesa | AP26: 9 | AQ26: 41292 | AS26: =+AR26-AQ26 -> -41292 | AT26: Acuerdo 020 de 2009 | AU26: Auto de inicio
B27: 024-2013 | C27: 1300146 | D27: ESPACIOS PUBLICOS VERDES | E27: ESCOMBROS | F27: 3 | H27: Escombros en espacio publico. Comparendo 295 | I27: De Oficio | T27: =CONCATENATE(J27," ",K27," ",L27," ",M27," ",N27," ",O27," ",P27," ",Q27," ",R27," ",S27) | U27: no reporta | V27: no reporta | W27: Aleida Helena Arango | X27: CL | Y27: 39 | Z27: B | AA27: SUR | AB27: 36 | AD27: 38 | AH27: =CONCATENATE(X27," ",Y27," ",Z27," ",AA27," ",AB27," ",AC27," ",AD27," ",AE27," ",AF27," ",AG27) -> CL 39 B SUR 36 38 | AI27: no reporta | AJ27: no reporta | AK27: Mesa | AP27: 9 | AQ27: 41292 | AR27: 41292 | AS27: =+AR27-AQ27 -> 0 | AT27: Acuerdo 020 de 2009 | AU27: Auto de archivo | AV27: 41292 | AW27: F. Villarraga | AX27: 41292 | BM27: 41292 | BN27: 41298 | BO27: 41305 | BP27: 41305 | BS27: 41446 | CE27: 41509
B28: 025-2013 | C28: 1300189 - AA 479 | D28: HIDRICO | H28: Requerimientos técnicos Concesión de Agua | I28: Autoridad Ambiental | T28: =CONCATENATE(J28," ",K28," ",L28," ",M28," ",N28," ",O28," ",P28," ",Q28," ",R28," ",S28) | U28: no reporta | V28: no reporta | W28: Amanda de Jesus Muñoz Martinez | X28: KR | Y28: 24 | Z28: C | AB28: 41 | AD28: 151 | AE28: SUR | AG28: 143-139 | AH28: =CONCATENATE(X28," ",Y28," ",Z28," ",AA28," ",AB28," ",AC28," ",AD28," ",AE28," ",AF28," ",AG28) -> KR 24 C 41 151 SUR 143-139 | AI28: 32325736 | AJ28: 3340176 | AL28: El Vallano | AP28: 11 | AQ28: 41295 | AR28: 41323 | AS28: =+AR28-AQ28 -> 28 | AT28: Acta de Compromiso | AU28: Auto de archivo
B29: 026-2013 | C29: 1300132 | D29: - | G29: LOTE | H29: Lote enmalezado que genera perjuicios al sector | I29: Guillermo Abad | J29: CL | K29: 53 | L29: C | M29: SUR | N29: 40 | O29: B | P29: 80 | T29: =CONCATENATE(J29," ",K29," ",L29," ",M29," ",N29," ",O29," ",P29," ",Q29," ",R29," ",S29) -> CL 53 C SUR 40 B 80 | U29: 71601756 | V29: 5795009 | W29: Por determinar | X29: KR | Y29: 43 | Z29: A | AB29: 50 | AC29: D | AD29: 106 | AE29: SUR | AH29: =CONCATENATE(X29," ",Y29," ",Z29," ",AA29," ",AB29," ",AC29," ",AD29," ",AE29," ",AF29," ",AG29) -> KR 43 A 50 D 106 SUR | AI29: no reporta | AJ29: no reporta | AK29: Loma del Barro | AM29: 007 | AN29: 027 | AO29: 00082 | AP29: 7 | AQ29: 41292 | AR29: 41303 | AS29: =+AR29-AQ29 -> 11 | AT29: Acta de Compromiso | AU29: Auto de archivo
B30: 027-2013 | C30: 1300131 | D30: ESPACIOS PUBLICOS VERDES | E30: ESCOMBROS | F30: 3 | H30: Vehiculo de placas LLG704 que arroja escombros en zona verde | I30: Anonimo | T30: =CONCATENATE(J30," ",K30," ",L30," ",M30," ",N30," ",O30," ",P30," ",Q30," ",R30," ",S30) | U30: no reporta | V30: no reporta | W30: Por determinar | X30: CL | Y30: 36 | AA30: SUR | AB30: 39 | AH30: =CONCATENATE(X30," ",Y30," ",Z30," ",AA30," ",AB30," ",AC30," ",AD30," ",AE30," ",AF30," ",AG30) -> CL 36 SUR 39 | AI30: no reporta | AJ30: no reporta | AK30: Los Naranjos | AP30: 9 | AQ30: 41292 | AR30: 41297 | AS30: =+AR30-AQ30 -> 5 | AT30: Acuerdo 020 de 2009 | AU30: Auto de archivo
B31: 028-2013 | C31: 1300128 | D31: - | E31: RESIDUOS SOLIDOS | F31: 3 | G31: LOTE SIN CERRAMIENTO | H31: Acumulación de residuos solidos en lote | I31: De Oficio | T31: =CONCATENATE(J31," ",K31," ",L31," ",M31," ",N31," ",O31," ",P31," ",Q31," ",R31," ",S31) | U31: no reporta | V31: no reporta | W31: Por determinar | X31: CL | Y31: 41 | AA31: SUR | AB31: 25 | AC31: A | AH31: =CONCATENATE(X31," ",Y31," ",Z31," ",AA31," ",AB31," ",AC31," ",AD31," ",AE31," ",AF31," ",AG31) -> CL 41 SUR 25 A | AI31: no reporta | AJ31: no reporta | AK31: La Mina | AM31: 003 | AN31: 001 | AO31: 00044 | AP31: 6 | AQ31: 41292 | AR31: 41305 | AS31: =+AR31-AQ31 -> 13 | AT31: Acta de Compromiso | AU31: Auto de archivo | AV31: 41324 | AW31: C. Rojas | AX31: 41324 | AY31: 41333 | AZ31: C. Rojas | BA31: 41333 | BB31: 41393 | BC31: J. Restrepo - S. Bustamante | BD31: 41393 | BK31: 41291 | BL31: 41303 | CE31: 41393
B32: 029-2013 | C32: 1300154 | D32: - | E32: MATERIAL DE CONTRUCCIÓN | H32: Caida de material de construcción en zona comun del edificio vegas del campestre | I32: Habitantes del edificio | J32: KR | K32: 44 | N32: 23 | P32: 52 | Q32: SUR | T32: =CONCATENATE(J32," ",K32," ",L32," ",M32," ",N32," ",O32," ",P32," ",Q32," ",R32," ",S32) -> KR 44 23 52 SUR | U32: no reporta | V32: no reporta | W32: Proyecto Torre Guayacan | X32: KR | Y32: 43 | Z32: A | AB32: 23 | AE32: SUR | AH32: =CONCATENATE(X32," ",Y32," ",Z32," ",AA32," ",AB32," ",AC32," ",AD32," ",AE32," ",AF32," ",AG32) -> KR 43 A 23 SUR | AI32: no reporta | AJ32: no reporta | AK32: Bosques de Zuñiga | AP32: 2 | AQ32: 41295 | AR32: 41323 | AS32: =+AR32-AQ32 -> 28 | AT32: Acta de Compromiso | AU32: Visitas patrulleros
A33: I.T 130336 Oficio 132185 I.T 132186 IT 1190 SAE8-14002 - 1311541-2014 - 1311653-2014 - 1313105-2014 | B33: 030-2013 | C33: 1300161 - 1300596 DP 130013 122161 DP 13041 - 122895 - 1302383 - 1305826-1307516-1307506-1307607-1307667 - 131848 - 131849 - 1308258 - 1308887-2014 - 1309067-2014 - 1309381-2014 - 1310403 - 1310829 | D33: SUELO | H33: Control de obra urbanistica | I33: William Chitiva | J33: CL | K33: 27 | L33: D | M33: SUR | N33: 27 | O33: C | T33: =CONCATENATE(J33," ",K33," ",L33," ",M33," ",N33," ",O33," ",P33," ",Q33," ",R33," ",S33) -> CL 27 D SUR 27 C | U33: no reporta | V33: no reporta | W33: Proyecto Amarello Inn | X33: KR | Y33: 27 | Z33: D | AB33: 27 | AD33: 126 | AE33: SUR | AH33: =CONCATENATE(X33," ",Y33," ",Z33," ",AA33," ",AB33," ",AC33," ",AD33," ",AE33," ",AF33," ",AG33) -> KR 27 D 27 126 SUR | AI33: no reporta | AJ33: no reporta | AK33: El Esmeraldal | AM33: 031 | AN33: 001 | AO33: 00120 | AP33: 4 | AQ33: 41295 | AR33: 41296 | AS33: =+AR33-AQ33 -> 1 | AT33: Acta de Compromiso | AU33: Citaciones | AV33: 41296 | AW33: J.Guzman | AX33: 41296 | AY33: 41313 | AZ33: J. Alvarez - L. Garcia | BA33: 41313 | BB33: 41338 | BC33: L.Taborda | BD33: 41338 | BE33: 41459 | BF33: J.Guzman | BG33: 41459 | BH33: 41507 | BI33: L. Taborda - JIUD | BJ33: 41507 | BK33: 41519 | BL33: 41519
B34: 031-2013 | C34: 1300173 - 1300180-1308701 | D34: FAUNA DOMESTICA | H34: Mascota que ataca a persona | I34: Carlos Henry Echeverri Acevedo | J34: CL | K34: 32 | L34: B | M34: SUR | N34: 43 | O34: A | P34: 28 | T34: =CONCATENATE(J34," ",K34," ",L34," ",M34," ",N34," ",O34," ",P34," ",Q34," ",R34," ",S34) -> CL 32 B SUR 43 A 28 | U34: 71632450 | V34: 2766460 | W34: Familia Oquendo | X34: TR | Y34: 35 | Z34: B | AA34: SUR | AB34: 31 | AC34: A | AD34: 3 | AG34: PISO 1 | AH34: =CONCATENATE(X34," ",Y34," ",Z34," ",AA34," ",AB34," ",AC34," ",AD34," ",AE34," ",AF34," ",AG34) -> TR 35 B SUR 31 A 3 PISO 1 | AI34: no reporta | AJ34: no reporta | AK34: La Sebastiana | AP34: 3 | AQ34: 41296 | AR34: 41302 | AS34: =+AR34-AQ34 -> 6 | AT34: Codigo de Policia | AU34: Auto de archivo | AV34: 41276 | AW34: santiago | AX34: 41447 | BO34: 41302 | BP34: 41303 | BU34: 41310 | BV34: 41317 | BY34: 41655 | BZ34: 41659 | CE34: 41928
B35: 032-2013 | C35: 1300175 | D35: FAUNA DOMESTICA | H35: Perro pitbull que ataca y muerde a dos personas en Gualandayes | I35: Anonimo | T35: =CONCATENATE(J35," ",K35," ",L35," ",M35," ",N35," ",O35," ",P35," ",Q35," ",R35," ",S35) | U35: no reporta | V35: no reporta | W35: Por determinar | AF35: 2.3 | AG35: 103 | AH35: =CONCATENATE(X35," ",Y35," ",Z35," ",AA35," ",AB35," ",AC35," ",AD35," ",AE35," ",AF35," ",AG35) -> 2,3 103 | AI35: no reporta | AJ35: no reporta | AK35: El Dorado | AP35: 7 | AQ35: 41296 | AR35: 41312 | AS35: =+AR35-AQ35 -> 16 | AT35: Codigo de Policia | AU35: Auto de archivo
B36: 033-2013 | C36: 1300156 | D36: FLORA | H36: Arboles en predio privado que taponan desagues | I36: Elvia Gonzales | J36: CL | K36: 49 | L36: D | M36: SUR | N36: 40 | O36: A | P36: 262 | T36: =CONCATENATE(J36," ",K36," ",L36," ",M36," ",N36," ",O36," ",P36," ",Q36," ",R36," ",S36) -> CL 49 D SUR 40 A 262 | U36: 32517990 | V36: 5992539 | W36: Teresita Angel | X36: CL | Y36: 49 | Z36: D | AA36: SUR | AB36: 40 | AC36: A | AD36: 250 | AH36: =CONCATENATE(X36," ",Y36," ",Z36," ",AA36," ",AB36," ",AC36," ",AD36," ",AE36," ",AF36," ",AG36) -> CL 49 D SUR 40 A 250 | AI36: no reporta | AJ36: no reporta | AK36: Loma del Barro | AP36: 7 | AQ36: 41295 | AR36: 41324 | AS36: =+AR36-AQ36 -> 29 | AT36: Acta de Compromiso | AU36: Auto de archivo
B37: 034-2013 | C37: 1300162 - 134124 - 134125 (Mismo 849-2013) | D37: HIDRICO | H37: Descarga de sedimentos en la quebrada Las Brujas | I37: Comunidad | T37: =CONCATENATE(J37," ",K37," ",L37," ",M37," ",N37," ",O37," ",P37," ",Q37," ",R37," ",S37) | U37: no reporta | V37: no reporta | W37: Construgen -Atalaya de San Jorge | X37: CL | Y37: 37 | Z37: B | AA37: SUR | AB37: 27 | AC37: B | AD37: 81 | AH37: =CONCATENATE(X37," ",Y37," ",Z37," ",AA37," ",AB37," ",AC37," ",AD37," ",AE37," ",AF37," ",AG37) -> CL 37 B SUR 27 B 81 | AI37: no reporta | AJ37: 5116199- 3336236 | AK37: Loma de las Brujas | AP37: 5 | AQ37: 41295 | AR37: 41310 | AS37: =+AR37-AQ37 -> 15 | AT37: Acta de Compromiso | AU37: Auto de archivo
B38: 035-2013 | C38: 1300177 | D38: - | E38: RESIDUOS SOLIDOS | H38: Disposición inadecuada de residuos sólidos | I38: Comunidad | T38: =CONCATENATE(J38," ",K38," ",L38," ",M38," ",N38," ",O38," ",P38," ",Q38," ",R38," ",S38) | U38: no reporta | V38: no reporta | W38: Camilo - Johana | X38: TR | Y38: 34 | Z38: C | AA38: SUR | AB38: 32 | AC38: D | AD38: 28 | AG38: 302 | AH38: =CONCATENATE(X38," ",Y38," ",Z38," ",AA38," ",AB38," ",AC38," ",AD38," ",AE38," ",AF38," ",AG38) -> TR 34 C SUR 32 D 28 302 | AI38: no reporta | AJ38: no reporta | AK38: Obrero | AP38: 9 | AQ38: 41296 | AR38: 41312 | AS38: =+AR38-AQ38 -> 16 | AT38: Acta de Compromiso | AU38: Verificación
B39: 036-2013 | C39: 1300184 | D39: FAUNA DOMESTICA | H39: Maltrato animal, se remite a fauna para valoración | I39: Anonimo | T39: =CONCATENATE(J39," ",K39," ",L39," ",M39," ",N39," ",O39," ",P39," ",Q39," ",R39," ",S39) | U39: no reporta | V39: 2623767 | W39: Miguel Angel Montoya | X39: CL | Y39: 49 | Z39: D | AA39: SUR | AB39: 40 | AC39: A | AD39: 332 | AG39: 102 | AH39: =CONCATENATE(X39," ",Y39," ",Z39," ",AA39," ",AB39," ",AC39," ",AD39," ",AE39," ",AF39," ",AG39) -> CL 49 D SUR 40 A 332 102 | AI39: no reporta | AJ39: no reporta | AK39: Loma del Barro | AP39: 7 | AQ39: 41297 | AR39: 41309 | AS39: =+AR39-AQ39 -> 12 | AT39: Maltrato Animal | AU39: Verificación
B40: 037-2013 | C40: 1300190 - 134994 - 135710 | D40: - | E40: RESIDUO ESPECIAL | H40: Disposición inadecuada de residuos de pinturas | I40: Comunidad | T40: =CONCATENATE(J40," ",K40," ",L40," ",M40," ",N40," ",O40," ",P40," ",Q40," ",R40," ",S40) | U40: no reporta | V40: no reporta | W40: Carlos Mario Ramírez | X40: DG | Y40: 31 | Z40: C | AB40: 34 | AC40: EE | AD40: 24 | AE40: SUR | AH40: =CONCATENATE(X40," ",Y40," ",Z40," ",AA40," ",AB40," ",AC40," ",AD40," ",AE40," ",AF40," ",AG40) -> DG 31 C 34 EE 24 SUR | AI40: no reporta | AJ40: no reporta | AK40: Uribe Angel | AP40: 3 | AQ40: 41297 | AR40: 41312 | AS40: =+AR40-AQ40 -> 15 | AT40: Acuerdo 020 de 2009 | AU40: Auto de archivo | AV40: 41312 | AW40: C. Rojas - J. Restrepo | AX40: 41312 | CE40: 41484
B41: 038-2013 | C41: 1300185 | D41: FAUNA DOMESTICA | H41: Manejo inadecuado de excrementos de mascotas | I41: Angela Moncada | J41: TR | K41: 36 | L41: A | M41: SUR | N41: 29 | P41: 96 | T41: =CONCATENATE(J41," ",K41," ",L41," ",M41," ",N41," ",O41," ",P41," ",Q41," ",R41," ",S41) -> TR 36 A SUR 29 96 | U41: 43721215 | V41: 2760770 | W41: Comunidad | X41: TR | Y41: 36 | Z41: A | AA41: SUR | AB41: 29 | AH41: =CONCATENATE(X41," ",Y41," ",Z41," ",AA41," ",AB41," ",AC41," ",AD41," ",AE41," ",AF41," ",AG41) -> TR 36 A SUR 29 | AI41: no reporta | AJ41: no reporta | AK41: La Sebastiana | AP41: 3 | AQ41: 41297 | AR41: 41312 | AS41: =+AR41-AQ41 -> 15 | AT41: Acuerdo 020 de 2009 | AU41: Auto de archivo | AV41: 41312 | AW41: C. Rojas - J. Restrepo | AX41: 41312 | CE41: 41311 | CF41: 41311
A42: 1309377-2014 (111899) | B42: 039-2013 | C42: 1300201 - 1309194 (2014) | D42: - | E42: ESCOMBROS | H42: Disposicion inadecuada de escombros | I42: Comunidad | T42: =CONCATENATE(J42," ",K42," ",L42," ",M42," ",N42," ",O42," ",P42," ",Q42," ",R42," ",S42) | U42: no reporta | V42: no reporta | W42: Viviana Arboleda | X42: KR | Y42: 32 | AB42: 41 | AC42: AA | AD42: 14 | AE42: SUR | AF42: 3.3 | AG42: 301 | AH42: =CONCATENATE(X42," ",Y42," ",Z42," ",AA42," ",AB42," ",AC42," ",AD42," ",AE42," ",AF42," ",AG42) -> KR 32 41 AA 14 SUR 3,3 301 | AI42: no reporta | AJ42: 3326353 | AK42: El Dorado | AP42: 9 | AQ42: 41298 | AR42: 41298 | AS42: =+AR42-AQ42 -> 0 | AT42: Acuerdo 020 de 2009 | AU42: Auto de archivo | AV42: 41298 | AW42: F. Villarraga | AX42: 41298 | BM42: 41298 | BN42: 41319 | BO42: 41319 | BP42: 41319 | BS42: 41446 | CE42: 42020
B43: 040-2013 | C43: 1300199 - 1300398 | D43: - | E43: ESCOMBROS | H43: Disposicion inadecuada de escombros | I43: De Oficio | T43: =CONCATENATE(J43," ",K43," ",L43," ",M43," ",N43," ",O43," ",P43," ",Q43," ",R43," ",S43) | U43: no reporta | V43: no reporta | W43: Ester Enid Garcia M | X43: CL | Y43: 39 | Z43: F | AA43: SUR | AB43: 24 | AC43: DD | AD43: 13 | AG43: 101 | AH43: =CONCATENATE(X43," ",Y43," ",Z43," ",AA43," ",AB43," ",AC43," ",AD43," ",AE43," ",AF43," ",AG43) -> CL 39 F SUR 24 DD 13 101 | AI43: 42878319 | AJ43: no reporta | AK43: El Salado | AP43: 6 | AQ43: 41298 | AR43: 41313 | AS43: =+AR43-AQ43 -> 15 | AT43: Acuerdo 020 de 2009 | AU43: Auto de archivo
B44: 041-2013 | C44: 1300210 | D44: AIRE | H44: Olores a quimicos por empresa Metro Cubico | I44: Romulo Calle | J44: TR | K44: 35 | L44: C | M44: SUR | N44: 33 | P44: 60 | T44: =CONCATENATE(J44," ",K44," ",L44," ",M44," ",N44," ",O44," ",P44," ",Q44," ",R44," ",S44) -> TR 35 C SUR 33 60 | U44: 70568083 | V44: no reporta | W44: Metro Cubico | X44: TR | Y44: 35 | Z44: C | AA44: SUR | AB44: 33 | AD44: 50 | AH44: =CONCATENATE(X44," ",Y44," ",Z44," ",AA44," ",AB44," ",AC44," ",AD44," ",AE44," ",AF44," ",AG44) -> TR 35 C SUR 33 50 | AI44: no reporta | AJ44: 2701365 | AK44: Los Naranjos | AP44: 9 | AQ44: 41299 | AR44: 41313 | AS44: =+AR44-AQ44 -> 14 | AT44: Acta de Compromiso | AU44: Auto de archivo
B45: 042-2013 | C45: 1300195 - 1300844 - 6265 - 6494 - 1302169 | D45: HIDRICO | H45: Aguas lluvias sin manejo | I45: Bernardo Arango | J45: KR | K45: 27 | L45: D | N45: 34 | O45: DD | P45: 105 | Q45: SUR | T45: =CONCATENATE(J45," ",K45," ",L45," ",M45," ",N45," ",O45," ",P45," ",Q45," ",R45," ",S45) -> KR 27 D 34 DD 105 SUR | U45: no reporta | V45: 3360706 | W45: Urbanización Molino de Piedra | X45: CL | Y45: 36 | AA45: SUR | AB45: 27 | AC45: D | AD45: 50 | AH45: =CONCATENATE(X45," ",Y45," ",Z45," ",AA45," ",AB45," ",AC45," ",AD45," ",AE45," ",AF45," ",AG45) -> CL 36 SUR 27 D 50 | AI45: no reporta | AJ45: 3362877 | AK45: Inmaculada | AP45: 5 | AQ45: 41299 | AR45: 41334 | AS45: =+AR45-AQ45 -> 35 | AT45: Acta de Compromiso | AU45: Auto de archivo | BK45: 41334 | BL45: 41339 | CE45: 41416
B46: 043-2013 | C46: 1300212 | D46: ESPACIOS PUBLICOS VERDES | E46: RESIDUOS SOLIDOS | H46: Manejo inadecuado de residuos solidos | I46: Olga Cecilia Ramirez | J46: KR | K46: 39 | L46: E | N46: 45 | O46: C | P46: 58 | Q46: SUR | T46: =CONCATENATE(J46," ",K46," ",L46," ",M46," ",N46," ",O46," ",P46," ",Q46," ",R46," ",S46) -> KR 39 E 45 C 58 SUR | U46: 32329677 | V46: 2706295 | W46: Comunidad | X46: KR | Y46: 39 | Z46: E | AB46: 45 | AC46: C | AE46: SUR | AH46: =CONCATENATE(X46," ",Y46," ",Z46," ",AA46," ",AB46," ",AC46," ",AD46," ",AE46," ",AF46," ",AG46) -> KR 39 E 45 C SUR | AI46: no reporta | AJ46: no reporta | AK46: La Paz | AP46: 7 | AQ46: 41299 | AR46: 41313 | AS46: =+AR46-AQ46 -> 14 | AT46: Acta de Compromiso | AU46: Auto de archivo | AV46: 41313 | AW46: C. Rojas - J. Restrepo | AX46: 41313 | CE46: 41313
B47: 044-2013 | C47: 1300224 | D47: FLORA | H47: Tala de San Joaquin sin autorización | I47: Adolfo Rene Cano Mesa | J47: KR | K47: 24 | L47: C | N47: 41 | Q47: SUR | S47: 161 | T47: =CONCATENATE(J47," ",K47," ",L47," ",M47," ",N47," ",O47," ",P47," ",Q47," ",R47," ",S47) -> KR 24 C 41 SUR 161 | U47: 70561611 | V47: 3148520023 | W47: Dorian | AG47: lote 3 | AH47: =CONCATENATE(X47," ",Y47," ",Z47," ",AA47," ",AB47," ",AC47," ",AD47," ",AE47," ",AF47," ",AG47) -> lote 3 | AI47: no reporta | AJ47: no reporta | AK47: San Rafael | AP47: 6 | AQ47: 41302 | AS47: =+AR47-AQ47 -> -41302 | AT47: Acta de Compromiso | AU47: Citaciones
B48: 045-2013 | C48: 1300249 | D48: ESPACIOS PUBLICOS VERDES | E48: ESCOMBROS | G48: lote municipio | H48: Escombros arrojado en lote del Municipio | I48: Comunidad | T48: =CONCATENATE(J48," ",K48," ",L48," ",M48," ",N48," ",O48," ",P48," ",Q48," ",R48," ",S48) | U48: no reporta | V48: no reporta | W48: Por determinar | X48: CL | Y48: 41 | Z48: B | AA48: SUR | AB48: 24 | AC48: DD | AD48: 9 | AH48: =CONCATENATE(X48," ",Y48," ",Z48," ",AA48," ",AB48," ",AC48," ",AD48," ",AE48," ",AF48," ",AG48) -> CL 41 B SUR 24 DD 9 | AI48: no reporta | AJ48: no reporta | AK48: San Rafael | AP48: 6 | AQ48: 41303 | AR48: 41313 | AS48: =+AR48-AQ48 -> 10 | AT48: Acta de Compromiso | AU48: Auto de archivo | BS48: 41446
B49: 046-2013 | C49: 1300265 | D49: AIRE | H49: quema de materiales que generan afectacion en el sector. | I49: Maria Clara Warren | J49: KR | K49: 27 | N49: 23 | P49: 195 | Q49: SUR | T49: =CONCATENATE(J49," ",K49," ",L49," ",M49," ",N49," ",O49," ",P49," ",Q49," ",R49," ",S49) -> KR 27 23 195 SUR | U49: 42897897 | V49: 3360103 | W49: Maria Elena Botero Pineda | X49: CL | Y49: 23 | AA49: SUR | AB49: 25 | AC49: B | AD49: 9 | AG49: 107 | AH49: =CONCATENATE(X49," ",Y49," ",Z49," ",AA49," ",AB49," ",AC49," ",AD49," ",AE49," ",AF49," ",AG49) -> CL 23 SUR 25 B 9 107 | AI49: 42986060 | AJ49: 2652504 | AK49: Loma El Atravezado | AM49: 032 | AN49: 008 | AO49: 00017 | AP49: 4 | AQ49: 41304 | AR49: 41306 | AS49: =+AR49-AQ49 -> 2 | AT49: Acta de Compromiso | AU49: Verificación
B50: 047-2013 | C50: 1300269 | D50: FAUNA DOMESTICA | H50: Animales domesticos que dañan sembrados | I50: Jorge Enrique Restrepo | T50: =CONCATENATE(J50," ",K50," ",L50," ",M50," ",N50," ",O50," ",P50," ",Q50," ",R50," ",S50) | U50: 8303852 | V50: 3361176 | W50: Maria Angela Restrepo | X50: KR | Y50: 20 | AB50: 25 | AD50: 184 | AE50: SUR | AH50: =CONCATENATE(X50," ",Y50," ",Z50," ",AA50," ",AB50," ",AC50," ",AD50," ",AE50," ",AF50," ",AG50) -> KR 20 25 184 SUR | AI50: no reporta | AJ50: 3361192 | AK50: Loma El Atravezado | AP50: 4 | AQ50: 41304 | AR50: 41316 | AS50: =+AR50-AQ50 -> 12 | AT50: Acta de Compromiso | AU50: Auto de archivo
B51: 048-2013 | C51: 1300284 | D51: FLORA | H51: Daño de ramas de arboles por frutos sector camino verde | I51: Anonimo | T51: =CONCATENATE(J51," ",K51," ",L51," ",M51," ",N51," ",O51," ",P51," ",Q51," ",R51," ",S51) | U51: no reporta | V51: no reporta | W51: Por determinar | AH51: =CONCATENATE(X51," ",Y51," ",Z51," ",AA51," ",AB51," ",AC51," ",AD51," ",AE51," ",AF51," ",AG51) | AI51: no reporta | AJ51: no reporta | AK51: San Jose | AP51: 6 | AQ51: 41305 | AR51: 41313 | AS51: =+AR51-AQ51 -> 8 | AT51: Acta de Compromiso | AU51: Auto de archivo
B52: 049-2013 | C52: 1300300 | D52: FAUNA DOMESTICA | H52: Ataque de una mascota a otra | I52: Leidy Paola Bedoya | J52: CL | K52: 40 | L52: A | M52: SUR | N52: 25 | P52: 81 | T52: =CONCATENATE(J52," ",K52," ",L52," ",M52," ",N52," ",O52," ",P52," ",Q52," ",R52," ",S52) -> CL 40 A SUR 25 81 | U52: 1037616486 | V52: 2766730 | W52: Claudia Patricia Martinez | X52: CL | Y52: 40 | Z52: A | AA52: SUR | AB52: 25 | AD52: 63 | AG52: 201 | AH52: =CONCATENATE(X52," ",Y52," ",Z52," ",AA52," ",AB52," ",AC52," ",AD52," ",AE52," ",AF52," ",AG52) -> CL 40 A SUR 25 63 201 | AI52: no reporta | AJ52: no reporta | AK52: La Mina | AP52: 6 | AQ52: 41306 | AR52: 41313 | AS52: =+AR52-AQ52 -> 7 | AT52: Codigo de Policia | AU52: Auto de archivo | BM52: 41306 | BN52: 41320 | BO52: 41323 | BP52: 41323 | BS52: 41513 | BT52: 41516 | BW52: 41522 | CE52: 41541
B53: 050-2013 | C53: 1300301 | D53: AIRE | E53: RESIDUOS SOLIDOS | F53: 10 | H53: quema de residuos solidos (material vegetal) | I53: De Oficio | T53: =CONCATENATE(J53," ",K53," ",L53," ",M53," ",N53," ",O53," ",P53," ",Q53," ",R53," ",S53) | U53: no reporta | V53: no reporta | W53: Sergio Uribe Arango | X53: CL | Y53: 36 | Z53: D | AA53: SUR | AB53: 24 | AD53: 57 | AG53: 118 | AH53: =CONCATENATE(X53," ",Y53," ",Z53," ",AA53," ",AB53," ",AC53," ",AD53," ",AE53," ",AF53," ",AG53) -> CL 36 D SUR 24 57 118 | AI53: 8252117 | AJ53: 3360500 | AL53: El Escobero | AN53: 002 | AO53: 00281 | AP53: 10 | AQ53: 41306 | AR53: 41306 | AS53: =+AR53-AQ53 -> 0 | AT53: Acuerdo 020 de 2009 | AU53: Fallos -
B54: 051-2013 | C54: 1300302 | D54: FLORA | H54: Movimiento de tierra en lote, intervención de arboles, quema de material vegetal | I54: De Oficio | T54: =CONCATENATE(J54," ",K54," ",L54," ",M54," ",N54," ",O54," ",P54," ",Q54," ",R54," ",S54) | U54: no reporta | V54: no reporta | W54: Juan David | X54: KR | Y54: 23 | AB54: 36 | AC54: C | AD54: 135 | AE54: SUR | AH54: =CONCATENATE(X54," ",Y54," ",Z54," ",AA54," ",AB54," ",AC54," ",AD54," ",AE54," ",AF54," ",AG54) -> KR 23 36 C 135 SUR | AI54: no reporta | AJ54: no reporta | AL54: El Escobero | AN54: 002 | AO54: 00302 | AP54: 10 | AQ54: 41306 | AR54: 41306 | AS54: =+AR54-AQ54 -> 0 | AT54: Acta de Compromiso | AU54: Auto de archivo
B55: 052-2013 | C55: 1300310 | D55: - | E55: ESCOMBROS | H55: Disposicion inadecuada de escombros | I55: Alvaro Buritica | J55: KR | K55: 47 | L55: A | N55: 39 | P55: 79 | Q55: SUR | T55: =CONCATENATE(J55," ",K55," ",L55," ",M55," ",N55," ",O55," ",P55," ",Q55," ",R55," ",S55) -> KR 47 A 39 79 SUR | U55: 70553261 | V55: 2763916 | W55: Carlos Gomez | X55: KR | Y55: 47 | Z55: A | AB55: 39 | AD55: 67 | AE55: SUR | AH55: =CONCATENATE(X55," ",Y55," ",Z55," ",AA55," ",AB55," ",AC55," ",AD55," ",AE55," ",AF55," ",AG55) -> KR 47 A 39 67 SUR | AI55: no reporta | AJ55: no reporta | AK55: Alcala | AP55: 8 | AQ55: 41309 | AR55: 41320 | AS55: =+AR55-AQ55 -> 11 | AT55: Acta de Compromiso | AU55: Auto de archivo
B56: 053-2013 | C56: 104506 - 1304665 - 131449 - (Informe 3550) | D56: HIDRICO | H56: Movimiento de tierra que afecta flora, suelo y corrientes de agua y nacimiento | I56: Andrei Amayan | T56: =CONCATENATE(J56," ",K56," ",L56," ",M56," ",N56," ",O56," ",P56," ",Q56," ",R56," ",S56) | U56: 98700834 | V56: 2132321 | W56: Fray Ricardo Gonzalez Vallesteros - Ana Maria Muñoz Tavera - William Grisales Herrera y otros | X56: CL | Y56: 27 | AB56: 8 | AC56: A | AD56: 85 | AG56: predio 267 | AI56: no reporta | AJ56: 3146573437 | AL56: Pantanillo | AN56: 005 | AO56: 00267 | AP56: 13 | AQ56: 41305 | AR56: 41312 | AS56: =+AR56-AQ56 -> 7 | AT56: Ley 1333 de 2009 | AU56: Remisiones Corantioquia | AV56: 41312 | AW56: L. Taborda | AX56: 41318 | AY56: 41499 | AZ56: J. Guzman - F. Villarraga | BA56: 41506 | BU56: 41578 | BV56: 41578 | CE56: 41583
A57: Oficio 13-2735 IT 13-2736 | B57: 054-2013 | C57: 4257-2012 | D57: HIDRICO | H57: Ocupacion de cauce en quebrada La Zuñiga sin legalizar | I57: Autoridad Ambiental | T57: =CONCATENATE(J57," ",K57," ",L57," ",M57," ",N57," ",O57," ",P57," ",Q57," ",R57," ",S57) | U57: no reporta | V57: no reporta | W57: Mont Juic - Oswaldo Gomez Sierra | X57: CL | Y57: 23 | AA57: SUR | AB57: 25 | AC57: B | AD57: 114 | AH57: =CONCATENATE(X57," ",Y57," ",Z57," ",AA57," ",AB57," ",AC57," ",AD57," ",AE57," ",AF57," ",AG57) -> CL 23 SUR 25 B 114 | AI57: no reporta | AJ57: no reporta | AK57: Zuñiga | AM57: 033 | AN57: 003 | AO57: 00035 | AP57: 4 | AQ57: 41305 | AR57: 41320 | AS57: =+AR57-AQ57 -> 15 | AT57: Acta de Compromiso | AU57: Auto de archivo
B58: 055-2013 | C58: 19 - (0003770) | D58: HIDRICO | H58: Infraccion sobre zona de retiro quebrada Las Brujas | I58: Autoridad Ambiental | T58: =CONCATENATE(J58," ",K58," ",L58," ",M58," ",N58," ",O58," ",P58," ",Q58," ",R58," ",S58) | U58: no reporta | V58: no reporta | W58: Clara Monica Garcia Restrepo | X58: CL | Y58: 37 | Z58: B | AA58: SUR | AB58: 27 | AC58: A | AD58: 45 | AF58: ramal 6 | AG58: 103 | AH58: =CONCATENATE(X58," ",Y58," ",Z58," ",AA58," ",AB58," ",AC58," ",AD58," ",AE58," ",AF58," ",AG58) -> CL 37 B SUR 27 A 45 ramal 6 103 | AI58: no reporta | AJ58: 3024500 | AK58: Loma de las Brujas | AP58: 5 | AQ58: 41311 | AS58: =+AR58-AQ58 -> -41311 | AT58: Acta de Compromiso | AU58: Auto de archivo | BU58: 41323 | BV58: 41324 | CE58: 41347
B59: 056-2013 | C59: I.T 050 - AA 040 | D59: HIDRICO | H59: Requerimientos para legalizar Ocupación de Cauce | I59: Autoridad Ambiental | T59: =CONCATENATE(J59," ",K59," ",L59," ",M59," ",N59," ",O59," ",P59," ",Q59," ",R59," ",S59) | U59: no reporta | V59: no reporta | W59: Juan Vicente Izasa Ocampo | X59: CL | Y59: 23 | AA59: SUR | AB59: 42 | AC59: B | AD59: 86 | AH59: =CONCATENATE(X59," ",Y59," ",Z59," ",AA59," ",AB59," ",AC59," ",AD59," ",AE59," ",AF59," ",AG59) -> CL 23 SUR 42 B 86 | AI59: no reporta | AJ59: 2705101 | AK59: Las Orquideas | AP59: 3 | AQ59: 41311 | AS59: =+AR59-AQ59 -> -41311 | AT59: Acta de Compromiso | AU59: Auto de archivo
B60: 057-2013 | C60: 104866 | D60: - | E60: ESCOMBROS | G60: LOTE SIN CERRAMIENTO | H60: Lote sin cerramiento donde acumulan escombros y residuos sólidos. | I60: Metroplus | J60: CL | K60: 53 | N60: 45 | P60: 77 | S60: piso 3 | T60: =CONCATENATE(J60," ",K60," ",L60," ",M60," ",N60," ",O60," ",P60," ",Q60," ",R60," ",S60) -> CL 53 45 77 piso 3 | U60: no reporta | V60: 5763730 | W60: Por determinar | X60: CL | Y60: 46 | Z60: A | AA60: SUR | AB60: 43 | AC60: A | AH60: =CONCATENATE(X60," ",Y60," ",Z60," ",AA60," ",AB60," ",AC60," ",AD60," ",AE60," ",AF60," ",AG60) -> CL 46 A SUR 43 A | AI60: no reporta | AJ60: no reporta | AK60: Primavera | AP60: 8 | AQ60: 41309 | AR60: 41320 | AS60: =+AR60-AQ60 -> 11 | AT60: Codigo de Policia | AU60: Auto de archivo
B61: 058-2013 | C61: 1300280 - 1301733 | D61: - | E61: MATERIAL DE CONTRUCCIÓN | F61: 9 | H61: Material de construcción en espacio público | I61: Comunidad | T61: =CONCATENATE(J61," ",K61," ",L61," ",M61," ",N61," ",O61," ",P61," ",Q61," ",R61," ",S61) | U61: no reporta | V61: no reporta | W61: Carlos Albeiro Cadavid Veles y otros | X61: KR | Y61: 42 | Z61: A | AB61: 40 | AC61: H | AD61: 74 | AE61: SUR | AH61: =CONCATENATE(X61," ",Y61," ",Z61," ",AA61," ",AB61," ",AC61," ",AD61," ",AE61," ",AF61," ",AG61) -> KR 42 A 40 H 74 SUR | AI61: 70563579 | AJ61: 3793876 | AK61: El Dorado | AP61: 7 | AQ61: 41312 | AR61: 41312 | AS61: =+AR61-AQ61 -> 0 | AT61: Acuerdo 020 de 2009 | AU61: Auto de archivo | AV61: 41312 | AW61: F. Villarraga | AX61: 41312 | BM61: 41317 | BN61: 41320 | BO61: 41323 | BP61: 41323 | BQ61: 41333 | BR61: 41333 | BS61: 41333 | BT61: 41373 | BU61: 41373 | BV61: 41376 | BW61: 41389 | BX61: 41400 | BY61: 41400 | BZ61: 41403
B62: 059-2013 | C62: 1300341 | D62: HIDRICO | H62: Descarga de aguas residuales a la quebrada La Sebastiana | I62: De Oficio | T62: =CONCATENATE(J62," ",K62," ",L62," ",M62," ",N62," ",O62," ",P62," ",Q62," ",R62," ",S62) | U62: no reporta | V62: no reporta | W62: Por determinar | X62: KR | Y62: 27 | AB62: 36 | AC62: AA | AE62: SUR | AH62: =CONCATENATE(X62," ",Y62," ",Z62," ",AA62," ",AB62," ",AC62," ",AD62," ",AE62," ",AF62," ",AG62) -> KR 27 36 AA SUR | AI62: no reporta | AJ62: no reporta | AK62: El Chocho | AP62: 5 | AQ62: 41311 | AR62: 41313 | AS62: =+AR62-AQ62 -> 2 | AT62: Acta de Compromiso | AU62: Auto de archivo | AV62: 41400 | AW62: J. Guzman | AX62: 41400 | CE62: 41703
B63: 060-2013 | C63: 1300348 | D63: - | E63: ESCOMBROS | H63: Manejo inadecuado de residuos de construcción | I63: Comunidad | T63: =CONCATENATE(J63," ",K63," ",L63," ",M63," ",N63," ",O63," ",P63," ",Q63," ",R63," ",S63) | U63: no reporta | V63: no reporta | W63: Carlos Gomez | X63: KR | Y63: 47 | Z63: A | AB63: 39 | AD63: 67 | AE63: SUR | AH63: =CONCATENATE(X63," ",Y63," ",Z63," ",AA63," ",AB63," ",AC63," ",AD63," ",AE63," ",AF63," ",AG63) -> KR 47 A 39 67 SUR | AI63: no reporta | AJ63: no reporta | AK63: Alcala | AP63: 8 | AQ63: 41311 | AR63: 41341 | AS63: =+AR63-AQ63 -> 30 | AT63: Acta de Compromiso | AU63: Auto de archivo
B64: 061-2013 | C64: 1300349 | D64: FLORA | H64: Daño de arboles en predio privado | I64: Magnolia Arango | J64: CL | K64: 27 | M64: SUR | N64: 45 | P64: 40 | T64: =CONCATENATE(J64," ",K64," ",L64," ",M64," ",N64," ",O64," ",P64," ",Q64," ",R64," ",S64) -> CL 27 SUR 45 40 | U64: 42978378 | V64: 2708830 | W64: Museo Otra Parte | AH64: =CONCATENATE(X64," ",Y64," ",Z64," ",AA64," ",AB64," ",AC64," ",AD64," ",AE64," ",AF64," ",AG64) | AI64: no reporta | AJ64: no reporta | AK64: Jardines | AP64: 2 | AQ64: 41311 | AR64: 41325 | AS64: =+AR64-AQ64 -> 14 | AT64: Acta de Compromiso | AU64: Auto de archivo
B65: 062-2013 | C65: 1300354 | D65: ESPACIOS PUBLICOS VERDES | E65: ESCOMBROS | H65: Disposicion inadecuada de escombros | I65: De Oficio | T65: =CONCATENATE(J65," ",K65," ",L65," ",M65," ",N65," ",O65," ",P65," ",Q65," ",R65," ",S65) | U65: no reporta | V65: no reporta | W65: Greys Mejia | X65: CL | Y65: 39 | Z65: B | AA65: SUR | AB65: 29 | AH65: =CONCATENATE(X65," ",Y65," ",Z65," ",AA65," ",AB65," ",AC65," ",AD65," ",AE65," ",AF65," ",AG65) -> CL 39 B SUR 29 | AI65: no reporta | AJ65: no reporta | AK65: San Jose | AP65: 6 | AQ65: 41312 | AR65: 41317 | AS65: =+AR65-AQ65 -> 5 | AT65: Acta de Compromiso | AU65: Auto de archivo
B66: 063-2013 | C66: 1300369 | D66: - | E66: ESCOMBROS | G66: LOTE | H66: Disposicion inadecuada de escombros | I66: Carlos Cardona | J66: KR | K66: 27 | N66: 41 | O66: B | Q66: SUR | T66: =CONCATENATE(J66," ",K66," ",L66," ",M66," ",N66," ",O66," ",P66," ",Q66," ",R66," ",S66) -> KR 27 41 B SUR | U66: no reporta | V66: 2708967 | W66: Por determinar | X66: KR | Y66: 28 | AB66: 41 | AC66: AA | AD66: 11 | AE66: SUR | AH66: =CONCATENATE(X66," ",Y66," ",Z66," ",AA66," ",AB66," ",AC66," ",AD66," ",AE66," ",AF66," ",AG66) -> KR 28 41 AA 11 SUR | AI66: no reporta | AJ66: no reporta | AK66: San Rafael | AP66: 6 | AQ66: 41312 | AR66: 41317 | AS66: =+AR66-AQ66 -> 5 | AT66: Acta de Compromiso | AU66: Auto de archivo
B67: 064-2013 | C67: 1300370 | D67: FLORA | H67: Daño de arboles en predio del Municipio | I67: Joaquin Buitrago | T67: =CONCATENATE(J67," ",K67," ",L67," ",M67," ",N67," ",O67," ",P67," ",Q67," ",R67," ",S67) | U67: no reporta | V67: 5381038 | W67: Finca La lluvia | AH67: =CONCATENATE(X67," ",Y67," ",Z67," ",AA67," ",AB67," ",AC67," ",AD67," ",AE67," ",AF67," ",AG67) | AI67: no reporta | AJ67: no reporta | AL67: Pantanillo | AP67: 13 | AQ67: 41312 | AR67: 41437 | AS67: =+AR67-AQ67 -> 125 | AT67: Acta de Compromiso | AU67: Auto de archivo | AV67: 41437 | AW67: L. Taborda | AX67: 41437
B68: 065-2013 | C68: 1300353 | D68: FAUNA DOMESTICA | H68: Manejo inadecuado de perros peligrosos | I68: Anonimo | T68: =CONCATENATE(J68," ",K68," ",L68," ",M68," ",N68," ",O68," ",P68," ",Q68," ",R68," ",S68) | U68: no reporta | V68: no reporta | W68: Por determinar | X68: KR | Y68: 42 | Z68: D | AB68: 45 | AC68: B | AD68: 99 | AE68: SUR | AH68: =CONCATENATE(X68," ",Y68," ",Z68," ",AA68," ",AB68," ",AC68," ",AD68," ",AE68," ",AF68," ",AG68) -> KR 42 D 45 B 99 SUR | AI68: no reporta | AJ68: no reporta | AK68: La Paz | AP68: 7 | AQ68: 41312 | AR68: 41325 | AS68: =+AR68-AQ68 -> 13 | AT68: Codigo de Policia | AU68: Auto de archivo
A69: | | B69: 066-2013 | C69: 1300358 | D69: HIDRICO | H69: Movimiento de tierra que afecta corriente de agua | I69: De Oficio | T69: =CONCATENATE(J69," ",K69," ",L69," ",M69," ",N69," ",O69," ",P69," ",Q69," ",R69," ",S69) | U69: no reporta | V69: no reporta | W69: Parcelación Fuente Clara Londoño Gomez & CIA | X69: CL | Y69: 36 | AA69: SUR | AB69: 22 | AD69: 105 | AG69: 138 | AH69: =CONCATENATE(X69," ",Y69," ",Z69," ",AA69," ",AB69," ",AC69," ",AD69," ",AE69," ",AF69," ",AG69) -> CL 36 SUR 22 105 138 | AI69: no reporta | AJ69: 3361524 | AL69: Santa Catalina | AP69: 10 | AQ69: 41312 | AR69: 41312 | AS69: =+AR69-AQ69 -> 0 | AT69: Acta de Compromiso | AU69: Citaciones | AV69: 41319 | AW69: J. Guzman - L. Taborda | AX69: 41319 | AY69: 41480 | AZ69: L. Taborda | BA69: 41480 | BB69: 41564 | BC69: L. Taborda - C. Calle | BD69: 41565
B70: 067-2013 | C70: 1300371 | D70: - | E70: RESIDUOS SOLIDOS | H70: Disposición inadecuada de residuos sólidos | I70: Comunidad | T70: =CONCATENATE(J70," ",K70," ",L70," ",M70," ",N70," ",O70," ",P70," ",Q70," ",R70," ",S70) | U70: no reporta | V70: no reporta | W70: Angela Ortiz Marin | X70: DG | Y70: 30 | Z70: A | AB70: 35 | AD70: 31 | AE70: SUR | AG70: 301 | AH70: =CONCATENATE(X70," ",Y70," ",Z70," ",AA70," ",AB70," ",AC70," ",AD70," ",AE70," ",AF70," ",AG70) -> DG 30 A 35 31 SUR 301 | AI70: no reporta | AJ70: no reporta | AK70: La Sebastiana | AP70: 3 | AQ70: 41312 | AR70: 41326 | AS70: =+AR70-AQ70 -> 14 | AT70: Acta de Compromiso | AU70: Auto de archivo
B71: 068-2013 | C71: 1300372 - 1304354 | D71: ESPACIOS PUBLICOS VERDES | E71: ESCOMBROS | F71: 9 | H71: Comparendo #299 | I71: De Oficio | T71: =CONCATENATE(J71," ",K71," ",L71," ",M71," ",N71," ",O71," ",P71," ",Q71," ",R71," ",S71) | U71: no reporta | V71: no reporta | W71: Maria del Socorro Tejada Franco | X71: CL | Y71: 40 | Z71: DD | AA71: SUR | AB71: 41 | AC71: A | AD71: 17 | AH71: =CONCATENATE(X71," ",Y71," ",Z71," ",AA71," ",AB71," ",AC71," ",AD71," ",AE71," ",AF71," ",AG71) -> CL 40 DD SUR 41 A 17 | AI71: 3006093452 | AJ71: 32309238 | AK71: El Dorado | AP71: 7 | AQ71: 41312 | AS71: =+AR71-AQ71 -> -41312 | AT71: Acuerdo 020 de 2009 | AU71: Auto de archivo | BS71: 41446
B72: 069-2013 | C72: 1300390 - 1303045 | D72: FAUNA DOMESTICA | H72: Disposicion de animal en alcantarillado | I72: De Oficio | U72: no reporta | V72: no reporta | W72: Hamilton Zuleta | AH72: =CONCATENATE(X72," ",Y72," ",Z72," ",AA72," ",AB72," ",AC72," ",AD72," ",AE72," ",AF72," ",AG72) | AI72: no reporta | AJ72: 2882082 | AK72: Las Vegas | AP72: 1 | AQ72: 41316 | AR72: 41316 | AS72: =+AR72-AQ72 -> 0 | AT72: Codigo de Policia | AU72: Auto de archivo | AV72: 41313 | AW72: J. Guzman | AX72: 41313 | BM72: 41313 | BN72: 41375 | BO72: 41380 | BP72: 41380 | BS72: 41380 | BT72: 41422 | BU72: 41422 | BV72: 41437 | BW72: 41451 | BX72: 41521 | CE72: 41675
B73: 070-2013 ; 183-2012 | C73: 1300391 | D73: - | E73: RESIDUOS SOLIDOS | H73: Disposicion inadecuada de residuos solidos | I73: Comunidad | T73: =CONCATENATE(J73," ",K73," ",L73," ",M73," ",N73," ",O73," ",P73," ",Q73," ",R73," ",S73) | U73: no reporta | V73: no reporta | W73: Amparo Gonzalez | X73: DG | Y73: 32 | AB73: 36 | AD73: 5 | AE73: SUR | AH73: =CONCATENATE(X73," ",Y73," ",Z73," ",AA73," ",AB73," ",AC73," ",AD73," ",AE73," ",AF73," ",AG73) -> DG 32 36 5 SUR | AI73: no reporta | AJ73: no reporta | AK73: Los Naranjos | AP73: 9 | AQ73: 41316 | AR73: 41326 | AS73: =+AR73-AQ73 -> 10 | AT73: Acta de Compromiso | AU73: Auto de archivo | AV73: 41326 | AW73: J. Alvarez - L. Garcia | AX73: 41326 | AY73: 41460 | AZ73: J. Restrepo - S. Bustamente | BA73: 41460 | CE73: 41326
B74: 071-2013 | C74: 1300414 | D74: ESPACIOS PUBLICOS VERDES | E74: RESIDUO ESPECIAL | H74: Disposición inadecuada de tres colchones | I74: Fabiola Morales | J74: TR | K74: 34 | L74: B | M74: SUR | N74: 33 | P74: 12 | T74: =CONCATENATE(J74," ",K74," ",L74," ",M74," ",N74," ",O74," ",P74," ",Q74," ",R74," ",S74) -> TR 34 B SUR 33 12 | U74: 32376684 | V74: 2766697 | W74: Luis Carlos Bustamante | X74: TR | Y74: 34 | Z74: B | AA74: SUR | AB74: 33 | AD74: 7 | AH74: =CONCATENATE(X74," ",Y74," ",Z74," ",AA74," ",AB74," ",AC74," ",AD74," ",AE74," ",AF74," ",AG74) -> TR 34 B SUR 33 7 | AI74: no reporta | AJ74: no reporta | AK74: Obrero | AP74: 9 | AQ74: 41317 | AR74: 41326 | AS74: =+AR74-AQ74 -> 9 | AT74: Acta de Compromiso | AU74: Auto de archivo
B75: 072-2013 | C75: 1300117 | D75: FAUNA DOMESTICA | H75: Manejo inadecuado de pozo septico y gallinas | I75: Maria Edilma Munera | J75: CL | K75: 40 | L75: B | M75: SUR | N75: 27 | O75: B | P75: 50 | T75: =CONCATENATE(J75," ",K75," ",L75," ",M75," ",N75," ",O75," ",P75," ",Q75," ",R75," ",S75) -> CL 40 B SUR 27 B 50 | U75: 41596084 | V75: 2769983 | W75: Por determinar | X75: CL | Y75: 40 | AA75: SUR | AB75: 27 | AD75: 133 | AH75: =CONCATENATE(X75," ",Y75," ",Z75," ",AA75," ",AB75," ",AC75," ",AD75," ",AE75," ",AF75," ",AG75) -> CL 40 SUR 27 133 | AI75: no reporta | AJ75: no reporta | AK75: San Jose | AP75: 6 | AQ75: 41290 | AR75: 41298 | AS75: =+AR75-AQ75 -> 8 | AT75: Acta de Compromiso | AU75: Auto de archivo | AV75: 41330 | AW75: C. Rojas - J. Restrepo - S. Bustamante | AX75: 41330 | CE75: 41330
B76: 073-2013 | C76: 1300415 | D76: FAUNA DOMESTICA | H76: Ataque de mascota | I76: Diego Fernando Hernandez Hoyos | J76: DG | K76: 31 | L76: C | N76: 33 | O76: A | P76: 130 | Q76: SUR | R76: 4 | S76: 407 | T76: =CONCATENATE(J76," ",K76," ",L76," ",M76," ",N76," ",O76," ",P76," ",Q76," ",R76," ",S76) -> DG 31 C 33 A 130 SUR 4 407 | U76: 10014700 | V76: 2760786 | W76: Monica Laura Hernandez Marin | X76: DG | Y76: 31 | Z76: C | AB76: 33 | AC76: A | AD76: 130 | AE76: SUR | AF76: 13 | AG76: 125 | AH76: =CONCATENATE(X76," ",Y76," ",Z76," ",AA76," ",AB76," ",AC76," ",AD76," ",AE76," ",AF76," ",AG76) -> DG 31 C 33 A 130 SUR 13 125 | AI76: 43501575 | AJ76: no reporta | AK76: Las Flores | AP76: 3 | AQ76: 41317 | AS76: =+AR76-AQ76 -> -41317 | AT76: Codigo de Policia | AU76: Auto de archivo | BM76: 41317 | BN76: 41334 | BO76: 41426 | BP76: 41339 | BS76: 41339 | BT76: 41381 | BU76: 41381 | BV76: 41387 | CE76: 41410
B77: 074-2013 | C77: 1300402 | D77: FAUNA DOMESTICA | H77: Tenencia inadecuada de mascotas | I77: Aida Maria Rendon M. | J77: CL | K77: 39 | M77: SUR | N77: 25 | O77: B | P77: 130 | T77: =CONCATENATE(J77," ",K77," ",L77," ",M77," ",N77," ",O77," ",P77," ",Q77," ",R77," ",S77) -> CL 39 SUR 25 B 130 | V77: 3342376 | W77: Juan David Colorado | X77: CL | Y77: 39 | AA77: SUR | AB77: 25 | AC77: B | AD77: 130 | AH77: =CONCATENATE(X77," ",Y77," ",Z77," ",AA77," ",AB77," ",AC77," ",AD77," ",AE77," ",AF77," ",AG77) -> CL 39 SUR 25 B 130 | AI77: no reporta | AJ77: 3342376 | AK77: El Chingui | AM77: 001 | AN77: 007 | AO77: 00037 | AP77: 6 | AQ77: 41318 | AR77: 41330 | AS77: =+AR77-AQ77 -> 12 | AT77: Acta de Compromiso | AU77: Auto de archivo | CE77: 41507
A78: I.T 130060 122186-2014 | B78: 075-2013 | C78: 1300405 | D78: HIDRICO | H78: Contaminación de aguas por marraneras | I78: Juliana Alvarez | T78: =CONCATENATE(J78," ",K78," ",L78," ",M78," ",N78," ",O78," ",P78," ",Q78," ",R78," ",S78) | U78: no reporta | V78: 3002158202 | W78: Margarita Correa | X78: CL | Y78: 36 | AA78: SUR | AB78: 22 | AD78: 4 | AG78: 134 | AH78: =CONCATENATE(X78," ",Y78," ",Z78," ",AA78," ",AB78," ",AC78," ",AD78," ",AE78," ",AF78," ",AG78) -> CL 36 SUR 22 4 134 | AI78: no reporta | AJ78: no reporta | AL78: Santa Catalina | AO78: 00197 | AP78: 10 | AQ78: 41316 | AR78: 41319 | AS78: =+AR78-AQ78 -> 3 | AT78: Acta de Compromiso | AU78: Verificación | AV78: 41319 | AW78: L. Taborda | AX78: 41319 | AY78: 41325 | AZ78: C. Acevedo | BA78: 41330 | BK78: 41366 | BL78: 41372
B79: 076-2013 | C79: 1300407 | D79: ESPACIOS PUBLICOS VERDES | E79: RESIDUOS SOLIDOS | H79: Disposicion inadecuada de residuos solidos | I79: Comunidad | T79: =CONCATENATE(J79," ",K79," ",L79," ",M79," ",N79," ",O79," ",P79," ",Q79," ",R79," ",S79) | U79: no reporta | V79: no reporta | W79: Granero Perez | X79: KR | Y79: 37 | AB79: 38 | AC79: A | AD79: 43 | AE79: SUR | AH79: =CONCATENATE(X79," ",Y79," ",Z79," ",AA79," ",AB79," ",AC79," ",AD79," ",AE79," ",AF79," ",AG79) -> KR 37 38 A 43 SUR | AI79: no reporta | AJ79: no reporta | AK79: Mesa | AP79: 9 | AQ79: 41316 | AR79: 41324 | AS79: =+AR79-AQ79 -> 8 | AT79: Acta de Compromiso | AU79: Auto de archivo | AV79: 41324 | AW79: C. Rojas | AX79: 41324 | AY79: 41341 | CE79: 41432
B80: 077-2013 | C80: 1300413 | D80: - | E80: RESIDUOS SOLIDOS | H80: Disposicion inadecuada de tablillas y fieltro en lote | I80: Nohelia Ruiz | J80: KR | K80: 27 | L80: B | N80: 41 | O80: B | P80: 4 | Q80: SUR | S80: 210 | T80: =CONCATENATE(J80," ",K80," ",L80," ",M80," ",N80," ",O80," ",P80," ",Q80," ",R80," ",S80) -> KR 27 B 41 B 4 SUR 210 | U80: no reporta | V80: 3332374 | W80: Habitante dirección | X80: KR | Y80: 28 | AB80: 41 | AC80: B | AD80: 4 | AE80: SUR | AG80: 301 | AH80: =CONCATENATE(X80," ",Y80," ",Z80," ",AA80," ",AB80," ",AC80," ",AD80," ",AE80," ",AF80," ",AG80) -> KR 28 41 B 4 SUR 301 | AI80: no reporta | AJ80: no reporta | AK80: San Rafael | AP80: 6 | AQ80: 41316 | AR80: 41318 | AS80: =+AR80-AQ80 -> 2 | AT80: Acta de Compromiso | AU80: Auto de archivo
B81: 078-2013 | C81: 1300428 | D81: - | E81: ESCOMBROS | H81: Manejo inadecuado de escombros | I81: De Oficio | T81: =CONCATENATE(J81," ",K81," ",L81," ",M81," ",N81," ",O81," ",P81," ",Q81," ",R81," ",S81) | U81: no reporta | V81: no reporta | W81: Juan David Fonseca Salazar | X81: TR | Y81: 35 | Z81: D | AA81: SUR | AB81: 29 | AD81: 63 | AG81: 201 | AH81: =CONCATENATE(X81," ",Y81," ",Z81," ",AA81," ",AB81," ",AC81," ",AD81," ",AE81," ",AF81," ",AG81) -> TR 35 D SUR 29 63 201 | AI81: 8357644 | AJ81: 3319962 | AK81: La Sebastiana | AP81: 3 | AQ81: 41317 | AR81: 41318 | AS81: =+AR81-AQ81 -> 1 | AT81: Acta de Compromiso | AU81: Auto de archivo
B82: 079-2013 | C82: AA - 398 | D82: HIDRICO | H82: Requerimiento por construcción de efluente final de STARD | I82: Autoridad Ambiental | T82: =CONCATENATE(J82," ",K82," ",L82," ",M82," ",N82," ",O82," ",P82," ",Q82," ",R82," ",S82) | U82: no reporta | V82: no reporta | W82: Natalia Robles Isaza y Angela Maria Izasa de Robles | X82: CL | Y82: 1 | Z82: A | AA82: SUR | AB82: 31 | AD82: 105 | AH82: =CONCATENATE(X82," ",Y82," ",Z82," ",AA82," ",AB82," ",AC82," ",AD82," ",AE82," ",AF82," ",AG82) -> CL 1 A SUR 31 105 | AI82: 21954786 | AJ82: 2667234 | AL82: Pantanillo | AO82: 00020 | AP82: 13 | AQ82: 41318 | AS82: =+AR82-AQ82 -> -41318 | AT82: Acta de Compromiso | AU82: Citaciones
B83: 080-2013 | C83: AA - 515 | D83: HIDRICO | H83: Requerimiento por construcción de STARD | I83: Autoridad Ambiental | T83: =CONCATENATE(J83," ",K83," ",L83," ",M83," ",N83," ",O83," ",P83," ",Q83," ",R83," ",S83) | U83: no reporta | V83: no reporta | W83: Edgar Alonso Velasquez Toro | AH83: =CONCATENATE(X83," ",Y83," ",Z83," ",AA83," ",AB83," ",AC83," ",AD83," ",AE83," ",AF83," ",AG83) | AI83: 71587134 | AJ83: 4117928 | AL83: Santa Catalina | AO83: 00005 | AP83: 10 | AQ83: 41318 | AR83: 41367 | AS83: =+AR83-AQ83 -> 49 | AT83: Acta de Compromiso | AU83: Visitas técnicos | BK83: 41367 | BL83: 41367
B84: 081-2013 | C84: 1300429 | D84: - | E84: ESCOMBROS | H84: Disposición inadecuada de escombros | I84: Administración Milan 3 | J84: KR | K84: 46 | L84: A | N84: 42 | Q84: SUR | R84: 3 | T84: =CONCATENATE(J84," ",K84," ",L84," ",M84," ",N84," ",O84," ",P84," ",Q84," ",R84," ",S84) -> KR 46 A 42 SUR 3 | U84: no reporta | V84: 3329068 | W84: Por determinar | X84: KR | Y84: 46 | Z84: A | AB84: 42 | AD84: 75 | AE84: SUR | AH84: =CONCATENATE(X84," ",Y84," ",Z84," ",AA84," ",AB84," ",AC84," ",AD84," ",AE84," ",AF84," ",AG84) -> KR 46 A 42 75 SUR | AI84: no reporta | AJ84: no reporta | AK84: Milan Vallejuelos | AP84: 8 | AQ84: 41317 | AR84: 41327 | AS84: =+AR84-AQ84 -> 10 | AT84: Acta de Compromiso | AU84: Auto de archivo
B85: 082-2013 | C85: 1300435 - DP13011 - IT 130054 | D85: FLORA | H85: Posible tala de arboles de mas de 50 años | I85: Jairo Hernan Mejia | J85: CL | K85: 36 | M85: SUR | N85: 23 | P85: 68 | S85: 115 | T85: =CONCATENATE(J85," ",K85," ",L85," ",M85," ",N85," ",O85," ",P85," ",Q85," ",R85," ",S85) -> CL 36 SUR 23 68 115 | U85: 70091622 | V85: 3153692278 | W85: Ingenieria y Concreto | X85: CL | Y85: 36 | AA85: SUR | AB85: 23 | AD85: 68 | AH85: =CONCATENATE(X85," ",Y85," ",Z85," ",AA85," ",AB85," ",AC85," ",AD85," ",AE85," ",AF85," ",AG85) -> CL 36 SUR 23 68 | AI85: no reporta | AJ85: no reporta | AK85: Loma El Atravezado | AP85: 4 | AQ85: 41318 | AS85: =+AR85-AQ85 -> -41318 | AT85: Remision u otros | AU85: Auto de archivo
B86: 083-2013 | C86: 1300437 | D86: FLORA | H86: Poda de individuos vegetales sin autorización | I86: De Oficio | T86: =CONCATENATE(J86," ",K86," ",L86," ",M86," ",N86," ",O86," ",P86," ",Q86," ",R86," ",S86) | U86: no reporta | V86: no reporta | W86: Doris Cardenas | X86: KR | Y86: 29 | Z86: C | AB86: 40 | AC86: E | AD86: 53 | AE86: SUR | AH86: =CONCATENATE(X86," ",Y86," ",Z86," ",AA86," ",AB86," ",AC86," ",AD86," ",AE86," ",AF86," ",AG86) -> KR 29 C 40 E 53 SUR | AI86: no reporta | AJ86: 2700267 | AK86: San Jose | AP86: 6 | AQ86: 41318 | AR86: 41318 | AS86: =+AR86-AQ86 -> 0 | AT86: Acta de Compromiso | AU86: Verificación
B87: 084-2013 | C87: 1300438 | D87: - | E87: RESIDUOS SOLIDOS | H87: Disposición inadecuada de residuos sólidos | I87: Alexandra Maria Bustamenta Vanegaz | T87: =CONCATENATE(J87," ",K87," ",L87," ",M87," ",N87," ",O87," ",P87," ",Q87," ",R87," ",S87) | U87: no reporta | V87: 4600800 ext2008 | W87: Por determinar | X87: DG | Y87: 33 | AB87: 34 | AE87: SUR | AH87: =CONCATENATE(X87," ",Y87," ",Z87," ",AA87," ",AB87," ",AC87," ",AD87," ",AE87," ",AF87," ",AG87) -> DG 33 34 SUR | AI87: no reporta | AJ87: no reporta | AK87: La Magnolia | AP87: 9 | AQ87: 41318 | AS87: =+AR87-AQ87 -> -41318 | AT87: Acta de Compromiso | AU87: Auto de archivo | AV87: 41327 | AW87: J. Alvarez - L. Garcia | AX87: 41327 | CE87: 41327
B88: 085-2013 | C88: 1300447 | D88: FAUNA DOMESTICA | H88: Manejo inadecuado de mascotas | I88: Claudia Patricia Pelaez | J88: CL | K88: 38 | L88: E | M88: SUR | N88: 47 | P88: 39 | T88: =CONCATENATE(J88," ",K88," ",L88," ",M88," ",N88," ",O88," ",P88," ",Q88," ",R88," ",S88) -> CL 38 E SUR 47 39 | U88: no reporta | V88: 2768741 | W88: Por determinar | X88: CL | Y88: 46 | Z88: DD | AA88: SUR | AB88: 37 | AD88: 64 | AH88: =CONCATENATE(X88," ",Y88," ",Z88," ",AA88," ",AB88," ",AC88," ",AD88," ",AE88," ",AF88," ",AG88) -> CL 46 DD SUR 37 64 | AI88: no reporta | AJ88: no reporta | AK88: El Trianon | AP88: 7 | AQ88: 41318 | AR88: 41327 | AS88: =+AR88-AQ88 -> 9 | AT88: Acta de Compromiso | AU88: Auto de archivo | AV88: 41327 | AW88: J. Alvarez - L. Garcia | AX88: 41327 | AY88: 41351 | AZ88: C. Rojas | BA88: 41351 | BB88: 41401 | BC88: C. Rojas - J. Restrepo - S. Bustamante | BD88: 41401 | BE88: 41442 | BF88: J. Alvarez - L. Garcia
B89: 086-2013 | C89: 1300517 | D89: - | E89: RESIDUOS SOLIDOS | H89: Manejo inadecuado de residuos solidos | I89: Jorge Ivan Bustamante | J89: KR | K89: 27 | L89: G | N89: 36 | Q89: SUR | T89: =CONCATENATE(J89," ",K89," ",L89," ",M89," ",N89," ",O89," ",P89," ",Q89," ",R89," ",S89) -> KR 27 G 36 SUR | U89: no reporta | V89: no reporta | W89: Minimarket Pronto | X89: KR | Y89: 27 | Z89: G | AB89: 36 | AD89: 114 | AE89: SUR | AH89: =CONCATENATE(X89," ",Y89," ",Z89," ",AA89," ",AB89," ",AC89," ",AD89," ",AE89," ",AF89," ",AG89) -> KR 27 G 36 114 SUR | AI89: no reporta | AJ89: 3322825 | AK89: La Pradera | AP89: 5 | AQ89: 41323 | AR89: 41323 | AS89: =+AR89-AQ89 -> 0 | AT89: Acta de Compromiso | AU89: Auto de archivo | AV89: 41323 | AW89: C. Rojas | AX89: 41323 | AY89: 41519 | AZ89: L. Garcia - J. Alvarez | BA89: 41519 | CE89: 41703
B90: 087-2013 | C90: 1300486 | D90: - | E90: RESIDUOS SOLIDOS | H90: Manejo inadecuado de residuos solidos | I90: Celina Patiño de Arias | J90: CL | K90: 39 | L90: B | M90: SUR | N90: 24 | O90: F | P90: 58 | T90: =CONCATENATE(J90," ",K90," ",L90," ",M90," ",N90," ",O90," ",P90," ",Q90," ",R90," ",S90) -> CL 39 B SUR 24 F 58 | U90: no reporta | V90: 2769495 | W90: Por determinar | X90: CL | Y90: 39 | Z90: B | AA90: SUR | AB90: 24 | AC90: F | AD90: 58 | AH90: =CONCATENATE(X90," ",Y90," ",Z90," ",AA90," ",AB90," ",AC90," ",AD90," ",AE90," ",AF90," ",AG90) -> CL 39 B SUR 24 F 58 | AI90: no reporta | AJ90: no reporta | AK90: El Chingui | AP90: 6 | AQ90: 41320 | AR90: 41365 | AS90: =+AR90-AQ90 -> 45 | AT90: Acta de Compromiso | AU90: Auto de archivo | AV90: 41365 | AW90: C. Rojas - J. Restrepo - S. Bustamante | AX90: 41365 | BU90: 41415 | BV90: 41415 | CE90: 41477
B91: 088-2013 | C91: 1300484 | D91: - | E91: RESIDUOS SOLIDOS | H91: Manejo inadecuado de residuos solidos | I91: Comunidad | T91: =CONCATENATE(J91," ",K91," ",L91," ",M91," ",N91," ",O91," ",P91," ",Q91," ",R91," ",S91) | U91: no reporta | V91: no reporta | W91: Claudia Rendon | X91: CL | Y91: 40 | AA91: SUR | AB91: 32 | AD91: 57 | AG91: 501 | AH91: =CONCATENATE(X91," ",Y91," ",Z91," ",AA91," ",AB91," ",AC91," ",AD91," ",AE91," ",AF91," ",AG91) -> CL 40 SUR 32 57 501 | AI91: no reporta | AJ91: no reporta | AK91: Mesa | AP91: 9 | AQ91: 41319 | AR91: 41327 | AS91: =+AR91-AQ91 -> 8 | AT91: Acta de Compromiso | AU91: Auto de archivo
B92: 089-2013 | C92: 1300487 | D92: FLORA | H92: Daño de jardin y arboles por niños | I92: Comunidad | T92: =CONCATENATE(J92," ",K92," ",L92," ",M92," ",N92," ",O92," ",P92," ",Q92," ",R92," ",S92) | U92: no reporta | V92: no reporta | W92: Mateo | X92: CL | Y92: 41 | Z92: B | AA92: SUR | AB92: 32 | AC92: B | AF92: 4.6 | AG92: 203 | AH92: =CONCATENATE(X92," ",Y92," ",Z92," ",AA92," ",AB92," ",AC92," ",AD92," ",AE92," ",AF92," ",AG92) -> CL 41 B SUR 32 B 4,6 203 | AI92: no reporta | AJ92: no reporta | AK92: El Dorado | AP92: 7 | AQ92: 41320 | AR92: 41327 | AS92: =+AR92-AQ92 -> 7 | AT92: Acta de Compromiso | AU92: Auto de archivo
B93: 090-2013 | C93: 1300500 | D93: FLORA | H93: Banqueo de terreno en retiro de quebrada y tala de arboles | I93: Jaime Gomez Escobar - Ediobras SAS | J93: KR | K93: 25 | L93: A | N93: 38 | O93: D | P93: 4 | Q93: SUR | T93: =CONCATENATE(J93," ",K93," ",L93," ",M93," ",N93," ",O93," ",P93," ",Q93," ",R93," ",S93) -> KR 25 A 38 D 4 SUR | U93: no reporta | V93: 3329238 | W93: Anibal Lopez Zapata | X93: KR | Y93: 23 | AB93: 36 | AC93: A | AD93: 95 | AE93: SUR | AH93: =CONCATENATE(X93," ",Y93," ",Z93," ",AA93," ",AB93," ",AC93," ",AD93," ",AE93," ",AF93," ",AG93) -> KR 23 36 A 95 SUR | AI93: no reporta | AJ93: no reporta | AL93: Santa Catalina | AP93: 10 | AQ93: 41320 | AR93: 41331 | AS93: =+AR93-AQ93 -> 11 | AT93: Remision u otros | AU93: Auto de archivo
B94: 091-2013 | C94: 1300503 | D94: - | E94: RESIDUOS SOLIDOS | H94: Disposición inadecuada de residuos sólidos | I94: Comunidad | T94: =CONCATENATE(J94," ",K94," ",L94," ",M94," ",N94," ",O94," ",P94," ",Q94," ",R94," ",S94) | U94: no reporta | V94: no reporta | W94: Por determinar | X94: CL | Y94: 40 | AA94: SUR | AB94: 27 | AC94: A | AD94: 41 | AH94: =CONCATENATE(X94," ",Y94," ",Z94," ",AA94," ",AB94," ",AC94," ",AD94," ",AE94," ",AF94," ",AG94) -> CL 40 SUR 27 A 41 | AI94: no reporta | AJ94: no reporta | AK94: La Mina | AP94: 6 | AQ94: 41323 | AR94: 41325 | AS94: =+AR94-AQ94 -> 2 | AT94: Acta de Compromiso | AU94: Auto de archivo | AV94: 41325 | AW94: J. Restrepo - S. Bustamente | AX94: 41325 | BU94: 41326 | BV94: 41326 | CE94: 41703
B95: 092-2013 | C95: 1300514 | D95: - | E95: RESIDUOS SOLIDOS | H95: Disposición inadecuada de residuos sólidos | I95: Gloria Goméz | T95: =CONCATENATE(J95," ",K95," ",L95," ",M95," ",N95," ",O95," ",P95," ",Q95," ",R95," ",S95) | U95: 30370832 | V95: 3321641 | W95: Edificio Villa Angel | X95: CL | Y95: 46 | Z95: A | AA95: SUR | AB95: 42 | AD95: 22 | AH95: =CONCATENATE(X95," ",Y95," ",Z95," ",AA95," ",AB95," ",AC95," ",AD95," ",AE95," ",AF95," ",AG95) -> CL 46 A SUR 42 22 | AI95: no reporta | AJ95: no reporta | AK95: La Paz | AP95: 7 | AQ95: 41323 | AR95: 41327 | AS95: =+AR95-AQ95 -> 4 | AT95: Acta de Compromiso | AU95: Auto de archivo | AV95: 41327 | AW95: C. Rojas | AX95: 41327 | AY95: 41519 | AZ95: Carlos - Jeison - Santiago
A96: 835-2012 R6610 I.T330 | B96: 093-2013 | C96: 1300515 | D96: HIDRICO | H96: Contaminacion de quebrada Las Palmas por movimiento de tierra | I96: Alonso Restrepo | T96: =CONCATENATE(J96," ",K96," ",L96," ",M96," ",N96," ",O96," ",P96," ",Q96," ",R96," ",S96) | U96: no reporta | V96: 3860326 - 3128982916 | W96: Parcelación Serrania | AH96: =CONCATENATE(X96," ",Y96," ",Z96," ",AA96," ",AB96," ",AC96," ",AD96," ",AE96," ",AF96," ",AG96) | AI96: no reporta | AJ96: no reporta | AL96: Las Palmas | AP96: 12 | AQ96: 41323 | AR96: 41330 | AS96: =+AR96-AQ96 -> 7 | AT96: Acta de Compromiso | AU96: Verificación | AV96: 41330 | AW96: J. Guzman - C. Calle | AX96: 41351 | AY96: 41369 | AZ96: L. Taborda | BA96: 41369 | BB96: 41480 | BC96: L. Taborda - C. Calle | BD96: 41480
B97: 094-2013 | C97: 1300516 | D97: - | E97: ESCOMBROS | H97: Disposición inadecuada de escombros | I97: Lucia Mejia | T97: =CONCATENATE(J97," ",K97," ",L97," ",M97," ",N97," ",O97," ",P97," ",Q97," ",R97," ",S97) | U97: no reporta | V97: 3105258678 | W97: Por determinar | X97: DG | Y97: 32 | Z97: D | AB97: 33 | AC97: A | AD97: 11 | AH97: =CONCATENATE(X97," ",Y97," ",Z97," ",AA97," ",AB97," ",AC97," ",AD97," ",AE97," ",AF97," ",AG97) -> DG 32 D 33 A 11 | AI97: no reporta | AJ97: no reporta | AK97: Bucarest | AP97: 9 | AQ97: 41323 | AR97: 41327 | AS97: =+AR97-AQ97 -> 4 | AT97: Acta de Compromiso | AU97: Auto de archivo | AV97: 41327 | AW97: C. Rojas - J. Restrepo - S. Bustamante | AX97: 41327 | AY97: 41351 | AZ97: C. Rojas | BA97: 41351 | CE97: 41351
B98: 095-2013 | C98: 1300544 - 1302825 | D98: - | E98: ESCOMBROS | F98: 9 | H98: Disposición inadecuada de escombros. Comparendo # 127 | I98: De Oficio | T98: =CONCATENATE(J98," ",K98," ",L98," ",M98," ",N98," ",O98," ",P98," ",Q98," ",R98," ",S98) | U98: no reporta | V98: no reporta | W98: Juan Damian Ortiz Escobar | X98: CL | Y98: 37 | AA98: SUR | AB98: 32 | AD98: 30 | AG98: 301 | AH98: =CONCATENATE(X98," ",Y98," ",Z98," ",AA98," ",AB98," ",AC98," ",AD98," ",AE98," ",AF98," ",AG98) -> CL 37 SUR 32 30 301 | AI98: 3354648 | AJ98: 3316309 | AK98: Mesa | AP98: 9 | AQ98: 41324 | AR98: 41326 | AS98: =+AR98-AQ98 -> 2 | AT98: Acuerdo 020 de 2009 | AU98: Auto de archivo | AV98: 41324 | AW98: J. Ospina | AX98: 41324 | BM98: 41326 | BN98: 41326 | BO98: 41326 | BP98: 41331 | BS98: 41331 | BT98: 41430 | BU98: 41430 | BV98: 41431 | BW98: 41446 | BX98: 41451 | BY98: 41451 | CE98: 41541
A99: 689-2012 R5375 | B99: 096-2013 | C99: 1300263 | D99: FLORA | H99: Solicitud copia expediente roceria de lote | I99: Alejandra Rojas | J99: KR | K99: 27 | N99: 36 | P99: 199 | Q99: SUR | T99: =CONCATENATE(J99," ",K99," ",L99," ",M99," ",N99," ",O99," ",P99," ",Q99," ",R99," ",S99) -> KR 27 36 199 SUR | U99: no reporta | V99: 3361863 | W99: Mauricio Toro | X99: KR | Y99: 27 | AB99: 36 | AD99: 199 | AE99: SUR | AH99: =CONCATENATE(X99," ",Y99," ",Z99," ",AA99," ",AB99," ",AC99," ",AD99," ",AE99," ",AF99," ",AG99) -> KR 27 36 199 SUR | AI99: no reporta | AJ99: 3122046742 | AK99: La Pradera | AO99: 00001 | AP99: 5 | AQ99: 41304 | AR99: 41304 | AS99: =+AR99-AQ99 -> 0 | AT99: Acta de Compromiso | AU99: Auto de archivo
A100: 412-2012 I.T686 | B100: 097-2013 | C100: 1300422 | D100: HIDRICO | H100: Requerimento AA por obras de captación | I100: Autoridad Ambiental | T100: =CONCATENATE(J100," ",K100," ",L100," ",M100," ",N100," ",O100," ",P100," ",Q100," ",R100," ",S100) | U100: no reporta | V100: no reporta | W100: Maria Estela Velez Restrepo | AF100: km 17 | AH100: =CONCATENATE(X100," ",Y100," ",Z100," ",AA100," ",AB100," ",AC100," ",AD100," ",AE100," ",AF100," ",AG100) -> km 17 | AI100: 21799761 | AJ100: 3860083 | AL100: Las Palmas | AN100: 004 | AO100: 00249 | AP100: 12 | AQ100: 41317 | AR100: 41317 | AS100: =+AR100-AQ100 -> 0 | AT100: Acta de Compromiso | AU100: Auto de archivo
...

Sheet 2014
AW1: ESTADO DEL PROCESO - FECHAS
A2: verificacion | AW2: Visita inicial | AZ2: Visita de verificación 1 | BC2: Visita de verificación 2 | BF2: Visita de verificación 3 | BI2: Visita de verificación 4 | BL2: Acta de compromiso - comparecencia | BN2: Auto de inicio | BP2: Descargos | BR2: Pruebas | BT2: Fallo - Decisión | BV2: Notificación - Remisión | BX2: Recurso de reposición | BZ2: Notificación - Remisión | CB2: Capacitación | CD2: Remisión Hacienda | CF2: Auto de archivo | CH2: Archivo
A3: Conexo | B3: Consecutivo | C3: Radicado | D3: Recurso afectado | E3: Comparendo | F3: Codigo Infracción | G3: Predios, Otros documentos, Proyecto | H3: Asunto | I3: Quejoso | J3: Tipo de via principal | K3: N° via principal | L3: letra | M3: Cuadrante | N3: Generadora | O3: Letra | P3: Placa | Q3: Cuadrante | R3: Bloque | S3: Interior | T3: Dirección | U3: Cedula quejoso | V3: Telefono quejoso | W3: Infractor | X3: Tipo de via principal | Y3: N° via principal | Z3: letra | AA3: Cuadrante | AB3: Generadora | AC3: Letra | AD3: Placa | AE3: Cuadrante | AF3: Bloque | AG3: Interior | AH3: Direccion | AI3: Cedula Infractor | AJ3: Telefono Infractor | AK3: Lugar Infraccón Barrio | AL3: Vereda | AM3: Codigo Barrio | AN3: Manzana - Vereda | AO3: Predio | AP3: Zona | AQ3: Fecha de ingreso (dd/mm/aaaa) | AR3: Fecha de actuación inicial (ddmm/aaaa) | AS3: Dias de atención | AT3: Destinación procedimental inical | AU3: Estado actual | AV3: Remitido a | AW3: Recibido - Asignado | AX3: Funcionario | AY3: Entregado | AZ3: Recibido - Asignado | BA3: Funcionario | BB3: Entregado | BC3: Recibido - Asignado | BD3: Funcionario | BE3: Entregado | BF3: Recibido - Asignado | BG3: Funcionario | BH3: Entregado | BI3: Recibido - Asignado | BJ3: Funcionario | BK3: Entregado | BL3: Recibido - Asignado | BM3: Entregado | BN3: Recibido - Asignado | BO3: Entregado | BP3: Recibido - Asignado | BQ3: Entregado | BR3: Recibido - Asignado | BS3: Entregado | BT3: Recibido - Asignado | BU3: Entregado | BV3: Recibido - Asignado | BW3: Entregado | BX3: Recibido - Asignado | BY3: Entregado | BZ3: Recibido - Asignado | CA3: Entregado | CB3: Recibido - Asignado | CC3: Entregado | CD3: Recibido - Asignado | CE3: Entregado | CF3: Recibido - Asignado | CG3: Entregado | CH3: Recibido - Asignado | CI3: Entregado
B4: 000-2015 | C4: 1314334 | D4: FAUNA DOMÉSTICA | H4: Bus de sotrames placa STY 558 atropello a canino en Gualandayes el 03-10-2014 a las 7:AM | I4: Comunidad | W4: Bus de sotrames placa STY558 | AV4: Archivo en Oficios recibidos 2014
B5: 001-2014 | C5: 1307937 - 1309615 | D5: FAUNA DOMÉSTICA | F5: - | H5: Agresión de mascota a una persona | I5: Nancy Rojas | J5: CL | K5: 39 | L5: E | N5: 24 | O5: DB | P5: 10 | T5: =CONCATENATE(J5," ",K5," ",L5," ",M5," ",N5," ",O5," ",P5," ",Q5," ",R5," ",S5) -> CL 39 E 24 DB 10 | U5: 43206550 | V5: 3323903 | W5: Lina Marcela Rico Montoya | X5: KR | Y5: 24 | Z5: DE | AB5: 39 | AC5: DD | AD5: 13 | AE5: SUR | AH5: =CONCATENATE(X5," ",Y5," ",Z5," ",AA5," ",AB5," ",AC5," ",AD5," ",AE5," ",AF5," ",AG5) -> KR 24 DE 39 DD 13 SUR | AI5: no reporta | AJ5: no reporta | AK5: El Chingui | AM5: 001 | AP5: 6 | AQ5: 41647 | AR5: 41676 | AS5: =AR5-AQ5 -> 29 | AT5: Código de policia | AU5: Auto de archivo | CF5: 42020
B6: 002-2014 | C6: 1307918 | E6: RESIDUOS SOLIDOS | F6: - | G6: Sensibilización | H6: Disposición de resisuos por parte de varios vecinos en cercanias a la vivienda del usuario | I6: Oscar Hracio Ochoa Ochoa | J6: CL | K6: 46 | M6: SUR | N6: 46 | O6: B | P6: 6 | T6: =CONCATENATE(J6," ",K6," ",L6," ",M6," ",N6," ",O6," ",P6," ",Q6," ",R6," ",S6) -> CL 46 SUR 46 B 6 | U6: 6789735 | V6: 3002757830 | W6: Varios usuarios | X6: CL | Y6: 46 | AA6: SUR | AB6: 46 | AC6: B | AH6: =CONCATENATE(X6," ",Y6," ",Z6," ",AA6," ",AB6," ",AC6," ",AD6," ",AE6," ",AF6," ",AG6) -> CL 46 SUR 46 B | AI6: no reporta | AJ6: no reporta | AK6: Primavera | AP6: 8 | AQ6: 41646 | AR6: 41653 | AS6: =AR6-AQ6 -> 7 | AT6: Acta de compromiso | AU6: Auto de archivo | CF6: 41778
B7: 003-2014 | C7: 1307928 | E7: RESIDUOS SOLIDOS | F7: - | G7: Sensibilización | H7: Disposición inadecuada de residuos solidos en esquina | I7: Comunidad | T7: No registra dirección | U7: no reporta | V7: no reporta | W7: Varios usuarios | X7: TR | Y7: 32 | Z7: C | AA7: SUR | AB7: 32 | AC7: B | AD7: 68 | AH7: =CONCATENATE(X7," ",Y7," ",Z7," ",AA7," ",AB7," ",AC7," ",AD7," ",AE7," ",AF7," ",AG7) -> TR 32 C SUR 32 B 68 | AI7: no reporta | AJ7: no reporta | AK7: La Magnolia | AP7: 9 | AQ7: 41647 | AR7: 41647 | AS7: =AR7-AQ7 -> 0 | AT7: Acta de compromiso | AU7: Auto de archivo | CF7: 41778
B8: 004-2014 | C8: 1307930 | E8: RESIDUOS SOLIDOS | F8: - | G8: Sensibilización | H8: Varias familias disponen residuos en el lote de la familia Berrio Castaño | I8: Familia Berrio Castaño | J8: KR | K8: 24 | L8: C | N8: 41 | P8: 0 | Q8: SUR | T8: =CONCATENATE(J8," ",K8," ",L8," ",M8," ",N8," ",O8," ",P8," ",Q8," ",R8," ",S8) -> KR 24 C 41 0 SUR | U8: no reporta | V8: 3332203 | W8: Varias familias | X8: KR | Y8: 24 | Z8: C | AB8: 41 | AD8: 0 | AE8: SUR | AH8: =CONCATENATE(X8," ",Y8," ",Z8," ",AA8," ",AB8," ",AC8," ",AD8," ",AE8," ",AF8," ",AG8) -> KR 24 C 41 0 SUR | AI8: no reporta | AJ8: no reporta | AL8: El Vallano | AP8: 11 | AQ8: 41647 | AR8: 41675 | AS8: =AR8-AQ8 -> 28 | AT8: Acta de compromiso | AU8: Auto de archivo | CF8: 41775
B9: 005-2014 | C9: 1307951 - 1308102 | D9: FLORA | F9: - | H9: Posible tala de arboles nativos sin autorización | I9: Anónimo | T9: No registra dirección | U9: no reporta | V9: no reporta | W9: Esteban Lopera y otros | AH9: Finca El Silencio | AI9: no reporta | AJ9: 3146175492 | AL9: Pantanillo | AP9: 12 | AQ9: 41648 | AR9: 41653 | AS9: =AR9-AQ9 -> 5 | AT9: Acta de compromiso | AU9: Auto de archivo | AW9: 41653 | AX9: J. Guzman | AY9: 41653 | BL9: 41681 | BM9: 41705 | CF9: 41927
B10: 006-2014 | C10: 1307950 - 1307967 | E10: ESCOMBROS | F10: - | H10: Residuos de escombros y tierras que nos han sido recogidos | I10: Comunidad | T10: No registra dirección | U10: no reporta | V10: no reporta | W10: Nelson Bolivar | X10: KR | Y10: 26 | AB10: 41 | AC10: B | AD10: 25 | AE10: SUR | AH10: =CONCATENATE(X10," ",Y10," ",Z10," ",AA10," ",AB10," ",AC10," ",AD10," ",AE10," ",AF10," ",AG10) -> KR 26 41 B 25 SUR | AI10: no reporta | AJ10: no reporta | AK10: San Rafael | AP10: 6 | AQ10: 41648 | AR10: 41675 | AS10: =AR10-AQ10 -> 27 | AT10: Acta de compromiso | AU10: Auto de archivo | AW10: 41675 | AX10: L. Garcia - J. Alvarez | AY10: 41675 | CF10: 41703
B11: 007-2014 | C11: 1307920 | E11: RESIDUOS SOLIDOS | F11: - | H11: Punto crítico de residuos solidos | I11: Carolina Berrio | J11: KR | K11: 41 | N11: 33 | O11: B | P11: 4 | Q11: SUR | T11: =CONCATENATE(J11," ",K11," ",L11," ",M11," ",N11," ",O11," ",P11," ",Q11," ",R11," ",S11) -> KR 41 33 B 4 SUR | U11: no reporta | V11: 3344314 | W11: Varios usuarios | AH11: No registra dirección | AI11: no reporta | AJ11: no reporta | AK11: Zona centro | AP11: 9 | AQ11: 41646 | AR11: 41675 | AS11: =AR11-AQ11 -> 29 | AT11: Acta de compromiso | AU11: Verificación
B12: 008-2014 | C12: 1307949 | E12: RESIDUOS SOLIDOS | F12: - | H12: Solicitan sensibilización en el sector por inadecuada disposición de residuos sólidos | I12: Comunidad | T12: No registra dirección | U12: no reporta | V12: no reporta | W12: Varios usuarios | X12: KR | Y12: 39 | AB12: 47 | AH12: =CONCATENATE(X12," ",Y12," ",Z12," ",AA12," ",AB12," ",AC12," ",AD12," ",AE12," ",AF12," ",AG12) -> KR 39 47 | AI12: no reporta | AJ12: no reporta | AK12: El Trianón | AP12: 7 | AQ12: 41648 | AR12: 41675 | AS12: =AR12-AQ12 -> 27 | AT12: Acta de compromiso | AU12: Auto de archivo
B13: 009-2014 | C13: 1307943 | E13: RESIDUOS SOLIDOS | F13: - | H13: Residuos de poda de jardin en el espacio público | I13: Comunidad | T13: No registra dirección | U13: no reporta | V13: no reporta | W13: Rocio | X13: CL | Y13: 46 | Z13: C | AA13: SUR | AB13: 37 | AD13: 63 | AH13: =CONCATENATE(X13," ",Y13," ",Z13," ",AA13," ",AB13," ",AC13," ",AD13," ",AE13," ",AF13," ",AG13) -> CL 46 C SUR 37 63 | AI13: no reporta | AJ13: no reporta | AK13: El Trianón | AP13: 7 | AQ13: 41283 | AR13: 41675 | AS13: =AR13-AQ13 -> 392 | AT13: Acta de compromiso | AU13: Auto de archivo | AW13: 41675 | AX13: L. Garcia - J. Alvarez | AY13: 41677 | BL13: 41682 | BM13: 41682
B14: 010-2014 | C14: 1307938 | D14: SUELO | F14: - | H14: Cambio de zona de verde por piso duro | I14: Comunidad | T14: No registra dirección | U14: no reporta | V14: no reporta | W14: Por definir | X14: KR | Y14: 42 | Z14: B | AB14: 46 | AC14: A | AE14: SUR | AH14: =CONCATENATE(X14," ",Y14," ",Z14," ",AA14," ",AB14," ",AC14," ",AD14," ",AE14," ",AF14," ",AG14) -> KR 42 B 46 A SUR | AI14: no reporta | AJ14: no reporta | AK14: La Paz | AP14: 7 | AQ14: 41647 | AR14: 41683 | AS14: =AR14-AQ14 -> 36 | AT14: Acta de compromiso | AU14: Auto de archivo
B15: 011-2014 | C15: 1307958 | D15: FAUNA DOMÉSTICA | F15: - | H15: Abandono de dos perros en parqueadero | I15: Luis Cañas | T15: No registra dirección | U15: no reporta | V15: 3341702 | W15: Juan Guillermo Serna | X15: KR | Y15: 43 | Z15: A | AB15: 45 | AD15: 27 | AE15: SUR | AH15: =CONCATENATE(X15," ",Y15," ",Z15," ",AA15," ",AB15," ",AC15," ",AD15," ",AE15," ",AF15," ",AG15) -> KR 43 A 45 27 SUR | AI15: no reporta | AJ15: 3108221291 | AK15: Primavera | AP15: 8 | AQ15: 41648 | AR15: 41653 | AS15: =AR15-AQ15 -> 5 | AT15: Acta de compromiso | AU15: Auto de archivo | AW15: 41653 | AX15: F. Villarraga | AY15: 41653 | CF15: 41675
B16: 012-2014 | C16: 131778 | D16: SUELO | F16: - | H16: Amenaza por inundación en predio | I16: CTGRD - OOPP - Edith Boada | T16: No registra dirección | U16: no reporta | V16: 3394000 | W16: José Patiño | X16: CL | Y16: 39 | Z16: B | AA16: SUR | AB16: 24 | AC16: EE | AD16: 128 | AG16: 114 | AH16: =CONCATENATE(X16," ",Y16," ",Z16," ",AA16," ",AB16," ",AC16," ",AD16," ",AE16," ",AF16," ",AG16) -> CL 39 B SUR 24 EE 128 114 | AI16: no reporta | AJ16: no reporta | AK16: El Chingui | AP16: 6 | AQ16: 41647 | AS16: =AR16-AQ16 -> -41647 | AT16: Acta de compromiso | AU16: Auto de archivo
B17: 013-2014 | C17: 100665 - 103500 | E17: RESIDUOS SOLIDOS | F17: - | H17: Humedades y disposición inadecuada de residuos solidos que afectan vivienda | I17: Secretaria de Salud | J17: CL | K17: 40 | L17: F | M17: SUR | N17: 30 | P17: 25 | T17: =CONCATENATE(J17," ",K17," ",L17," ",M17," ",N17," ",O17," ",P17," ",Q17," ",R17," ",S17) -> CL 40 F SUR 30 25 | U17: no reporta | V17: 3394000 | W17: Por definir | X17: CL | Y17: 40 | Z17: G | AA17: SUR | AB17: 30 | AH17: =CONCATENATE(X17," ",Y17," ",Z17," ",AA17," ",AB17," ",AC17," ",AD17," ",AE17," ",AF17," ",AG17) -> CL 40 G SUR 30 | AI17: no reporta | AJ17: no reporta | AK17: El Dorado | AP17: 7 | AQ17: 41647 | AR17: 41675 | AS17: =AR17-AQ17 -> 28 | AT17: Acta de compromiso | AU17: Citaciones
B18: 014-2014 | C18: 1307940 | D18: SUELO | F18: - | H18: Cambio de zona de verde por piso duro | I18: De oficio - Parques y Arborización | T18: No registra dirección | U18: no reporta | V18: 3394000 | W18: Juan Sebastian Briceño | X18: CL | Y18: 25 | AA18: SUR | AB18: 45 | AD18: 23 | AH18: =CONCATENATE(X18," ",Y18," ",Z18," ",AA18," ",AB18," ",AC18," ",AD18," ",AE18," ",AF18," ",AG18) -> CL 25 SUR 45 23 | AI18: 1037588511 | AJ18: 4444458 | AK18: Villagrande | AP18: 4 | AQ18: 41648 | AR18: 41690 | AS18: =AR18-AQ18 -> 42 | AT18: Acta de compromiso | AU18: Citaciones | AW18: 41690 | AX18: L. Garcia - J. Alvarez | AY18: 41690 | CF18: 41703
B19: 015-2014 | C19: 1307939 - 1308266 | D19: SUELO | F19: - | H19: Cambio de zona de verde por piso duro | I19: De oficio - Parques y Arborización | T19: No registra dirección | U19: no reporta | V19: 3394000 | W19: Por definir | X19: DG | Y19: 31 | Z19: E | AB19: 34 | AD19: 13 | AE19: SUR | AH19: =CONCATENATE(X19," ",Y19," ",Z19," ",AA19," ",AB19," ",AC19," ",AD19," ",AE19," ",AF19," ",AG19) -> DG 31 E 34 13 SUR | AI19: no reporta | AJ19: no reporta | AK19: Obrero | AP19: 9 | AQ19: 41648 | AR19: 41662 | AS19: =AR19-AQ19 -> 14 | AT19: Acta de compromiso | AU19: Citaciones | CF19: 41731
B20: 016-2014 | C20: 1307980 | D20: FAUNA DOMÉSTICA | F20: - | H20: Mascota a la que no recogen sus excrementos | I20: Eunice Muñoz | T20: No registra dirección | U20: 32336889 | V20: 3333027 | W20: Por definir | X20: CL | Y20: 41 | AA20: SUR | AF20: 2.6 | AG20: 403 | AH20: =CONCATENATE(X20," ",Y20," ",Z20," ",AA20," ",AB20," ",AC20," ",AD20," ",AE20," ",AF20," ",AG20) -> CL 41 SUR 2.6 403 | AI20: no reporta | AJ20: no reporta | AK20: El Dorado | AP20: 7 | AQ20: 41652 | AR20: 41680 | AS20: =AR20-AQ20 -> 28 | AT20: Acta de compromiso | AU20: Citaciones | CF20: 41816
B21: 017-2014 | C21: 1307970-132221 | D21: FAUNA DOMÉSTICA | F21: - | H21: Mascota de raza peligrosa que ha agredido a personas | I21: Jenny Castañeda Bolivar | J21: KR | K21: 27 | L21: B | N21: 23 | P21: 60 | Q21: SUR | T21: =CONCATENATE(J21," ",K21," ",L21," ",M21," ",N21," ",O21," ",P21," ",Q21," ",R21," ",S21) -> KR 27 B 23 60 SUR | U21: 42895814 | V21: 5975726 | W21: Gladys Castañeda | AH21: No registra dirección | AI21: no reporta | AJ21: no reporta | AK21: Zuñiga | AP21: 4 | AQ21: 41649 | AR21: 41712 | AS21: =AR21-AQ21 -> 63 | AT21: Código de policia | AU21: Citaciones | AW21: 41712 | AX21: C. Rojas - C. Calle | AY21: 41716
B22: 018-2014 | C22: 1307962 | E22: RESIDUOS SOLIDOS | F22: - | H22: Presencia de escombros y residuos especiales en este sitio | I22: Anónimo | T22: No registra dirección | U22: no reporta | V22: no reporta | W22: Por definir | X22: DG | Y22: 32 | Z22: D | AB22: 32 | AC22: C | AH22: =CONCATENATE(X22," ",Y22," ",Z22," ",AA22," ",AB22," ",AC22," ",AD22," ",AE22," ",AF22," ",AG22) -> DG 32 D 32 C | AI22: no reporta | AJ22: no reporta | AK22: La Magnolia | AP22: 9 | AQ22: 41649 | AR22: 41675 | AS22: =AR22-AQ22 -> 26 | AT22: Acta de compromiso | AU22: Citaciones
B23: 019-2014 | C23: 1307953 | D23: FLORA | F23: - | H23: Poda de 5 arboles sin tecnica | I23: Comunidad | J23: CL | K23: 36 | L23: D | M23: SUR | N23: 26 | O23: A | P23: 6 | T23: =CONCATENATE(J23," ",K23," ",L23," ",M23," ",N23," ",O23," ",P23," ",Q23," ",R23," ",S23) -> CL 36 D SUR 26 A 6 | U23: no reporta | V23: no reporta | W23: Emilse Santamaria Bolivar | X23: CL | Y23: 36 | Z23: D | AA23: SUR | AB23: 26 | AC23: A | AD23: 6 | AH23: =CONCATENATE(X23," ",Y23," ",Z23," ",AA23," ",AB23," ",AC23," ",AD23," ",AE23," ",AF23," ",AG23) -> CL 36 D SUR 26 A 6 | AI23: no reporta | AJ23: no reporta | AK23: San Rafael | AP23: 6 | AQ23: 41648 | AR23: 41721 | AS23: =AR23-AQ23 -> 73 | AT23: Acta de compromiso | AU23: Citaciones | AW23: 41721 | AX23: J. Restrepo - S. Bustamante - C. Rojas | AY23: 41722 | CF23: 41753
B24: 020-2014 | C24: 1308025 | E24: RESIDUOS SOLIDOS | F24: - | H24: El usuario de esta dirección saca la basura a la Transv 33 A Sur esquina | I24: Comunidad | J24: TR | K24: 33 | L24: A | M24: SUR | T24: =CONCATENATE(J24," ",K24," ",L24," ",M24," ",N24," ",O24," ",P24," ",Q24," ",R24," ",S24) -> TR 33 A SUR | U24: no reporta | V24: no reporta | W24: Por definir | X24: DG | Y24: 33 | AB24: 33 | AD24: 32 | AE24: SUR | AG24: 2 | AH24: =CONCATENATE(X24," ",Y24," ",Z24," ",AA24," ",AB24," ",AC24," ",AD24," ",AE24," ",AF24," ",AG24) -> DG 33 33 32 SUR 2 | AI24: no reporta | AJ24: no reporta | AK24: La Magnolia | AP24: 9 | AQ24: 41654 | AR24: 41675 | AS24: =AR24-AQ24 -> 21 | AT24: Acta de compromiso | AU24: Citaciones
B25: 021-2014 | C25: 1308072 | F25: - | H25: Disposición de escombros en lote | I25: Edward Patiño | J25: CL | K25: 41 | L25: B | M25: SUR | N25: 25 | O25: A | P25: 25 | S25: 98-15 | T25: =CONCATENATE(J25," ",K25," ",L25," ",M25," ",N25," ",O25," ",P25," ",Q25," ",R25," ",S25) -> CL 41 B SUR 25 A 25 98-15 | U25: 3413718 | V25: 3026782 | W25: José Santamaria | X25: CL | Y25: 41 | Z25: B | AA25: SUR | AH25: =CONCATENATE(X25," ",Y25," ",Z25," ",AA25," ",AB25," ",AC25," ",AD25," ",AE25," ",AF25," ",AG25) -> CL 41 B SUR | AI25: no reporta | AJ25: no reporta | AK25: San Rafael | AP25: 6 | AQ25: 41656 | AR25: 41676 | AS25: =AR25-AQ25 -> 20 | AT25: Acta de compromiso | AU25: Auto de archivo | AW25: 41677 | AX25: L. Garcia - J. Alvarez | AY25: 41680
B26: 022-2014 | C26: 1308017 | D26: FAUNA DOMÉSTICA | F26: - | H26: Ataque de perro a una mascota | I26: Jorge Alzate | J26: CL | K26: 45 | L26: A | M26: SUR | N26: 39 | O26: B | P26: 101 | T26: =CONCATENATE(J26," ",K26," ",L26," ",M26," ",N26," ",O26," ",P26," ",Q26," ",R26," ",S26) -> CL 45 A SUR 39 B 101 | U26: no reporta | V26: 3004544007 | W26: Tatiana Tabares | X26: CL | Y26: 45 | Z26: A | AA26: SUR | AB26: 39 | AC26: B | AD26: 101 | AG26: 215 | AH26: =CONCATENATE(X26," ",Y26," ",Z26," ",AA26," ",AB26," ",AC26," ",AD26," ",AE26," ",AF26," ",AG26) -> CL 45 A SUR 39 B 101 215 | AI26: no reporta | AJ26: no reporta | AK26: El Trianón | AP26: 7 | AQ26: 41654 | AR26: 41663 | AS26: =AR26-AQ26 -> 9 | AT26: Código de policia | AU26: Citaciones | CF26: 42020
B27: 023-2014 | C27: 1308050 | E27: RESIDUOS SOLIDOS | F27: - | G27: Sensibilización | H27: Disposición de escombros y basuras en lote | I27: De oficio - Inspección Ambiental | T27: No registra dirección | U27: no reporta | V27: 3394072 | W27: Por definir | X27: CL | Y27: 40 | Z27: A | AA27: SUR | AH27: =CONCATENATE(X27," ",Y27," ",Z27," ",AA27," ",AB27," ",AC27," ",AD27," ",AE27," ",AF27," ",AG27) -> CL 40 A SUR | AI27: no reporta | AJ27: no reporta | AK27: La Mina | AP27: 6 | AQ27: 41655 | AR27: 41676 | AS27: =AR27-AQ27 -> 21 | AT27: Acta de compromiso | AU27: Citaciones
B28: 024-2014 | C28: 1308076 | D28: FAUNA DOMÉSTICA | F28: - | H28: Ataque de perro a una persona | I28: Luis Fernando Botero Ruiz - Nohemy Ayala | J28: KR | K28: 27 | L28: D | N28: 27 | P28: 95 | Q28: SUR | S28: 112 | T28: =CONCATENATE(J28," ",K28," ",L28," ",M28," ",N28," ",O28," ",P28," ",Q28," ",R28," ",S28) -> KR 27 D 27 95 SUR 112 | U28: 70038585 | V28: 3108919244 - 3566198 | W28: Por definir | X28: CL | Y28: 27 | AA28: SUR | AB28: 27 | AC28: D | AD28: 123 | AH28: =CONCATENATE(X28," ",Y28," ",Z28," ",AA28," ",AB28," ",AC28," ",AD28," ",AE28," ",AF28," ",AG28) -> CL 27 SUR 27 D 123 | AI28: no reporta | AJ28: no reporta | AK28: El Esmeraldal | AP28: 4 | AQ28: 41656 | AR28: 41673 | AS28: =AR28-AQ28 -> 17 | AT28: Código de policia | AU28: Citaciones | CF28: 42020
B29: 025-2014 | C29: 1308015 - 1302338 | D29: SUELO | F29: - | H29: Cambio de zona de verde por piso duro | I29: De oficio - Parques y Arborización | T29: No registra dirección | U29: no reporta | V29: 3394000 | W29: Por definir | X29: CL | Y29: 45 | Z29: B | AA29: SUR | AB29: 43 | AD29: 18 | AH29: =CONCATENATE(X29," ",Y29," ",Z29," ",AA29," ",AB29," ",AC29," ",AD29," ",AE29," ",AF29," ",AG29) -> CL 45 B SUR 43 18 | AI29: no reporta | AJ29: no reporta | AK29: La Paz | AP29: 7 | AQ29: 41654 | AR29: 41676 | AS29: =AR29-AQ29 -> 22 | AT29: Acta de compromiso | AU29: Citaciones | AW29: 41676 | AX29: A.Restrepo - S.Ossa | AY29: 41676 | AZ29: 41762 | BA29: L. Taborda | BB29: 41762 | BL29: 41754 | BM29: 41754 | CF29: 41794
A30: 14879 Oficio 13-3152 I.T 13-3153 | B30: 026-2014 | C30: 1308079-132286 - 304489 | D30: HÍDRICO | F30: - | G30: Saltamonte | H30: Revisión de determinantes ambientales de obra Proyecto Saltamonte | I30: De oficio - Inspección Ambiental | T30: No registra dirección | U30: no reporta | V30: 3394072 | W30: Proyecto Saltamonte - Coninsa Ramon H | X30: KR | Y30: 27 | Z30: G | AB30: 35 | AD30: 175 | AE30: SUR | AH30: =CONCATENATE(X30," ",Y30," ",Z30," ",AA30," ",AB30," ",AC30," ",AD30," ",AE30," ",AF30," ",AG30) -> KR 27 G 35 175 SUR | AI30: no reporta | AJ30: 3347443 | AK30: Inmaculada | AP30: 5 | AQ30: 41656 | AR30: 41656 | AS30: =AR30-AQ30 -> 0 | AT30: Acta de compromiso | AU30: Citaciones | AV30: Adjuntan informe el dia 24-06-2015 | AW30: 41725 | AX30: C. Calle | AY30: 41729 | AZ30: 41772 | BA30: L. Taborda | BB30: 41773
B31: 027-2014 | C31: 1308081 | E31: RESIDUOS SOLIDOS | F31: - | H31: Residuos de corte de pasto que fue arrojadoa la Urb Altos del Trianón | I31: Comunidad | T31: No registra dirección | U31: no reporta | V31: no reporta | W31: Por definir | X31: CL | Y31: 45 | Z31: B | AA31: SUR | AB31: 37 | AD31: 170 | AH31: =CONCATENATE(X31," ",Y31," ",Z31," ",AA31," ",AB31," ",AC31," ",AD31," ",AE31," ",AF31," ",AG31) -> CL 45 B SUR 37 170 | AI31: no reporta | AJ31: no reporta | AK31: El Trianón | AP31: 7 | AQ31: 41656 | AR31: 41676 | AS31: =AR31-AQ31 -> 20 | AT31: Acta de compromiso | AU31: Citaciones | CF31: 41778
B32: 028-2014 | C32: 1308089 | E32: RESIDUOS SOLIDOS | F32: - | H32: La señora tira residuos de comida al exterior lo cual genera problemas de insalubridad | I32: Comunidad | T32: No registra dirección | U32: no reporta | V32: no reporta | W32: Luz Mila | X32: TR | Y32: 35 | Z32: B | AA32: SUR | AB32: 31 | AC32: A | AD32: 3 | AG32: 201 | AH32: =CONCATENATE(X32," ",Y32," ",Z32," ",AA32," ",AB32," ",AC32," ",AD32," ",AE32," ",AF32," ",AG32) -> TR 35 B SUR 31 A 3 201 | AI32: no reporta | AJ32: no reporta | AK32: La Sebastiana | AP32: 3 | AQ32: 41659 | AR32: 41668 | AS32: =AR32-AQ32 -> 9 | AT32: Acta de compromiso | AU32: Citaciones | AW32: 41668 | AX32: A.Restrepo - S.Ossa | AY32: 41668 | AZ32: 41677 | BA32: J. Restrepo - S. Bustamante | BB32: 41680 | CF32: 41687
B33: 029-2014 | C33: 1308080 - 1309944 | D33: SUELO | F33: - | H33: Cambio de zona de verde por piso duro | I33: Anónimo | T33: No registra dirección | U33: no reporta | V33: no reporta | W33: Panaderia | X33: KR | Y33: 45 | AB33: 29 | AC33: A | AE33: SUR | AH33: =CONCATENATE(X33," ",Y33," ",Z33," ",AA33," ",AB33," ",AC33," ",AD33," ",AE33," ",AF33," ",AG33) -> KR 45 29 A SUR | AI33: no reporta | AJ33: no reporta | AK33: Jardines | AP33: 2 | AQ33: 41656 | AR33: 41683 | AS33: =AR33-AQ33 -> 27 | AT33: Acta de compromiso | AU33: Citaciones
A34: I.T 132004 Oficio 132005 13-2468 13-2469 | B34: 030-2014 | C34: 1308118 - DP1404 | D34: HÍDRICO | E34: RESIDUOS SOLIDOS | F34: - | H34: Contaminación de fuente La Zuñiga por posibles residuos de construcción | I34: Oswaldo Gomez Sierra | J34: CL | K34: 23 | M34: SUR | N34: 25 | O34: B | P34: 114 | T34: =CONCATENATE(J34," ",K34," ",L34," ",M34," ",N34," ",O34," ",P34," ",Q34," ",R34," ",S34) -> CL 23 SUR 25 B 114 | U34: 71613482 | V34: 5702506-4362436 | W34: Por definir | AH34: No registra dirección | AI34: no reporta | AJ34: no reporta | AK34: Zuñiga | AP34: 4 | AQ34: 41660 | AR34: 41674 | AS34: =AR34-AQ34 -> 14 | AT34: Remisión u otros | AU34: Auto de archivo | AW34: 41682 | AX34: J. Guzman | AY34: 41689
B35: 031-2014 | C35: 1308140 | E35: RESIDUOS SOLIDOS | F35: - | G35: Sensibilización | H35: Solicitan sensibilización en el sector por inadecuada disposición de residuos sólidos | I35: Comunidad | T35: No registra dirección | U35: no reporta | V35: no reporta | W35: Por definir | X35: TR | Y35: 33 | Z35: A | AA35: SUR | AB35: 31 | AC35: E | AH35: =CONCATENATE(X35," ",Y35," ",Z35," ",AA35," ",AB35," ",AC35," ",AD35," ",AE35," ",AF35," ",AG35) -> TR 33 A SUR 31 E | AI35: no reporta | AJ35: no reporta | AK35: La Magnolia | AP35: 9 | AQ35: 41662 | AR35: 41662 | AS35: =AR35-AQ35 -> 0 | AT35: Acta de compromiso | AU35: Citaciones | AW35: 41662 | AX35: A.Restrepo - S.Ossa | AY35: 41662 | CF35: 41662
B36: 032-2014 | C36: 1308113 | E36: RESIDUOS SOLIDOS | F36: - | H36: Hermanas que dejan los excrementos de sus mascotas en el espacio público | I36: De oficio - Inspección Ambiental | T36: No registra dirección | U36: no reporta | V36: 3394072 | W36: Cristina Acosta - Mónica Acosta | X36: KR | Y36: 42 | Z36: A | AB36: 48 | AC36: C | AD36: 73 | AE36: SUR | AF36: 3.7 | AG36: 403 | AH36: =CONCATENATE(X36," ",Y36," ",Z36," ",AA36," ",AB36," ",AC36," ",AD36," ",AE36," ",AF36," ",AG36) -> KR 42 A 48 C 73 SUR 3.7 403 | AI36: no reporta | AJ36: no reporta | AK36: Loma del Barro | AP36: 7 | AQ36: 41660 | AR36: 41661 | AS36: =AR36-AQ36 -> 1 | AT36: Acta de compromiso | AU36: Citaciones | BL36: 41666 | BM36: 41666
B37: 033-2014 | C37: 102523 | F37: - | H37: Disposición inadecuada de resiuduos y material reciclable | I37: De oficio - Inspección Primera - Nataly Estrada | J37: CL | K37: 40 | L37: E | M37: SUR | N37: 41 | P37: 51 | T37: =CONCATENATE(J37," ",K37," ",L37," ",M37," ",N37," ",O37," ",P37," ",Q37," ",R37," ",S37) -> CL 40 E SUR 41 51 | U37: no reporta | V37: 2065686 | W37: Jesus Eduardo Durango Echavarria | AH37: No registra dirección | AI37: no reporta | AJ37: no reporta | AK37: El Dorado | AP37: 7 | AQ37: 41656 | AR37: 41662 | AS37: =AR37-AQ37 -> 6 | AT37: Acta de compromiso | AU37: Citaciones | AW37: 41662 | AX37: A.Restrepo - S.Ossa | AY37: 41662 | CF37: 41675
B38: 034-2014 | C38: 1308241 | E38: RESIDUOS SOLIDOS | F38: - | H38: Imposición de comparendo ambiental 555 | I38: De oficio - Inspección Ambiental | T38: No registra dirección | U38: no reporta | V38: 3394072 | W38: Consorcio Prosperidad 2013 | X38: AV | Y38: 15 | AB38: 124 | AD38: 67 | AG38: 701 | AH38: =CONCATENATE(X38," ",Y38," ",Z38," ",AA38," ",AB38," ",AC38," ",AD38," ",AE38," ",AF38," ",AG38) -> AV 15 124 67 701 | AI38: 900606407-0 | AJ38: 2155651-2156457 | AK38: La Mina | AP38: 6 | AQ38: 41666 | AR38: 41668 | AS38: =AR38-AQ38 -> 2 | AT38: Comparendo ambiental | AU38: Citaciones | BN38: 41668 | BO38: 41668 | CF38: 41708
B39: 035-2014 | C39: 1308207 | E39: RESIDUOS SOLIDOS | F39: - | G39: Sensibilización | H39: Solicitan sensibilización en el sector por inadecuada disposición de residuos sólidos | I39: De oficio - Inspección Ambiental | T39: No registra dirección | U39: no reporta | V39: 3394072 | W39: Varios usuarios | AH39: No registra dirección | AI39: no reporta | AJ39: no reporta | AK39: Los Naranjos | AP39: 9 | AQ39: 41667 | AR39: 41667 | AS39: =AR39-AQ39 -> 0 | AT39: Acta de compromiso | AU39: Citaciones | AW39: 41667 | AX39: A.Restrepo - S.Ossa | AY39: 41667
B40: 036-2014 | C40: 1308219 | E40: RESIDUOS SOLIDOS | F40: - | G40: Sensibilización | H40: Solicitan sensibilización en el sector por inadecuada disposición de residuos sólidos | I40: De oficio - Inspección Ambiental | T40: No registra dirección | U40: no reporta | V40: 3394072 | W40: Varios usuarios | AH40: No registra dirección | AI40: no reporta | AJ40: no reporta | AK40: Los Naranjos | AP40: 9 | AQ40: 41667 | AR40: 41667 | AS40: =AR40-AQ40 -> 0 | AT40: Acta de compromiso | AU40: Citaciones | AW40: 41667 | AX40: A.Restrepo - S.Ossa | AY40: 41667
B41: 037-2014 | C41: 1308209 | E41: RESIDUOS SOLIDOS | F41: - | G41: Sensibilización | H41: Solicitan sensibilización en el sector por inadecuada disposición de residuos sólidos | I41: De oficio - Enviaseo - Luz Stella Molina | J41: TR | K41: 32 | M41: SUR | N41: 32 | O41: D | P41: 18 | T41: =CONCATENATE(J41," ",K41," ",L41," ",M41," ",N41," ",O41," ",P41," ",Q41," ",R41," ",S41) -> TR 32 SUR 32 D 18 | U41: no reporta | V41: 3153694456 | W41: Varios usuarios | X41: TR | Y41: 32 | AA41: SUR | AB41: 32 | AC41: D | AH41: =CONCATENATE(X41," ",Y41," ",Z41," ",AA41," ",AB41," ",AC41," ",AD41," ",AE41," ",AF41," ",AG41) -> TR 32 SUR 32 D | AI41: no reporta | AJ41: no reporta | AK41: La Magnolia | AP41: 9 | AQ41: 41667 | AR41: 41667 | AS41: =AR41-AQ41 -> 0 | AT41: Acta de compromiso | AU41: Citaciones | AW41: 41667 | AX41: A.Restrepo - S.Ossa | AY41: 41667
B42: 038-2014 | C42: 1308107 | E42: RESIDUOS SOLIDOS | F42: - | H42: La señora coloca los residuo solidos en horas y lugares no autorizados | I42: Anónimo | T42: No registra dirección | U42: no reporta | V42: no reporta | W42: Claudia | AF42: e | AG42: 902 | AH42: =CONCATENATE(X42," ",Y42," ",Z42," ",AA42," ",AB42," ",AC42," ",AD42," ",AE42," ",AF42," ",AG42) -> e 902 | AI42: no reporta | AJ42: no reporta | AK42: Inmaculada | AP42: 5 | AQ42: 41660 | AR42: 41681 | AS42: =AR42-AQ42 -> 21 | AT42: Acta de compromiso | AU42: Citaciones | CF42: 41778
B43: 039-2014 | C43: 1308206 | D43: HÍDRICO | F43: - | H43: Vertimiento de aguas negras a fuente hídrica | I43: Luis Gonzalo Parra | T43: No registra dirección | U43: no reporta | V43: 3104641982 | W43: EPM | X43: KR | Y43: 25 | Z43: A | AB43: 36 | AC43: D | AD43: 151 | AE43: SUR | AF43: 0 | AH43: =CONCATENATE(X43," ",Y43," ",Z43," ",AA43," ",AB43," ",AC43," ",AD43," ",AE43," ",AF43," ",AG43) -> KR 25 A 36 D 151 SUR 0 | AI43: no reporta | AJ43: 4444115 | AK43: La Pradera | AP43: 5 | AQ43: 41663 | AR43: 41663 | AS43: =AR43-AQ43 -> 0 | AT43: Remisión u otros | AU43: Citaciones | AW43: 41663 | AX43: J. Guzman | AY43: 41663 | CF43: 41669
B44: 040-2014 | C44: 1308132 | D44: FLORA | E44: ESCOMBROS | F44: 9 | H44: Comparendo 572 - Tala de guaduas en zona verde de esta bodega | I44: Any Ocampo | J44: CL | K44: 52 | M44: SUR | N44: 44 | P44: 45 | T44: =CONCATENATE(J44," ",K44," ",L44," ",M44," ",N44," ",O44," ",P44," ",Q44," ",R44," ",S44) -> CL 52 SUR 44 45 | U44: no reporta | V44: 4440334 - 3780314 | W44: Casa sobre la roca - Iglesia Cristiana Integral | X44: CL | Y44: 25 | Z44: A | AA44: SUR | AB44: 48 | AD44: 35 | AH44: =CONCATENATE(X44," ",Y44," ",Z44," ",AA44," ",AB44," ",AC44," ",AD44," ",AE44," ",AF44," ",AG44) -> CL 25 A SUR 48 35 | AI44: 830010896-6 | AJ44: no reporta | AK44: Las Vegas | AP44: 1 | AQ44: 41661 | AR44: 41682 | AS44: =AR44-AQ44 -> 21 | AT44: Comparendo ambiental | AU44: Citaciones
B45: 041-2014 | C45: 1308208 | E45: RESIDUOS SOLIDOS | F45: - | G45: Sensibilización | H45: Solicitan sensibilización en el sector por inadecuada disposición de residuos sólidos | I45: De oficio - Inspección Ambiental | T45: No registra dirección | U45: no reporta | V45: 3394072 | W45: Varios usuarios | X45: KR | Y45: 24 | Z45: C | AB45: 41 | AD45: 70 | AF45: 2 | AH45: =CONCATENATE(X45," ",Y45," ",Z45," ",AA45," ",AB45," ",AC45," ",AD45," ",AE45," ",AF45," ",AG45) -> KR 24 C 41 70 2 | AI45: no reporta | AJ45: no reporta | AK45: La Mina | AP45: 6 | AQ45: 41666 | AR45: 41666 | AS45: =AR45-AQ45 -> 0 | AT45: Acta de compromiso | AU45: Citaciones | AW45: 41667 | AX45: A.Restrepo - S.Ossa | AY45: 41667
B46: 042-2014 | C46: 1308105 | D46: FAUNA DOMÉSTICA | F46: - | H46: Ataque de mascota a una persona | I46: Carlos Mario Ramirez Gaviria - Admon Unidad Flor del Campo | J46: CL | K46: 40 | L46: AA | M46: SUR | N46: 32 | P46: 75 | T46: =CONCATENATE(J46," ",K46," ",L46," ",M46," ",N46," ",O46," ",P46," ",Q46," ",R46," ",S46) -> CL 40 AA SUR 32 75 | U46: no reporta | V46: 5794001-3122597321 | W46: Por definir | X46: CL | Y46: 40 | Z46: AA | AA46: SUR | AB46: 32 | AD46: 75 | AF46: 6 | AG46: 127 | AH46: =CONCATENATE(X46," ",Y46," ",Z46," ",AA46," ",AB46," ",AC46," ",AD46," ",AE46," ",AF46," ",AG46) -> CL 40 AA SUR 32 75 6 127 | AI46: no reporta | AJ46: no reporta | AK46: El Dorado | AP46: 7 | AQ46: 41660 | AR46: 41690 | AS46: =AR46-AQ46 -> 30 | AT46: Código de policia | AU46: Citaciones | AW46: 41687 | AX46: F. Villarraga | AY46: 41718 | CF46: 41708
B47: 043-2014 | C47: 102806 | D47: SUELO | F47: - | H47: Problemas de inestabilidad del terreno | I47: CGTRD - Lina Patricia Mesa | J47: CL | K47: 40 | L47: F | M47: SUR | N47: 24 | O47: D | P47: 200 | T47: =CONCATENATE(J47," ",K47," ",L47," ",M47," ",N47," ",O47," ",P47," ",Q47," ",R47," ",S47) -> CL 40 F SUR 24 D 200 | U47: no reporta | V47: 3060087 | W47: Por definir | AH47: No registra dirección | AI47: no reporta | AJ47: no reporta | AK47: La Mina | AP47: 6 | AQ47: 41655 | AS47: =AR47-AQ47 -> -41655 | AT47: Acta de compromiso | AU47: Citaciones
B48: 044-2014 | C48: 1308173 | E48: RESIDUOS SOLIDOS | F48: - | G48: Sensibilización | H48: Solicitan sensibilización en el sector por inadecuada disposición de residuos sólidos | I48: Comunidad | T48: No registra dirección | U48: no reporta | V48: no reporta | W48: Bloques 7.13, 7.14, 7.4, 7.5, 7.6, 3.5, 3.4, 4.1, 2.2, 3 Señorial | AH48: No registra dirección | AI48: no reporta | AJ48: no reporta | AK48: Loma del Barro | AP48: 7 | AQ48: 41653 | AR48: 41656 | AS48: =AR48-AQ48 -> 3 | AT48: Acta de compromiso | AU48: Citaciones | AW48: 41656 | AX48: A.Restrepo - S.Ossa | AY48: 41656 | CF48: 41673
A49: QRS 7409 | B49: 045-2014 | C49: 1308172 - 110544 | F49: - | G49: Sensibilización | H49: Solicitan sensibilización en el sector por inadecuada disposición de residuos sólidos | I49: Comunidad | T49: No registra dirección | U49: no reporta | V49: no reporta | W49: Unidad Residencial las Cometas | X49: CL | Y49: 34 | Z49: DD | AA49: SUR | AH49: =CONCATENATE(X49," ",Y49," ",Z49," ",AA49," ",AB49," ",AC49," ",AD49," ",AE49," ",AF49," ",AG49) -> CL 34 DD SUR | AI49: no reporta | AJ49: no reporta | AK49: Inmaculada | AP49: 5 | AQ49: 41653 | AR49: 41652 | AS49: =AR49-AQ49 -> -1 | AT49: Acta de compromiso | AU49: Auto de archivo | AW49: 41652 | AX49: A.Restrepo - S.Ossa | AY49: 41652
B50: 046-2014 | C50: 1307802 | D50: HÍDRICO | F50: - | H50: Requerimiento para obras de protección a fuente la Zuñiga | I50: De oficio - Autoridad Ambiental Delegada | T50: No registra dirección | U50: no reporta | V50: 3394000 | W50: Conjunto Residencial Allegro P.H | X50: KR | Y50: 27 | AB50: 20 | AD50: 181 | AE50: SUR | AH50: =CONCATENATE(X50," ",Y50," ",Z50," ",AA50," ",AB50," ",AC50," ",AD50," ",AE50," ",AF50," ",AG50) -> KR 27 20 181 SUR | AI50: no reporta | AJ50: 5702506 | AK50: Zuñiga | AP50: 4 | AQ50: 41662 | AR50: 42904 | AS50: =AR50-AQ50 -> 1242 | AU50: Auto de archivo
B51: 047-2014 | C51: 1308144 | E51: RESIDUOS SOLIDOS | F51: - | H51: Disponen las basuras en dias y horas no autorizadas | I51: De oficio - Inspección Ambiental | T51: No registra dirección | U51: no reporta | V51: 3394072 | W51: Taberna El Barril | X51: DG | Y51: 31 | Z51: E | AB51: 33 | AC51: A | AD51: 26 | AE51: SUR | AH51: =CONCATENATE(X51," ",Y51," ",Z51," ",AA51," ",AB51," ",AC51," ",AD51," ",AE51," ",AF51," ",AG51) -> DG 31 E 33 A 26 SUR | AI51: no reporta | AJ51: no reporta | AK51: La Magnolia | AP51: 9 | AQ51: 41662 | AR51: 41680 | AS51: =AR51-AQ51 -> 18 | AT51: Acta de compromiso | AU51: Auto de archivo | CF51: 41778
B52: 048-2014 | C52: 1308165 | E52: RESIDUOS SOLIDOS | F52: - | H52: Estan haciendo tala de varios arboles por el sector La Esperanza | I52: Luz Elena Rios | T52: Km 12 via Escobero - Condominio Beranda | U52: no reporta | V52: 3414519 | W52: Por definir | AH52: Predios 697, 181, 182 | AI52: no reporta | AJ52: no reporta | AL52: Las Palmas | AP52: 12 | AQ52: 41663 | AR52: 41775 | AS52: =AR52-AQ52 -> 112 | AT52: Remisión u otros | AU52: Verificación | AW52: 41775 | AX52: L. Taborda | AY52: 41775
B53: 049-2014 | C53: 1308167 | E53: RESIDUOS SOLIDOS | F53: - | H53: El señor es de la cooperativa Preambiental y deja la basura en la esquina los Lunes y Jueves | I53: Nancy Zapata | J53: TR | K53: 34 | L53: E | M53: SUR | N53: 33 | P53: 13 | S53: 301 | T53: =CONCATENATE(J53," ",K53," ",L53," ",M53," ",N53," ",O53," ",P53," ",Q53," ",R53," ",S53) -> TR 34 E SUR 33 13 301 | U53: 42980444 | V53: 3316196 | W53: Germán | X53: TR | Y53: 34 | Z53: E | AA53: SUR | AB53: 33 | AH53: =CONCATENATE(X53," ",Y53," ",Z53," ",AA53," ",AB53," ",AC53," ",AD53," ",AE53," ",AF53," ",AG53) -> TR 34 E SUR 33 | AI53: no reporta | AJ53: no reporta | AK53: Los Naranjos | AP53: 9 | AQ53: 41663 | AR53: 41675 | AS53: =AR53-AQ53 -> 12 | AT53: Acta de compromiso | AU53: Verificación
B54: 050-2014 | C54: 1308174 | D54: FLORA | F54: - | H54: Corta de vegetación nativa en predio privado | I54: Olga Elena Mejia | T54: Finca Las Palmitas | U54: no reporta | V54: 3104626390 | W54: Familia Gutierrez | AH54: No registra dirección | AI54: no reporta | AJ54: no reporta | AL54: Las Palmas | AP54: 12 | AQ54: 41666 | AS54: =AR54-AQ54 -> -41666 | AT54: Acta de compromiso | AU54: Visitas técnicos
B55: 051-2014 | C55: 1308193 - 1309733 | E55: RESIDUOS SOLIDOS | F55: - | H55: Material de construcción y escombros en el área pública | I55: De oficio - Inspección Ambiental | T55: No registra dirección | U55: no reporta | V55: 3394072 | W55: Covin S.A - Proyecto Ambar | X55: KR | Y55: 46 | AB55: 7 | AD55: 103 | AH55: =CONCATENATE(X55," ",Y55," ",Z55," ",AA55," ",AB55," ",AC55," ",AD55," ",AE55," ",AF55," ",AG55) -> KR 46 7 103 | AI55: 811021433-9 | AJ55: 3115676 | AK55: Alto de Misael | AP55: 3 | AQ55: 41666 | AR55: 41666 | AS55: =AR55-AQ55 -> 0 | AT55: Comparendo ambiental | AU55: Auto de archivo | AW55: 41666 | AX55: F. Villarraga | AY55: 41666 | BV55: 41814 | BW55: 41814 | CF55: 41940
B56: 052-2014 | C56: 1308178 - 1308223 | E56: RESIDUOS SOLIDOS | F56: - | H56: Escombros y tablillas dejadas en el espacio público | I56: Anónimo | T56: No registra dirección | U56: no reporta | V56: 3394072 | W56: Henry Carvajal | X56: TR | Y56: 32 | Z56: A | AA56: SUR | AB56: 29 | AD56: 54 | AH56: =CONCATENATE(X56," ",Y56," ",Z56," ",AA56," ",AB56," ",AC56," ",AD56," ",AE56," ",AF56," ",AG56) -> TR 32 A SUR 29 54 | AI56: no reporta | AJ56: no reporta | AK56: Alto de Misael | AP56: 3 | AQ56: 41666 | AR56: 41688 | AS56: =AR56-AQ56 -> 22 | AT56: Acta de compromiso | AU56: Auto de archivo | AW56: 41688 | AX56: L. Taborda | AY56: 41688 | CF56: 41689
B57: 053-2014 | C57: 1308177 | E57: RESIDUOS SOLIDOS | F57: - | H57: El mercado La Vaquita hace manejo inadecuado de residuos en dias y horas no autorizadas | I57: Comunidad | T57: No registra dirección | U57: no reporta | V57: no reporta | W57: Mercados La Vaquita | X57: CL | Y57: 37 | AA57: SUR | AB57: 40 | AH57: =CONCATENATE(X57," ",Y57," ",Z57," ",AA57," ",AB57," ",AC57," ",AD57," ",AE57," ",AF57," ",AG57) -> CL 37 SUR 40 | AI57: no reporta | AJ57: no reporta | AK57: Zona centro | AP57: 9 | AQ57: 41666 | AR57: 41676 | AS57: =AR57-AQ57 -> 10 | AT57: Acta de compromiso | AU57: Verificación
B58: 054-2014 | C58: 102695 | D58: HÍDRICO | F58: - | H58: Perjuicios a viviendas por aguas de nacimiento | I58: CTGRD - David Sanchez Cárdenas | J58: DG | K58: 30 | N58: 34 | O58: B | P58: 22 | Q58: SUR | T58: =CONCATENATE(J58," ",K58," ",L58," ",M58," ",N58," ",O58," ",P58," ",Q58," ",R58," ",S58) -> DG 30 34 B 22 SUR | U58: no reporta | V58: 3323902 | W58: Por definir | AH58: No registra dirección | AI58: no reporta | AJ58: no reporta | AK58: Uribe Angel | AP58: 3 | AQ58: 41659 | AS58: =AR58-AQ58 -> -41659 | AT58: Acta de compromiso | AU58: Visitas técnicos
A59: 411-2012 | B59: 055-2014 | C59: 1307971 | D59: HÍDRICO | F59: - | H59: Afectación de predio por entrega de aguas lluvias | I59: De oficio - Autoridad Ambiental Delegada | T59: No registra dirección | U59: no reporta | V59: 3394000 | W59: Parcelación Valle Alto | AH59: No registra dirección | AI59: no reporta | AJ59: no reporta | AL59: Las Palmas | AP59: 12 | AQ59: 41653 | AS59: =AR59-AQ59 -> -41653 | AT59: Acta de compromiso | AU59: Auto de archivo
B60: 056-2014 | C60: 1308214 | E60: RESIDUOS SOLIDOS | F60: - | H60: Residuos de poda y zonas verdes | I60: Comunidad | T60: No registra dirección | U60: no reporta | V60: no reporta | W60: Torre Comcel | X60: KR | Y60: 41 | Z60: B | AB60: 44 | AD60: 9 | AE60: SUR | AH60: =CONCATENATE(X60," ",Y60," ",Z60," ",AA60," ",AB60," ",AC60," ",AD60," ",AE60," ",AF60," ",AG60) -> KR 41 B 44 9 SUR | AI60: no reporta | AJ60: no reporta | AK60: El Dorado | AP60: 7 | AQ60: 41667 | AR60: 41779 | AS60: =AR60-AQ60 -> 112 | AT60: Acta de compromiso | AU60: Auto de archivo | AW60: 41779 | AX60: L. Taborda | AY60: 41779 | CF60: 41779
B61: 057-2014 | C61: 1308202 | D61: HÍDRICO | F61: - | H61: Afectación al abastecimiento de agua de comunidad cercana y corta de arboles en el sitio | I61: Joaquin Buitrago | T61: No registra dirección | U61: no reporta | V61: 5381038 | W61: Amparo Sierra | AH61: No registra dirección | AI61: no reporta | AJ61: no reporta | AL61: Pantanillo | AP61: 13 | AQ61: 41667 | AR61: 41691 | AS61: =AR61-AQ61 -> 24 | AT61: Remisión u otros | AU61: Auto de archivo | AW61: 41691 | AX61: J. Guzman - F. Villarraga | AY61: 41691 | CF61: 41691 | CG61: 41691
A62: I.T 132691 - Oficio 132698 | B62: 058-2014 | C62: 1308233 | E62: RESIDUOS SOLIDOS | F62: - | H62: Acumulación de residuos en lote del Municipio | I62: Nora Grajales - Diana Velasquez | J62: KR | K62: 30 | N62: 41 | O62: BB | P62: 42 | Q62: SUR | T62: =CONCATENATE(J62," ",K62," ",L62," ",M62," ",N62," ",O62," ",P62," ",Q62," ",R62," ",S62) -> KR 30 41 BB 42 SUR | U62: no reporta | V62: 3334963 - 3331649 | W62: Varios usuarios - Municipio | AH62: No registra dirección | AI62: no reporta | AJ62: no reporta | AK62: San Rafael | AP62: 6 | AQ62: 41668 | AR62: 41780 | AS62: =AR62-AQ62 -> 112 | AT62: Acta de compromiso | AU62: Visitas patrulleros | AW62: 41780 | AX62: C. Rojas - C. Calle | AY62: 41786
B63: 059-2014 | C63: 1308236 | E63: RESIDUOS SOLIDOS | F63: - | H63: Solicitan control de punto negro de residuos | I63: De oficio - Enviaseo | T63: No registra dirección | U63: no reporta | V63: 4600800 | W63: Varios usuarios | X63: CL | Y63: 33 | AA63: SUR | AB63: 43 | AC63: A | AH63: =CONCATENATE(X63," ",Y63," ",Z63," ",AA63," ",AB63," ",AC63," ",AD63," ",AE63," ",AF63," ",AG63) -> CL 33 SUR 43 A | AI63: no reporta | AJ63: no reporta | AK63: San Marcos | AP63: 2 | AQ63: 41668 | AS63: =AR63-AQ63 -> -41668 | AT63: Comparendo ambiental | AU63: Visitas patrulleros | AW63: 41681 | AX63: L. Garcia - J. Alvarez | AY63: 41681
B64: 060-2014 | C64: 1308247 | E64: RESIDUOS SOLIDOS | F64: - | H64: Acumulación de residuos de frutas en especio público | I64: Marta Cortes | J64: TR | K64: 34 | L64: B | M64: SUR | N64: 32 | O64: B | P64: 65 | T64: =CONCATENATE(J64," ",K64," ",L64," ",M64," ",N64," ",O64," ",P64," ",Q64," ",R64," ",S64) -> TR 34 B SUR 32 B 65 | U64: no reporta | V64: 3335325 | W64: Empresa Pulpa de Frutas | X64: TR | Y64: 34 | Z64: B | AA64: SUR | AB64: 32 | AC64: B | AD64: 65 | AH64: =CONCATENATE(X64," ",Y64," ",Z64," ",AA64," ",AB64," ",AC64," ",AD64," ",AE64," ",AF64," ",AG64) -> TR 34 B SUR 32 B 65 | AI64: no reporta | AJ64: no reporta | AK64: Obrero | AP64: 9 | AQ64: 41669 | AS64: =AR64-AQ64 -> -41669 | AT64: Acta de compromiso | AU64: Visitas patrulleros | AW64: 41681 | AX64: L. Garcia - J. Alvarez | AY64: 41681
B65: 061-2014 | C65: 1308272 | E65: RESIDUOS SOLIDOS | F65: - | H65: Comparendo No 0557 por Escombros en espacio público | I65: De oficio - Inspección Ambiental | T65: No registra dirección | U65: no reporta | V65: 3394072 | W65: Beatriz Montoya | X65: KR | Y65: 42 | Z65: C | AB65: 48 | AC65: C | AD65: 43 | AE65: SUR | AF65: 2.3 | AG65: 504 | AH65: =CONCATENATE(X65," ",Y65," ",Z65," ",AA65," ",AB65," ",AC65," ",AD65," ",AE65," ",AF65," ",AG65) -> KR 42 C 48 C 43 SUR 2.3 504 | AI65: 42887956 | AJ65: 3325329 | AK65: Loma del Barro | AP65: 7 | AQ65: 41670 | AR65: 41670 | AS65: =AR65-AQ65 -> 0 | AT65: Comparendo ambiental | AU65: Auto de inicio | AW65: 41670 | AX65: J. Guzman | AY65: 41670
B66: 062-2014 | C66: 1308271 | E66: RESIDUOS SOLIDOS | F66: - | H66: Comparendo No 0558 por Escombros en espacio público | I66: De oficio - Inspección Ambiental | T66: No registra dirección | U66: no reporta | V66: 3394072 | W66: Marina Jimenez | X66: KR | Y66: 42 | AB66: 48 | AC66: C | AD66: 15 | AE66: SUR | AF66: 3.1 | AG66: 402 | AH66: =CONCATENATE(X66," ",Y66," ",Z66," ",AA66," ",AB66," ",AC66," ",AD66," ",AE66," ",AF66," ",AG66) -> KR 42 48 C 15 SUR 3.1 402 | AI66: 32329930 | AJ66: no reporta | AK66: Loma del Barro | AP66: 7 | AQ66: 41670 | AR66: 41670 | AS66: =AR66-AQ66 -> 0 | AT66: Comparendo ambiental | AU66: Auto de inicio | AW66: 41670 | AX66: J. Guzman | AY66: 41670
B67: 063-2014 | C67: 1308243 | E67: RESIDUOS SOLIDOS | F67: - | H67: Solicitan sensibilización en el sector por inadecuada disposición de residuos sólidos | I67: De oficio - Enviaseo - Aracely Tamayo | J67: CL | K67: 38 | M67: SUR | N67: 40 | O67: A | P67: 18 | T67: =CONCATENATE(J67," ",K67," ",L67," ",M67," ",N67," ",O67," ",P67," ",Q67," ",R67," ",S67) -> CL 38 SUR 40 A 18 | U67: no reporta | V67: 3329299 | W67: Varios usuarios | AH67: No registra dirección | AI67: no reporta | AJ67: no reporta | AK67: Zona centro | AP67: 9 | AQ67: 41669 | AS67: =AR67-AQ67 -> -41669 | AT67: Acta de compromiso | AU67: Visitas patrulleros
B68: 064-2014 | C68: 1308244 | E68: RESIDUOS SOLIDOS | F68: - | H68: Solicitan sensibilización en el sector por inadecuada disposición de residuos sólidos | I68: De oficio - Enviaseo - Alba Alicia Benavides | J68: CL | K68: 38 | L68: A | M68: SUR | N68: 43 | P68: 4 | T68: =CONCATENATE(J68," ",K68," ",L68," ",M68," ",N68," ",O68," ",P68," ",Q68," ",R68," ",S68) -> CL 38 A SUR 43 4 | U68: no reporta | V68: 3319671 | W68: Varios usuarios | X68: CL | Y68: 38 | Z68: A | AA68: SUR | AB68: 43 | AH68: =CONCATENATE(X68," ",Y68," ",Z68," ",AA68," ",AB68," ",AC68," ",AD68," ",AE68," ",AF68," ",AG68) -> CL 38 A SUR 43 | AI68: no reporta | AJ68: no reporta | AK68: Zona centro | AP68: 9 | AQ68: 41669 | AS68: =AR68-AQ68 -> -41669 | AT68: Acta de compromiso | AU68: Visitas patrulleros | AW68: 41681 | AX68: L. Garcia - J. Alvarez | AY68: 41681
B69: 065-2014 | C69: 105628 | D69: FAUNA DOMÉSTICA | F69: - | H69: Solicitan verificar tenencia de mascotas peligrosas | I69: De oficio - Inspección Espacio Público | T69: No registra dirección | U69: no reporta | V69: 3394000 | W69: Varios usuarios | X69: KR | Y69: 24 | Z69: E | AB69: 40 | AD69: 140 | AE69: SUR | AH69: =CONCATENATE(X69," ",Y69," ",Z69," ",AA69," ",AB69," ",AC69," ",AD69," ",AE69," ",AF69," ",AG69) -> KR 24 E 40 140 SUR | AI69: no reporta | AJ69: no reporta | AK69: El Salado | AP69: 6 | AQ69: 41642 | AR69: 41680 | AS69: =AR69-AQ69 -> 38 | AT69: Acta de compromiso | AU69: Auto de archivo | AW69: 41680 | AX69: J. Restrepo - S. Bustamante - C. Rojas | AY69: 41680 | CF69: 41779
B70: 066-2014 | C70: 1307744 - 110545 | D70: FAUNA DOMÉSTICA | F70: - | H70: Paseadores de perros que manejan animales sin trailla y con muchos | I70: Anónimo | T70: No registra dirección | U70: no reporta | V70: no reporta | W70: Por definir | X70: CL | Y70: 39 | AA70: SUR | AB70: 43 | AC70: A | AD70: 30 | AH70: =CONCATENATE(X70," ",Y70," ",Z70," ",AA70," ",AB70," ",AC70," ",AD70," ",AE70," ",AF70," ",AG70) -> CL 39 SUR 43 A 30 | AI70: no reporta | AJ70: no reporta | AK70: Alcalá | AP70: 8 | AQ70: 41674 | AR70: 41697 | AS70: =AR70-AQ70 -> 23 | AT70: Acta de compromiso | AU70: Auto de archivo | AW70: 41779 | AX70: L. Taborda | AY70: 41779 | BL70: 41697 | CF70: 41779
B71: 067-2014 | C71: 1308248 | E71: RESIDUOS SOLIDOS | F71: - | H71: Usuarios que han dejado escombros en el espacio público | I71: Comunidad | J71: CL | K71: 36 | L71: E | M71: SUR | N71: 27 | T71: =CONCATENATE(J71," ",K71," ",L71," ",M71," ",N71," ",O71," ",P71," ",Q71," ",R71," ",S71) -> CL 36 E SUR 27 | U71: no reporta | V71: no reporta | W71: Gloria, Blanca, Jaime Cardona | X71: CL | Y71: 36 | Z71: E | AA71: SUR | AB71: 27 | AC71: G | AD71: 86 | AG71: 1,2,3 | AH71: =CONCATENATE(X71," ",Y71," ",Z71," ",AA71," ",AB71," ",AC71," ",AD71," ",AE71," ",AF71," ",AG71) -> CL 36 E SUR 27 G 86 1,2,3 | AI71: no reporta | AJ71: no reporta | AK71: La Pradera | AP71: 5 | AQ71: 41669 | AR71: 41677 | AS71: =AR71-AQ71 -> 8 | AT71: Acta de compromiso | AU71: Auto de archivo | AW71: 41677 | AX71: L. Garcia - J. Alvarez | AY71: 41680 | CF71: 41778
B72: 068-2014 | C72: 1308249-132056 | E72: RESIDUOS SOLIDOS | F72: - | H72: Residuos solidos dejados por recicladores informales | I72: Alexis Parra | T72: No registra dirección | U72: no reporta | V72: 3311847-3695770 | W72: Varios usuarios | X72: CL | Y72: 37 | AA72: SUR | AB72: 33 | AD72: 14 | AH72: =CONCATENATE(X72," ",Y72," ",Z72," ",AA72," ",AB72," ",AC72," ",AD72," ",AE72," ",AF72," ",AG72) -> CL 37 SUR 33 14 | AI72: no reporta | AJ72: no reporta | AK72: Los Naranjos | AP72: 9 | AQ72: 41669 | AS72: =AR72-AQ72 -> -41669 | AT72: Acta de compromiso | AU72: Visitas patrulleros | AW72: 41682 | AX72: C. Calle- C.Rojas | AY72: 41696
B73: 069-2014 | C73: 1308250 | D73: AIRE | F73: - | H73: Contaminación por emisiones de polvo y ruido | I73: Eida Margarita Muñoz | J73: TR | K73: 32 | L73: A | M73: SUR | N73: 31 | O73: E | P73: 50 | T73: =CONCATENATE(J73," ",K73," ",L73," ",M73," ",N73," ",O73," ",P73," ",Q73," ",R73," ",S73) -> TR 32 A SUR 31 E 50 | U73: no reporta | V73: 5990412 | W73: Por definir | X73: TR | Y73: 32 | Z73: A | AA73: SUR | AB73: 31 | AC73: E | AD73: 40 | AH73: =CONCATENATE(X73," ",Y73," ",Z73," ",AA73," ",AB73," ",AC73," ",AD73," ",AE73," ",AF73," ",AG73) -> TR 32 A SUR 31 E 40 | AI73: no reporta | AJ73: no reporta | AK73: La Magnolia | AP73: 9 | AQ73: 41669 | AR73: 41680 | AS73: =AR73-AQ73 -> 11 | AT73: Acta de compromiso | AU73: Auto de archivo | AW73: 41680 | AX73: J. Restrepo - S. Bustamante - C. Rojas | AY73: 41680 | CF73: 41779
B74: 070-2014 | C74: 1308256 | E74: RESIDUOS SOLIDOS | F74: - | H74: Escombros dejados en el espacio público | I74: Anónimo | T74: No registra dirección | U74: no reporta | V74: no reporta | W74: Danilo | X74: CL | Y74: 38 | Z74: A | AA74: SUR | AB74: 43 | AD74: 46 | AH74: =CONCATENATE(X74," ",Y74," ",Z74," ",AA74," ",AB74," ",AC74," ",AD74," ",AE74," ",AF74," ",AG74) -> CL 38 A SUR 43 46 | AI74: no reporta | AJ74: no reporta | AK74: Zona centro | AP74: 9 | AQ74: 41669 | AR74: 41680 | AS74: =AR74-AQ74 -> 11 | AT74: Acta de compromiso | AU74: Auto de archivo | AW74: 41680 | AX74: C. Calle- C.Rojas | AY74: 41680 | CF74: 41779
B75: 071-2014 | C75: 1308257-1314359 | D75: LOTE-PREDIO | F75: - | H75: Perjucios por el manejo de aguas lluvias de Urbanización Trentto | I75: Comunidad | T75: No registra dirección | U75: no reporta | V75: no reporta | W75: Urbanización Trentto | X75: KR | Y75: 27 | Z75: D | AB75: 27 | AE75: SUR | AG75: 123 | AH75: =CONCATENATE(X75," ",Y75," ",Z75," ",AA75," ",AB75," ",AC75," ",AD75," ",AE75," ",AF75," ",AG75) -> KR 27 D 27 SUR 123 | AI75: no reporta | AJ75: no reporta | AK75: El Esmeraldal | AP75: 4 | AQ75: 41669 | AS75: =AR75-AQ75 -> -41669 | AT75: Acta de compromiso | AU75: Visitas técnicos
B76: 072-2014 | C76: 1308261 | D76: FAUNA DOMÉSTICA | F76: - | H76: No recogen los excrementos de sus mascotas | I76: Raul Diaz | J76: CL | K76: 46 | M76: SUR | N76: 46 | P76: 8 | T76: =CONCATENATE(J76," ",K76," ",L76," ",M76," ",N76," ",O76," ",P76," ",Q76," ",R76," ",S76) -> CL 46 SUR 46 8 | U76: 70032279 | V76: 3127836442 | W76: Por definir | X76: CL | Y76: 46 | AA76: SUR | AB76: 46 | AC76: B | AD76: 25 | AH76: =CONCATENATE(X76," ",Y76," ",Z76," ",AA76," ",AB76," ",AC76," ",AD76," ",AE76," ",AF76," ",AG76) -> CL 46 SUR 46 B 25 | AI76: no reporta | AJ76: no reporta | AK76: Primavera | AP76: 8 | AQ76: 41670 | AS76: =AR76-AQ76 -> -41670 | AT76: Acta de compromiso | AU76: Visitas patrulleros | AW76: 41682 | AX76: L. Garcia - J. Alvarez | AY76: 41682
B77: 073-2014 | C77: 1308242 | E77: RESIDUOS SOLIDOS | F77: - | H77: Solicitan sensibilización en el sector por inadecuada disposición de residuos sólidos | I77: Farmaceutica Herson | J77: KR | K77: 48 | N77: 48 | P77: 75 | Q77: SUR | S77: 158 | T77: =CONCATENATE(J77," ",K77," ",L77," ",M77," ",N77," ",O77," ",P77," ",Q77," ",R77," ",S77) -> KR 48 48 75 SUR 158 | U77: no reporta | V77: 4483424 | W77: Varios usuarios | AH77: No registra dirección | AI77: no reporta | AJ77: no reporta | AK77: Las Vegas | AP77: 1 | AQ77: 41669 | AR77: 41682 | AS77: =AR77-AQ77 -> 13 | AT77: Acta de compromiso | AU77: Auto de archivo | AW77: 41682 | AX77: J. Restrepo - S. Bustamante - C. Rojas | AY77: 41682 | AZ77: 41701 | BA77: J. Restrepo - S. Bustamante | BB77: 41702 | CF77: 41717
B78: 074-2014 | C78: 1308274 | E78: RESIDUOS SOLIDOS | F78: - | H78: Solicitan control de manejo de residuos solidos de esta vivienda | I78: Anónimo | T78: No registra dirección | U78: no reporta | V78: no reporta | W78: Alba Aristizabal | AF78: 1.1 | AG78: 402 | AH78: =CONCATENATE(X78," ",Y78," ",Z78," ",AA78," ",AB78," ",AC78," ",AD78," ",AE78," ",AF78," ",AG78) -> 1.1 402 | AI78: 42879035 | AJ78: 3332915 | AK78: El Dorado | AP78: 7 | AQ78: 41670 | AR78: 41682 | AS78: =AR78-AQ78 -> 12 | AT78: Acta de compromiso | AU78: Auto de archivo | AW78: 41682 | AX78: J. Restrepo - S. Bustamante - C. Rojas | AY78: 41683 | CF78: 41687
B79: 075-2014 | C79: 1308392 | E79: RESIDUOS SOLIDOS | F79: 1 | H79: Manejo inadecuado de residuos solidos - Frisby S.A - Comparendo 556 | I79: De Oficio | T79: No registra dirección | U79: no reporta | V79: no reporta | W79: Frisby S.A | X79: CL | Y79: 38 | AA79: SUR | AB79: 42 | AH79: =CONCATENATE(X79," ",Y79," ",Z79," ",AA79," ",AB79," ",AC79," ",AD79," ",AE79," ",AF79," ",AG79) -> CL 38 SUR 42 | AI79: 8914085845 | AJ79: no reporta | AK79: Zona Centro | AM79: 022 | AP79: 9 | AQ79: 41315 | AR79: 41315 | AS79: =AR79-AQ79 -> 0 | AT79: Comparendo ambiental | AU79: Auto de archivo | CF79: 41841
B80: 076-2014 | C80: 1308046 | D80: FAUNA DOMÉSTICA | F80: - | H80: Perro que sueltan no le recogen excremetos y ataca a vecinos | I80: Marta Palacio | J80: CL | K80: 36 | L80: D | M80: SUR | N80: 26 | O80: A | P80: 6 | S80: 116 | T80: =CONCATENATE(J80," ",K80," ",L80," ",M80," ",N80," ",O80," ",P80," ",Q80," ",R80," ",S80) -> CL 36 D SUR 26 A 6 116 | U80: 43613625 | V80: 5971975 | W80: Jhoany | X80: CL | Y80: 36 | Z80: D | AA80: SUR | AB80: 26 | AC80: A | AD80: 6 | AG80: 115 | AH80: =CONCATENATE(X80," ",Y80," ",Z80," ",AA80," ",AB80," ",AC80," ",AD80," ",AE80," ",AF80," ",AG80) -> CL 36 D SUR 26 A 6 115 | AI80: 70546060 | AJ80: 3217972816 | AL80: El Escobero | AP80: 10 | AQ80: 41675 | AS80: =AR80-AQ80 -> -41675 | AT80: Acta de compromiso | AU80: Auto de archivo
B81: 077-2014 | C81: 1308135 | D81: LOTE-PREDIO | H81: Lote enmalezado y sin cerramiento | I81: Sonia Rua | J81: KR | K81: 42 | L81: A | N81: 26 | P81: 217 | Q81: SUR | S81: 301 | T81: =CONCATENATE(J81," ",K81," ",L81," ",M81," ",N81," ",O81," ",P81," ",Q81," ",R81," ",S81) -> KR 42 A 26 217 SUR 301 | U81: 42899695 | V81: 3334639 | W81: Por definir | AH81: =CONCATENATE(X81," ",Y81," ",Z81," ",AA81," ",AB81," ",AC81," ",AD81," ",AE81," ",AF81," ",AG81) | AI81: no reporta | AJ81: no reporta | AK81: Las Orquideas | AP81: 3 | AQ81: 41661 | AS81: =AR81-AQ81 -> -41661 | AT81: Acta de compromiso | AU81: Citaciones
B82: 078-2014 | C82: 1308282 | D82: FLORA | H82: Tala de arboles sector los gallegos | I82: anonimo | T82: =CONCATENATE(J82," ",K82," ",L82," ",M82," ",N82," ",O82," ",P82," ",Q82," ",R82," ",S82) | U82: no reporta | V82: no reporta | W82: Por definir | AH82: =CONCATENATE(X82," ",Y82," ",Z82," ",AA82," ",AB82," ",AC82," ",AD82," ",AE82," ",AF82," ",AG82) | AI82: no reporta | AJ82: no reporta | AL82: Pantanillo | AN82: 005 | AP82: 13 | AQ82: 41673 | AR82: 41778 | AS82: =AR82-AQ82 -> 105 | AT82: Acta de compromiso | AU82: Auto de archivo | CF82: 41787
A83: 13-1888 | B83: 079-2014 | C83: 102708 | D83: HÍDRICO | H83: Descarga de agua que desestabiliz talud | I83: Mauricio Puerta Arango | J83: CL | K83: 5 | L83: G | N83: 32 | P83: 110 | S83: 1601 | T83: =CONCATENATE(J83," ",K83," ",L83," ",M83," ",N83," ",O83," ",P83," ",Q83," ",R83," ",S83) -> CL 5 G 32 110 1601 | U83: 70100245 | V83: 3104140100 | W83: La Calleja | AH83: =CONCATENATE(X83," ",Y83," ",Z83," ",AA83," ",AB83," ",AC83," ",AD83," ",AE83," ",AF83," ",AG83) | AI83: no reporta | AJ83: no reporta | AL83: Santa Catalina | AP83: 10 | AQ83: 41655 | AR83: 41667 | AS83: =AR83-AQ83 -> 12 | AT83: Acta de compromiso | AU83: Auto de archivo | AW83: 28/01/204 | AX83: J. Guzman | AY83: 41667 | CF83: 41690
B84: 080-2014 | C84: 1308325 | E84: RESIDUOS SOLIDOS | G84: Sensibilización | H84: Disposición inadecuada de residuos solidos | I84: Comunidad | J84: CL | K84: 45 | M84: SUR | N84: 42 | O84: C | T84: =CONCATENATE(J84," ",K84," ",L84," ",M84," ",N84," ",O84," ",P84," ",Q84," ",R84," ",S84) -> CL 45 SUR 42 C | U84: no reporta | V84: no reporta | W84: Edificio Petra | X84: KR | Y84: 42 | Z84: C | AB84: 45 | AC84: B | AD84: 64 | AE84: SUR | AG84: 401 - 501 | AH84: =CONCATENATE(X84," ",Y84," ",Z84," ",AA84," ",AB84," ",AC84," ",AD84," ",AE84," ",AF84," ",AG84) -> KR 42 C 45 B 64 SUR 401 - 501 | AI84: no reporta | AJ84: no reporta | AK84: La Paz | AM84: 011 | AP84: 7 | AQ84: 41675 | AR84: 41676 | AS84: =AR84-AQ84 -> 1 | AT84: Acta de compromiso | AU84: Auto de archivo | AW84: 41674 | AX84: A.Restrepo - S.Ossa | AY84: 41681 | CF84: 41715
B85: 081-2014 | C85: 1308287-132282 | E85: RESIDUOS SOLIDOS | H85: Disposición inadecuada de residuos solidos | I85: Comunidad | T85: =CONCATENATE(J85," ",K85," ",L85," ",M85," ",N85," ",O85," ",P85," ",Q85," ",R85," ",S85) | U85: no reporta | V85: no reporta | W85: Nora Ruiz | X85: KR | Y85: 36 | AB85: 38 | AD85: 60 | AE85: SUR | AG85: 201 | AH85: =CONCATENATE(X85," ",Y85," ",Z85," ",AA85," ",AB85," ",AC85," ",AD85," ",AE85," ",AF85," ",AG85) -> KR 36 38 60 SUR 201 | AI85: no reporta | AJ85: no reporta | AK85: Mesa | AP85: 9 | AQ85: 41673 | AR85: 41702 | AS85: =AR85-AQ85 -> 29 | AT85: Acta de compromiso | AU85: Auto de archivo | AW85: 41702 | AX85: C. Rojas - C. Calle | AY85: 41704 | CF85: 41704
A86: correo | B86: 082-2014 | C86: 1308289-132269 | E86: RESIDUOS SOLIDOS | H86: Disposición inadecuada de residuos solidos | I86: Mauricio Villa - jose253@une.net.co | T86: =CONCATENATE(J86," ",K86," ",L86," ",M86," ",N86," ",O86," ",P86," ",Q86," ",R86," ",S86) | U86: no reporta | V86: no reporta | W86: Berta Oliva Loaiza | X86: KR | Y86: 36 | AB86: 38 | AE86: SUR | AH86: =CONCATENATE(X86," ",Y86," ",Z86," ",AA86," ",AB86," ",AC86," ",AD86," ",AE86," ",AF86," ",AG86) -> KR 36 38 SUR | AI86: 21550289 | AJ86: 2715276 | AK86: Mesa | AM86: 021 | AP86: 9 | AQ86: 41673 | AR86: 41702 | AS86: =AR86-AQ86 -> 29 | AT86: Acta de compromiso | AU86: Auto de archivo | AW86: 41702 | AX86: C. Rojas - C. Calle | AY86: 41704 | CF86: 41704
A87: IT 132318 | B87: 083-2014 | C87: 1308290-1308692-132318 | D87: LOTE-PREDIO | H87: Lote enmalezado | I87: Comunidad | J87: CL | K87: 32 | L87: A | M87: SUR | N87: 28 | P87: 30 | T87: =CONCATENATE(J87," ",K87," ",L87," ",M87," ",N87," ",O87," ",P87," ",Q87," ",R87," ",S87) -> CL 32 A SUR 28 30 | U87: no reporta | V87: 6011075 | W87: Gabriel Grajales | X87: KR | Y87: 28 | AB87: 27 | AD87: 149 | AE87: SUR | AH87: =CONCATENATE(X87," ",Y87," ",Z87," ",AA87," ",AB87," ",AC87," ",AD87," ",AE87," ",AF87," ",AG87) -> KR 28 27 149 SUR | AI87: no reporta | AJ87: 3310131 | AK87: Alto de Misael | AP87: 3 | AQ87: 41673 | AR87: 41683 | AS87: =AR87-AQ87 -> 10 | AT87: Acta de compromiso | AU87: Auto de archivo | AW87: 41683 | AX87: L. Garcia - J. Alvarez | AY87: 41683 | AZ87: 41730 | BA87: C. Rojas - C. Calle | BB87: 41731 | CF87: 41690
B88: 084-2014 | C88: 1308298 | D88: FAUNA DOMÉSTICA | H88: Tenencia inadecuada de mascota, al parcer hay maltrato | I88: Juan Felipe Restrepo Gomez | J88: CL | K88: 48 | L88: C | M88: SUR | N88: 39 | O88: A | P88: 155 | S88: 142 | T88: =CONCATENATE(J88," ",K88," ",L88," ",M88," ",N88," ",O88," ",P88," ",Q88," ",R88," ",S88) -> CL 48 C SUR 39 A 155 142 | U88: 71786978 | V88: 3146390236 | W88: Gustavo Uribe Buitrago | X88: CL | Y88: 48 | Z88: C | AA88: SUR | AB88: 39 | AC88: A | AD88: 155 | AG88: 137 | AH88: =CONCATENATE(X88," ",Y88," ",Z88," ",AA88," ",AB88," ",AC88," ",AD88," ",AE88," ",AF88," ",AG88) -> CL 48 C SUR 39 A 155 137 | AI88: no reporta | AJ88: no reporta | AK88: Loma del Barro | AP88: 7 | AQ88: 41673 | AR88: 41683 | AS88: =AR88-AQ88 -> 10 | AT88: Acta de compromiso | AU88: Auto de archivo | CF88: 41715
B89: 085-2014 | C89: 1308299 | D89: FAUNA DOMÉSTICA | H89: Maltrato animal | I89: Lina Ramirez | J89: KR | K89: 26 | N89: 41 | O89: B | P89: 80 | T89: =CONCATENATE(J89," ",K89," ",L89," ",M89," ",N89," ",O89," ",P89," ",Q89," ",R89," ",S89) -> KR 26 41 B 80 | U89: 97020619051 | V89: 3321876 | W89: Jonatan Henao Grisales | X89: KR | Y89: 26 | AB89: 41 | AC89: B | AD89: 56 | AE89: SUR | AG89: 201 | AH89: =CONCATENATE(X89," ",Y89," ",Z89," ",AA89," ",AB89," ",AC89," ",AD89," ",AE89," ",AF89," ",AG89) -> KR 26 41 B 56 SUR 201 | AI89: no reporta | AJ89: no reporta | AK89: San Rafael | AM89: 004 | AP89: 6 | AQ89: 41673 | AR89: 41709 | AS89: =AR89-AQ89 -> 36 | AT89: Acta de compromiso | AU89: Auto de archivo | BL89: 41709 | BM89: 41709 | CF89: 41725
B90: 086-2014 | C90: 1308300 | E90: RESIDUO ESPECIAL | H90: Disposición inadecuada de tablas y cajones | I90: anonimo | T90: =CONCATENATE(J90," ",K90," ",L90," ",M90," ",N90," ",O90," ",P90," ",Q90," ",R90," ",S90) | U90: no reporta | V90: no reporta | W90: Sulma Muñoz | X90: DG | Y90: 29 | AB90: 33 | AD90: 48 | AE90: SUR | AG90: 130 | AH90: =CONCATENATE(X90," ",Y90," ",Z90," ",AA90," ",AB90," ",AC90," ",AD90," ",AE90," ",AF90," ",AG90) -> DG 29 33 48 SUR 130 | AI90: no reporta | AJ90: no reporta | AK90: Uribe Angel | AM90: 030 | AP90: 3 | AQ90: 41673 | AS90: =AR90-AQ90 -> -41673 | AT90: Acta de compromiso | AU90: Visitas patrulleros | AW90: 41682 | AX90: L. Garcia - J. Alvarez | AY90: 41683
B91: 087-2014 | C91: 1308307 | E91: ESCOMBROS | H91: Disposición inadecuada de residuos de construcción | I91: De oficio | T91: =CONCATENATE(J91," ",K91," ",L91," ",M91," ",N91," ",O91," ",P91," ",Q91," ",R91," ",S91) | U91: no reporta | V91: no reporta | W91: Uribe Herrera Construcciones | X91: CL | Y91: 44 | AA91: SUR | AB91: 40 | AC91: A | AD91: 15 | AH91: =CONCATENATE(X91," ",Y91," ",Z91," ",AA91," ",AB91," ",AC91," ",AD91," ",AE91," ",AF91," ",AG91) -> CL 44 SUR 40 A 15 | AI91: no reporta | AJ91: 3326728 | AK91: El Dorado | AM91: 013 | AP91: 7 | AQ91: 41674 | AR91: 41674 | AS91: =AR91-AQ91 -> 0 | AT91: Acta de compromiso | AU91: Auto de archivo | AW91: 41673 | AX91: J. Restrepo - S. Bustamante - C. Rojas | AY91: 41674 | AZ91: 41683 | BA91: L. Garcia - J. Alvarez | BB91: 41683 | CF91: 41703
B92: 088-2014 | C92: 1308308 | E92: RESIDUO ESPECIAL | H92: Disposición inadecuda de colchones - Comparendo 559 | I92: anonimo | T92: =CONCATENATE(J92," ",K92," ",L92," ",M92," ",N92," ",O92," ",P92," ",Q92," ",R92," ",S92) | U92: no reporta | V92: no reporta | W92: Alba Denis Celis | X92: KR | Y92: 24 | Z92: DB | AB92: 39 | AC92: DD | AD92: 16 | AE92: SUR | AH92: =CONCATENATE(X92," ",Y92," ",Z92," ",AA92," ",AB92," ",AC92," ",AD92," ",AE92," ",AF92," ",AG92) -> KR 24 DB 39 DD 16 SUR | AI92: 43040815 | AJ92: no reporta | AK92: El Chingui | AM92: 001 | AP92: 6 | AQ92: 41674 | AR92: 41676 | AS92: =AR92-AQ92 -> 2 | AT92: Comparendo ambiental | AU92: Auto de archivo | AW92: 41673 | AX92: J. Restrepo - S. Bustamante - C. Rojas | AY92: 41674 | BN92: 41676 | BO92: 41676 | CF92: 41787
B93: 089-2014 | C93: 1308323 | E93: ESCOMBROS | H93: Disposición inadecuada de escombros (tablilla) | I93: De oficio | T93: =CONCATENATE(J93," ",K93," ",L93," ",M93," ",N93," ",O93," ",P93," ",Q93," ",R93," ",S93) | U93: no reporta | V93: no reporta | W93: Luz Marina de Garcia | X93: CL | Y93: 45 | Z93: B | AA93: SUR | AB93: 42 | AC93: B | AD93: 19 | AG93: 201 | AH93: =CONCATENATE(X93," ",Y93," ",Z93," ",AA93," ",AB93," ",AC93," ",AD93," ",AE93," ",AF93," ",AG93) -> CL 45 B SUR 42 B 19 201 | AI93: 32335596 | AJ93: 3312385 | AK93: La Paz | AM93: 011 | AP93: 7 | AQ93: 41675 | AR93: 41675 | AS93: =AR93-AQ93 -> 0 | AT93: Acta de compromiso | AU93: Auto de archivo | AW93: 41674 | AX93: S. Bustamante | AY93: 41675 | AZ93: 41683 | BA93: L. Garcia - J. Alvarez | BB93: 41689 | CF93: 41690
B94: 090-2014 | C94: 1308345 | D94: FLORA | H94: Tala de arboles en predio al parecer del municipio | I94: anonimo | T94: =CONCATENATE(J94," ",K94," ",L94," ",M94," ",N94," ",O94," ",P94," ",Q94," ",R94," ",S94) | U94: no reporta | V94: no reporta | W94: Por definir | X94: KR | Y94: 41 | Z94: A | AB94: 46 | AC94: DD | AE94: SUR | AH94: =CONCATENATE(X94," ",Y94," ",Z94," ",AA94," ",AB94," ",AC94," ",AD94," ",AE94," ",AF94," ",AG94) -> KR 41 A 46 DD SUR | AI94: no reporta | AJ94: no reporta | AK94: La paz | AM94: 011 | AP94: 7 | AQ94: 41675 | AR94: 41683 | AS94: =AR94-AQ94 -> 8 | AT94: Acta de compromiso | AU94: Auto de archivo | CF94: 41863
B95: 091-2014 | C95: 1308347 - 1308384 | D95: FLORA | G95: Bruja Norte | H95: Verificación de intervención de tala y poda de arboles | I95: De oficio | T95: =CONCATENATE(J95," ",K95," ",L95," ",M95," ",N95," ",O95," ",P95," ",Q95," ",R95," ",S95) | U95: no reporta | V95: no reporta | W95: Constructora Capital - Jhon Jairo Gomez | X95: CL | Y95: 36 | Z95: B | AA95: SUR | AB95: 27 | AC95: A | AH95: =CONCATENATE(X95," ",Y95," ",Z95," ",AA95," ",AB95," ",AC95," ",AD95," ",AE95," ",AF95," ",AG95) -> CL 36 B SUR 27 A | AI95: 70879120 | AJ95: 2355242 | AK95: La Pradera | AM95: 016 | AP95: 5 | AQ95: 41675 | AR95: 41675 | AS95: =AR95-AQ95 -> 0 | AT95: Acta de compromiso | AU95: Verificación | AW95: 41673 | AX95: J. Guzman | AY95: 41675 | AZ95: 41677 | BA95: J. Restrepo - S. Bustamante | BB95: 41677
B96: 092-2014 | C96: 1308348 | D96: FAUNA SILVESTRE | H96: Sinsonte en espacio comun (servidumbre) | I96: De oficio | T96: =CONCATENATE(J96," ",K96," ",L96," ",M96," ",N96," ",O96," ",P96," ",Q96," ",R96," ",S96) | U96: no reporta | V96: no reporta | W96: Por definir contiguo a | X96: CL | Y96: 49 | Z96: D | AA96: SUR | AB96: 47 | AD96: 21 | AG96: 115 | AH96: =CONCATENATE(X96," ",Y96," ",Z96," ",AA96," ",AB96," ",AC96," ",AD96," ",AE96," ",AF96," ",AG96) -> CL 49 D SUR 47 21 115 | AI96: no reporta | AJ96: no reporta | AK96: Las Casitas | AM96: 008 | AP96: 8 | AQ96: 41675 | AS96: =AR96-AQ96 -> -41675 | AT96: Acta de compromiso | AU96: Visitas patrulleros | AW96: 41684 | AX96: L. Garcia - J. Alvarez | AY96: 41684
B97: 093-2014 | C97: 1308319 | D97: ESPACIO PUBLICOS VERDES | E97: ESCOMBROS | H97: Cambio de piso blando y retirar escombros del espacio público | I97: De oficio | T97: =CONCATENATE(J97," ",K97," ",L97," ",M97," ",N97," ",O97," ",P97," ",Q97," ",R97," ",S97) | U97: no reporta | V97: no reporta | W97: Por definir contiguo a | X97: CL | Y97: 40 | Z97: E | AA97: SUR | AB97: 40 | AD97: 35 | AH97: =CONCATENATE(X97," ",Y97," ",Z97," ",AA97," ",AB97," ",AC97," ",AD97," ",AE97," ",AF97," ",AG97) -> CL 40 E SUR 40 35 | AI97: no reporta | AJ97: no reporta | AK97: El Dorado | AM97: 013 | AP97: 7 | AQ97: 41674 | AR97: 41681 | AS97: =AR97-AQ97 -> 7 | AT97: Acta de compromiso | AU97: Auto de archivo | AW97: 41681 | AX97: L. Garcia - J. Alvarez | AY97: 41681 | AZ97: 41779 | BA97: L. Taborda | BB97: 41779 | CF97: 42010
B98: 094-2014 | C98: 1308352 | D98: FAUNA SILVESTRE | H98: Persona que utiliza tramperas para cazar fauna y las tiene en cautiverio | I98: Leonardo Garcia | T98: =CONCATENATE(J98," ",K98," ",L98," ",M98," ",N98," ",O98," ",P98," ",Q98," ",R98," ",S98) | U98: no reporta | V98: no reporta | W98: Por definir | X98: CL | Y98: 41 | AA98: SUR | AB98: 25 | AD98: 165 | AG98: 401 | AH98: =CONCATENATE(X98," ",Y98," ",Z98," ",AA98," ",AB98," ",AC98," ",AD98," ",AE98," ",AF98," ",AG98) -> CL 41 SUR 25 165 401 | AI98: no reporta | AJ98: no reporta | AK98: La Mina | AM98: 003 | AP98: 6 | AQ98: 41675 | AS98: =AR98-AQ98 -> -41675 | AT98: Acta de compromiso | AU98: Citaciones | AW98: 41684 | AX98: L. Garcia - J. Alvarez | AY98: 41684
B99: 095-2014 | C99: 1308359 | E99: MATERIALES DE CONSTRUCCIÓN | H99: Disposición inadecuada de material de construcción | I99: Carlos A. Uribe | J99: KR | K99: 28 | L99: B | N99: 40 | P99: 19 | Q99: SUR | T99: =CONCATENATE(J99," ",K99," ",L99," ",M99," ",N99," ",O99," ",P99," ",Q99," ",R99," ",S99) -> KR 28 B 40 19 SUR | U99: 76309814 | V99: 3024517 | W99: Albeiro Restrepo Montoya | X99: CL | Y99: 40 | AA99: SUR | AB99: 28 | AC99: B | AD99: 13 | AH99: =CONCATENATE(X99," ",Y99," ",Z99," ",AA99," ",AB99," ",AC99," ",AD99," ",AE99," ",AF99," ",AG99) -> CL 40 SUR 28 B 13 | AI99: 70553279 | AJ99: 2700276 | AK99: San José | AM99: 014 | AP99: 6 | AQ99: 41676 | AR99: 41684 | AS99: =AR99-AQ99 -> 8 | AT99: Acta de compromiso | AU99: Auto de archivo | AW99: 41684 | AX99: L. Garcia - J. Alvarez | AY99: 41684 | CF99: 41703
B100: 096-2014 | C100: 1308361 - 1310741 | D100: LOTE-PREDIO | H100: Lote que requiere mantenimiento por maleza | I100: Juan Carlos Taborda | J100: KR | K100: 42 | N100: 23 | O100: A | P100: 188 | Q100: SUR | T100: =CONCATENATE(J100," ",K100," ",L100," ",M100," ",N100," ",O100," ",P100," ",Q100," ",R100," ",S100) -> KR 42 23 A 188 SUR | U100: no reporta | V100: 5988939 | W100: Alejandro | AH100: =CONCATENATE(X100," ",Y100," ",Z100," ",AA100," ",AB100," ",AC100," ",AD100," ",AE100," ",AF100," ",AG100) | AI100: no reporta | AJ100: no reporta | AK100: Las Orquideas | AM100: 035 | AP100: 3 | AQ100: 41676 | AS100: =AR100-AQ100 -> -41676 | AT100: Acta de compromiso | AU100: Visitas patrulleros | AW100: 41684 | AX100: L. Garcia - J. Alvarez | AY100: 41684 | AZ100: 41702 | BA100: S. Bustamante - J. Restrepo | BB100: 41702 | BL100: 41738
...

Sheet 2015
AW1: ESTADO DEL PROCESO - FECHAS
AW2: Visita inicial | AZ2: Visita de verificación 1 | BC2: Visita de verificación 2 | BF2: Visita de verificación 3 | BI2: Visita de verificación 4 | BL2: Acta de compromiso - comparecencia | BN2: Auto de inicio | BP2: Descargos | BR2: Pruebas | BT2: Fallo - Decisión | BV2: Notificación - Remisión | BX2: Recurso de reposición | BZ2: Notificación - Remisión | CB2: Capacitación | CD2: Remisión Hacienda | CF2: Auto de archivo | CH2: Archivo
A3: Conexo | B3: Consecutivo | C3: Radicado | D3: Recurso afectado | E3: Comparendo | F3: Código Infracción | G3: Predios, Otros documentos, Proyecto | H3: Asunto | I3: Quejoso | J3: Tipo de vía principal | K3: N° vía principal | L3: letra | M3: Cuadrante | N3: Generadora | O3: Letra | P3: Placa | Q3: Cuadrante | R3: Bloque | S3: Interior | T3: Dirección | U3: Cedula quejoso | V3: Teléfono quejoso | W3: Infractor | X3: Tipo de vía principal | Y3: N° vía principal | Z3: letra | AA3: Cuadrante | AB3: Generadora | AC3: Letra | AD3: Placa | AE3: Cuadrante | AF3: Bloque | AG3: Interior | AH3: Dirección | AI3: Cedula Infractor | AJ3: Teléfono Infractor | AK3: Lugar Infracción Barrio | AL3: Vereda | AM3: Código Barrio | AN3: Manzana - Vereda | AO3: Predio | AP3: Zona | AQ3: Fecha de ingreso (dd/mm/aaaa) | AR3: Fecha de actuación inicial (ddmm/aaaa) | AS3: Días de atención | AT3: Destinación procedimental inicial | AU3: Estado actual | AV3: Remitido a - Observa. | AW3: Recibido - Asignado | AX3: Funcionario | AY3: Entregado | AZ3: Recibido - Asignado | BA3: Funcionario | BB3: Entregado | BC3: Recibido - Asignado | BD3: Funcionario | BE3: Entregado | BF3: Recibido - Asignado | BG3: Funcionario | BH3: Entregado | BI3: Recibido - Asignado | BJ3: Funcionario | BK3: Entregado | BL3: Recibido - Asignado | BM3: Entregado | BN3: Recibido - Asignado | BO3: Entregado | BP3: Recibido - Asignado | BQ3: Entregado | BR3: Recibido - Asignado | BS3: Entregado | BT3: Recibido - Asignado | BU3: Entregado | BV3: Recibido - Asignado | BW3: Entregado | BX3: Recibido - Asignado | BY3: Entregado | BZ3: Recibido - Asignado | CA3: Entregado | CB3: Recibido - Asignado | CC3: Entregado | CD3: Recibido - Asignado | CE3: Entregado | CF3: Recibido - Asignado | CG3: Entregado | CH3: Recibido - Asignado | CI3: Entregado
B4: 001-2015
B5: 002-2015 | C5: 1316797 | D5: FLORA | H5: Tala de guadual en zona de acueducto San José | I5: Lady Yesenia Guerra Diez | T5: No reporta | U5: 43872755 | V5: 3116240215 | W5: Valerio Calle | AH5: No reporta | AI5: no reporta | AJ5: no reporta | AL5: El Vallano | AP5: 11 | AQ5: 42006 | AR5: 42013 | AS5: =+AR5-AQ5 -> 7 | AT5: Ley 1333 de 2009 | AU5: Auto de archivo | AV5: DP | AW5: 42013 | AX5: J. Guzmán | AY5: 42013 | CF5: 42054
B6: 003-2015 | C6: 1316800 | E6: RESIDUOS SOLIDOS | H6: Acumulación de escombros y residuos ordinarios en espacio público | I6: Rosa Ospina de Giraldo | J6: CL | K6: 48 | M6: SUR | N6: 39 | P6: 12 | T6: =CONCATENATE(J6," ",K6," ",L6," ",M6," ",N6," ",O6," ",P6," ",Q6," ",R6," ",S6) -> CL 48 SUR 39 12 | U6: 32404384 | V6: 3311168 | W6: Gloria | X6: CL | Y6: 48 | AA6: SUR | AB6: 39 | AD6: 6 | AH6: =CONCATENATE(X6," ",Y6," ",Z6," ",AA6," ",AB6," ",AC6," ",AD6," ",AE6," ",AF6," ",AG6) -> CL 48 SUR 39 6 | AI6: no reporta | AJ6: no reporta | AK6: El Trianón | AP6: 7 | AQ6: 42009 | AS6: =+AR6-AQ6 -> -42009 | AT6: Acta de compromiso | AU6: Auto de archivo
B7: 004-2015 | C7: 1316802 | D7: FLORA | H7: Afectaciones a arboles sin autorización y de forma inadecuada | I7: Dario Tabares | J7: CL | K7: 26 | L7: A | M7: SUR | N7: 42 | O7: A | P7: 27 | T7: =CONCATENATE(J7," ",K7," ",L7," ",M7," ",N7," ",O7," ",P7," ",Q7," ",R7," ",S7) -> CL 26 A SUR 42 A 27 | U7: 70547027 | V7: 3315861 | W7: Edelmira Londoño | X7: CL | Y7: 26 | Z7: A | AA7: SUR | AB7: 42 | AC7: A | AD7: 27 | AH7: =CONCATENATE(X7," ",Y7," ",Z7," ",AA7," ",AB7," ",AC7," ",AD7," ",AE7," ",AF7," ",AG7) -> CL 26 A SUR 42 A 27 | AI7: no reporta | AJ7: no reporta | AK7: Las orquideas | AP7: 3 | AQ7: 42009 | AR7: 42011 | AS7: =+AR7-AQ7 -> 2 | AT7: Pendiente de tramite | AU7: Auto de archivo | AW7: 42011 | AX7: L. Garcia | AY7: 42011 | CF7: 42037
B8: 005-2015 | C8: 1316819 | E8: RESIDUOS SOLIDOS | H8: Acumulación de residuos en predio privado | I8: De oficio - Secretaria de Salud | T8: No reporta | U8: No reporta | V8: 3394000 | W8: Por determinar | X8: KR | Y8: 26 | AB8: 41 | AC8: A | AD8: 46 | AE8: SUR | AH8: =CONCATENATE(X8," ",Y8," ",Z8," ",AA8," ",AB8," ",AC8," ",AD8," ",AE8," ",AF8," ",AG8) -> KR 26 41 A 46 SUR | AI8: no reporta | AJ8: no reporta | AK8: San Rafael | AP8: 6 | AQ8: 42010 | AS8: =+AR8-AQ8 -> -42010 | AT8: Acta de compromiso | AU8: Remisión u otros | AV8: Obras Publicas - cerramiento | AW8: 42019 | AX8: L. Garcia | AY8: 42019
B9: 006-2015 | C9: 1316822 | D9: FLORA | G9: Proyecto Austral | H9: Afectación a dos arboles | I9: John Jairo Duque | J9: CL | K9: 36 | M9: SUR | N9: 27 | O9: A | P9: 24 | S9: 101 | T9: =CONCATENATE(J9," ",K9," ",L9," ",M9," ",N9," ",O9," ",P9," ",Q9," ",R9," ",S9) -> CL 36 SUR 27 A 24 101 | U9: No reporta | V9: 5708521 - 3006172104 | W9: Administración Copropiedad | X9: CL | Y9: 36 | AA9: SUR | AB9: 27 | AC9: A | AD9: 24 | AH9: =CONCATENATE(X9," ",Y9," ",Z9," ",AA9," ",AB9," ",AC9," ",AD9," ",AE9," ",AF9," ",AG9) -> CL 36 SUR 27 A 24 | AI9: no reporta | AJ9: no reporta | AK9: Inmaculada | AP9: 5 | AQ9: 42010 | AS9: =+AR9-AQ9 -> -42010 | AT9: Acta de compromiso | AU9: Auto de archivo
B10: 007-2015 | C10: 1316834 | D10: FLORA | G10: Urbanización Envigado Campestre | H10: Tala de pino en predio privado | I10: Jorge Humberto Toro Restrepo | J10: CL | K10: 40 | L10: F | M10: SUR | N10: 248 | P10: 200 | S10: 316 | T10: =CONCATENATE(J10," ",K10," ",L10," ",M10," ",N10," ",O10," ",P10," ",Q10," ",R10," ",S10) -> CL 40 F SUR 248 200 316 | U10: No reporta | V10: no reporta | W10: Oscar Perez | X10: CL | Y10: 40 | Z10: F | AA10: SUR | AB10: 248 | AD10: 200 | AG10: 113-315 | AH10: =CONCATENATE(X10," ",Y10," ",Z10," ",AA10," ",AB10," ",AC10," ",AD10," ",AE10," ",AF10," ",AG10) -> CL 40 F SUR 248 200 113-315 | AI10: no reporta | AJ10: no reporta | AK10: La Mina | AP10: 6 | AQ10: 42011 | AR10: 42026 | AS10: =+AR10-AQ10 -> 15 | AT10: Acta de compromiso | AU10: Notificación | AW10: 42026 | AX10: J. Guzmán | AY10: 42026
B11: 008-2015 | C11: 1316836 | D11: FLORA | H11: Daño a Eucalipto por quemas | I11: Carlos Carvajal Rendon | J11: Cl | K11: 47 | M11: SUR | N11: 39 | P11: 38 | T11: =CONCATENATE(J11," ",K11," ",L11," ",M11," ",N11," ",O11," ",P11," ",Q11," ",R11," ",S11) -> Cl 47 SUR 39 38 | U11: No reporta | V11: 3394070 | W11: Habitante en dirección | X11: CL | Y11: 47 | AA11: SUR | AB11: 39 | AD11: 38 | AH11: =CONCATENATE(X11," ",Y11," ",Z11," ",AA11," ",AB11," ",AC11," ",AD11," ",AE11," ",AF11," ",AG11) -> CL 47 SUR 39 38 | AI11: no reporta | AJ11: no reporta | AK11: El Trianón | AP11: 7 | AQ11: 42011 | AR11: 42019 | AS11: =+AR11-AQ11 -> 8 | AT11: Acta de compromiso | AU11: Auto de archivo | AW11: 42019 | AX11: L. Garcia | AY11: 42019 | CF11: 42037
B12: 009-2015 | C12: 1316885 - 1309543 | D12: FLORA | H12: Daño de arbol y jardin - es reincidente | I12: Martha Nohemi Colorado | J12: DG | K12: 33 | N12: 33 | O12: A | P12: 23 | Q12: SUR | T12: =CONCATENATE(J12," ",K12," ",L12," ",M12," ",N12," ",O12," ",P12," ",Q12," ",R12," ",S12) -> DG 33 33 A 23 SUR | U12: 21719241 | V12: 2065979 | W12: Diego | AH12: No reporta | AI12: no reporta | AJ12: no reporta | AK12: La Magnolia | AP12: 9 | AQ12: 42013 | AR12: 42024 | AS12: =+AR12-AQ12 -> 11 | AT12: Acta de compromiso | AU12: Auto de archivo | AW12: 42023 | AX12: L. Garcia | AY12: 42024 | CF12: 42037
B13: 010-2015 | C13: 1316890 | E13: RESIDUOS SOLIDOS | H13: Acumulación de residuos en predio privado | I13: Comunidad Edificio Arboleda Mejia | J13: CL | K13: 40 | M13: SUR | N13: 31 | P13: 22 | T13: =CONCATENATE(J13," ",K13," ",L13," ",M13," ",N13," ",O13," ",P13," ",Q13," ",R13," ",S13) -> CL 40 SUR 31 22 | U13: No reporta | V13: no reporta | W13: Constructora | AH13: No reporta | AI13: no reporta | AJ13: no reporta | AK13: Mesa | AP13: 9 | AQ13: 42017 | AS13: =+AR13-AQ13 -> -42017 | AT13: Acta de compromiso | AU13: Auto de archivo
B14: 011-2015 | C14: 1316893 | E14: RESIDUOS SOLIDOS | H14: Sacan recortes de madera y basuras en sitios, dias y horas no autorizados | I14: Comunidad | T14: No reporta | U14: No reporta | V14: no reporta | W14: Por determinar | X14: KR | Y14: 37 | AB14: 39 | AC14: B | AD14: 53 | AE14: SUR | AH14: =CONCATENATE(X14," ",Y14," ",Z14," ",AA14," ",AB14," ",AC14," ",AD14," ",AE14," ",AF14," ",AG14) -> KR 37 39 B 53 SUR | AI14: no reporta | AJ14: no reporta | AK14: Mesa | AP14: 9 | AQ14: 42017 | AS14: =+AR14-AQ14 -> -42017 | AT14: Acta de compromiso | AU14: Auto de archivo
B15: 012-2015 | C15: 1316920 | E15: RESIDUOS SOLIDOS | H15: Acumulación de residuos en predio privado | I15: Comunidad | T15: No reporta | U15: No reporta | V15: no reporta | W15: Everardo Ceballos | X15: KR | Y15: 40 | AB15: 52 | AC15: B | AD15: 40 | AE15: SUR | AG15: 3 | AH15: =CONCATENATE(X15," ",Y15," ",Z15," ",AA15," ",AB15," ",AC15," ",AD15," ",AE15," ",AF15," ",AG15) -> KR 40 52 B 40 SUR 3 | AI15: no reporta | AJ15: 2767150 | AK15: Loma del Barro | AP15: 7 | AQ15: 42018 | AS15: =+AR15-AQ15 -> -42018 | AT15: Acta de compromiso | AU15: Visitas patrulleros
B16: 013-2015 | C16: 1316903 | E16: RESIDUOS SOLIDOS | H16: Acumulación de residuos en espacio público | I16: Comunidad | T16: No reporta | U16: No reporta | V16: no reporta | W16: Por determinar | X16: CL | Y16: 47 | Z16: A | AA16: SUR | AB16: 39 | AC16: A | AD16: 4 | AH16: =CONCATENATE(X16," ",Y16," ",Z16," ",AA16," ",AB16," ",AC16," ",AD16," ",AE16," ",AF16," ",AG16) -> CL 47 A SUR 39 A 4 | AI16: no reporta | AJ16: no reporta | AK16: El Trianón | AP16: 7 | AQ16: 42018 | AR16: 42024 | AS16: =+AR16-AQ16 -> 6 | AT16: Acta de compromiso | AU16: Auto de archivo | AW16: 42024 | AX16: L Garcia | AY16: 42024 | CF16: 42037
B17: 014-2015 | C17: 1316936 | E17: RESIDUOS SOLIDOS | H17: Disposición de tierras hacia la quebrada | I17: Comunidad | T17: No reporta | U17: No reporta | V17: no reporta | W17: Constructora | X17: DG | Y17: 31 | AB17: 33 | AD17: 16 | AH17: =CONCATENATE(X17," ",Y17," ",Z17," ",AA17," ",AB17," ",AC17," ",AD17," ",AE17," ",AF17," ",AG17) -> DG 31 33 16 | AI17: no reporta | AJ17: no reporta | AK17: Las Flores | AP17: 3 | AQ17: 42019 | AR17: 42024 | AS17: =+AR17-AQ17 -> 5 | AT17: Acta de compromiso | AU17: Auto de archivo | AW17: 42024 | AX17: L Garcia | AY17: 42024 | CF17: 42037
B18: 015-2015 | C18: 1316840 | E18: RESIDUOS SOLIDOS | G18: Club Equitación Equus | H18: Manejo de residuos sólidos - Respel | I18: De oficio | T18: No reporta | U18: No reporta | V18: no reporta | W18: Club Equitación Equus | AH18: Km 13 via palmas | AI18: no reporta | AJ18: 3171159 | AL18: Santa Catalina | AP18: 10 | AQ18: 42011 | AR18: 41968 | AS18: =+AR18-AQ18 -> -43 | AT18: Acta de compromiso | AU18: Auto de archivo | AW18: 41968 | AX18: J. guzman - C. Espinoza | AY18: 41968
B19: 016-2015 | C19: Es la misma 028-2015 - 1316859 | D19: FLORA | G19: Urbanización Ciudadela Real | H19: Posibles talas ilegales de árboles | I19: Comunidad | J19: CL | K19: 48 | L19: C | M19: SUR | N19: 43 | O19: A | P19: 50 | T19: =CONCATENATE(J19," ",K19," ",L19," ",M19," ",N19," ",O19," ",P19," ",Q19," ",R19," ",S19) -> CL 48 C SUR 43 A 50 | U19: No reporta | V19: no reporta | W19: Habitante en dirección | X19: CL | Y19: 48 | Z19: C | AA19: SUR | AB19: 43 | AC19: A | AD19: 50 | AG19: 159 | AH19: =CONCATENATE(X19," ",Y19," ",Z19," ",AA19," ",AB19," ",AC19," ",AD19," ",AE19," ",AF19," ",AG19) -> CL 48 C SUR 43 A 50 159 | AI19: no reporta | AJ19: no reporta | AK19: Primavera | AP19: 8 | AQ19: 42012 | AR19: 42011 | AS19: =+AR19-AQ19 -> -1 | AT19: Código de policia | AU19: Visitas técnicos
B20: 017-2015 | C20: 1316954 | E20: RESIDUOS SOLIDOS | H20: Acumulación de residuos en espacio público | I20: Comunidad | T20: =CONCATENATE(J20," ",K20," ",L20," ",M20," ",N20," ",O20," ",P20," ",Q20," ",R20," ",S20) | U20: No reporta | V20: no reporta | W20: Por determinar | X20: KR | Y20: 29 | AB20: 40 | AC20: E | AD20: 53 | AE20: SUR | AH20: =CONCATENATE(X20," ",Y20," ",Z20," ",AA20," ",AB20," ",AC20," ",AD20," ",AE20," ",AF20," ",AG20) -> KR 29 40 E 53 SUR | AI20: no reporta | AJ20: no reporta | AK20: San José | AP20: 6 | AQ20: 42023 | AR20: 42030 | AS20: =+AR20-AQ20 -> 7 | AT20: Acta de compromiso | AU20: Auto de archivo | AW20: 42030 | AX20: L. Garcia
B21: 018-2015 | C21: 1316955 | E21: RESIDUOS SOLIDOS | H21: Disposición inadecuada de residuos solidos | I21: Eunice Restrepo R | J21: CL | K21: 39 | L21: B | M21: SUR | N21: 39 | P21: 3 | T21: =CONCATENATE(J21," ",K21," ",L21," ",M21," ",N21," ",O21," ",P21," ",Q21," ",R21," ",S21) -> CL 39 B SUR 39 3 | U21: No reporta | V21: 3342528 - 3003479842 | W21: Varios usuarios | AH21: =CONCATENATE(X21," ",Y21," ",Z21," ",AA21," ",AB21," ",AC21," ",AD21," ",AE21," ",AF21," ",AG21) | AI21: no reporta | AJ21: no reporta | AK21: Mesa | AP21: 9 | AQ21: 42023 | AR21: 42031 | AS21: =+AR21-AQ21 -> 8 | AT21: Acta de compromiso | AU21: Visitas patrulleros | AW21: 42030 | AX21: L. Garcia | AY21: 42031
B22: 019-2015 | C22: 1317025 | D22: FLORA | H22: Daño de zonas verde | I22: Beatriz Elena Mira | J22: KR | K22: 44 | L22: A | N22: 39 | P22: 11 | Q22: SUR | T22: =CONCATENATE(J22," ",K22," ",L22," ",M22," ",N22," ",O22," ",P22," ",Q22," ",R22," ",S22) -> KR 44 A 39 11 SUR | U22: 21852310 | V22: 6011160 | W22: Jairo Vanegas | AH22: No reporta | AI22: no reporta | AJ22: no reporta | AK22: Alcalá | AP22: 8 | AQ22: 42026 | AR22: 42031 | AS22: =+AR22-AQ22 -> 5 | AT22: Acta de compromiso | AU22: Auto de archivo | AW22: 42030 | AX22: L. Garcia | AY22: 42031
B23: 020-2015 | C23: 1317057 - 162985 - 3558 (Mismo 1013-14 y 952-2014) 3453 - 438356-53546 | D23: FLORA | H23: Tala de bosques y rastrojos | I23: De oficio | T23: No reporta | U23: No reporta | V23: 3394072 | W23: Benjamin de Jesus Gallego - Juan Jose Gutierrez | AH23: Predio 189 | AI23: 8248031 | AJ23: 5381382 | AL23: Pantanillo | AP23: 13 | AQ23: 42026 | AR23: 42026 | AS23: =+AR23-AQ23 -> 0 | AT23: Ley 1333 de 2009 | AU23: Auto de archivo | AW23: 42026 | AX23: J. Guzman | AY23: 42026 | AZ23: 42146 | BA23: J. Guzman | BB23: 42149
B24: 021-2015 | C24: 1317056 | D24: FLORA | H24: Tala de guadua en servidumbre | I24: Anonimo | T24: No reporta | U24: No reporta | V24: no reporta | W24: Familia Gonzalez | X24: CL | Y24: 27 | AA24: SUR | AB24: 27 | AC24: D | AD24: 5 | AH24: =CONCATENATE(X24," ",Y24," ",Z24," ",AA24," ",AB24," ",AC24," ",AD24," ",AE24," ",AF24," ",AG24) -> CL 27 SUR 27 D 5 | AI24: no reporta | AJ24: no reporta | AK24: El Esmeraldal | AP24: 4 | AQ24: 42027 | AS24: =+AR24-AQ24 -> -42027 | AT24: Acta de compromiso | AU24: Auto de archivo | AW24: 42031 | AX24: L. Garcia
B25: 022-2015 | C25: 1316932 | E25: RESIDUOS SOLIDOS | G25: Mandipapas | H25: Disposición inadecuada de residuos sólidos | I25: Enviaseo | T25: No reporta | U25: No reporta | V25: 4032000 | W25: Restaurante Mandipapas | X25: KR | Y25: 42 | AB25: 42 | AD25: 8 | AE25: SUR | AH25: =CONCATENATE(X25," ",Y25," ",Z25," ",AA25," ",AB25," ",AC25," ",AD25," ",AE25," ",AF25," ",AG25) -> KR 42 42 8 SUR | AI25: no reporta | AJ25: 3328403 | AK25: Zona Centro | AP25: 9 | AQ25: 42019 | AS25: =+AR25-AQ25 -> -42019 | AT25: Comparendo ambiental | AU25: Auto de inicio
B26: 023-2015 | C26: 1316970 | E26: RESIDUOS SOLIDOS | H26: Disposición inadecuada de residuos sólidos | I26: Jose Rene Rios | T26: No reporta | U26: No reporta | V26: 3126109400 | W26: Varios usuarios | AH26: Sector paradero | AI26: no reporta | AJ26: no reporta | AL26: Perico | AP26: 13 | AQ26: 42024 | AS26: =+AR26-AQ26 -> -42024 | AT26: Acta de compromiso | AU26: Auto de archivo | AW26: 42031 | AX26: L. Garcia
B27: 024-2015 | C27: 1316933 - 1316898 - 1316897 | D27: FLORA | H27: Daño de vegetación nativa - quemas | I27: De oficio - Inspección Palmas | T27: No reporta | U27: No reporta | V27: 3860909 | W27: Juan Ricardo Villegas - Claudia Marcela Chica - Felix Andres Caceres - Januario Alfonso Chica | AH27: Predio 433 - 432 | AI27: no reporta | AJ27: 3318107 - 3113775711 | AL27: Pantanillo | AP27: 13 | AQ27: 42019 | AR27: 42019 | AS27: =+AR27-AQ27 -> 0 | AT27: Acta de compromiso | AU27: Auto de archivo | AW27: 42019 | AX27: J. Guzman | AY27: 42019
B28: 025-2015 | C28: 1316995 | D28: HÍDRICO | H28: Construcción de muro en canal de quebrada | I28: Comunidad | T28: No reporta | U28: No reporta | V28: no reporta | W28: Jorge Ramiro Hincapie | X28: CL | Y28: 48 | Z28: C | AA28: SUR | AB28: 39 | AC28: D | AD28: 155 | AG28: 103 | AH28: =CONCATENATE(X28," ",Y28," ",Z28," ",AA28," ",AB28," ",AC28," ",AD28," ",AE28," ",AF28," ",AG28) -> CL 48 C SUR 39 D 155 103 | AI28: 8299025 | AJ28: 3795912 | AK28: Las antillas | AP28: 7 | AQ28: 42025 | AR28: 42025 | AS28: =+AR28-AQ28 -> 0 | AT28: Ley 1333 de 2009 | AU28: Auto de archivo | AW28: 42025 | AX28: J. Guzman | AY28: 42025
B29: 026-2015 | C29: 1317012 | D29: LOTE-PREDIO | G29: Proyecto Brezzo | H29: Control ambiental de obra | I29: De oficio | T29: No reporta | U29: No reporta | V29: no reporta | W29: Proyecto Brezzo - Arquitectura y Concreto | X29: KR | Y29: 27 | Z29: D | AB29: 27 | AD29: 6 | AE29: SUR | AH29: =CONCATENATE(X29," ",Y29," ",Z29," ",AA29," ",AB29," ",AC29," ",AD29," ",AE29," ",AF29," ",AG29) -> KR 27 D 27 6 SUR | AI29: no reporta | AJ29: 3103863306 | AK29: El Esmeraldal | AP29: 4 | AQ29: 42026 | AR29: 42024 | AS29: =+AR29-AQ29 -> -2 | AT29: Acta de compromiso | AU29: Citaciones | AW29: 42024 | AX29: J. Guzman | AY29: 42024
B30: 027-2015 | C30: 1316967 | E30: RESIDUOS SOLIDOS | H30: Colchon en espacio público | I30: Anonimo | T30: No reporta | U30: No reporta | V30: no reporta | W30: Por determinar | X30: KR | Y30: 44 | AB30: 46 | AD30: 43 | AE30: SUR | AG30: 301 | AH30: =CONCATENATE(X30," ",Y30," ",Z30," ",AA30," ",AB30," ",AC30," ",AD30," ",AE30," ",AF30," ",AG30) -> KR 44 46 43 SUR 301 | AI30: no reporta | AJ30: no reporta | AK30: Primavera | AP30: 8 | AQ30: 42024 | AR30: 42023 | AS30: =+AR30-AQ30 -> -1 | AT30: Remisión u otros | AU30: Auto de archivo | AW30: 42023 | AX30: L. Garcia | AY30: 42023 | CF30: 42023
B31: 028-2015 | C31: Es la misma 016-2015 - 1316859 | D31: FLORA | G31: Urbanización Ciudadela Real | H31: Tala de nispero | I31: Comunidad | T31: No reporta | U31: No reporta | V31: no reporta | W31: Habitante en dirección | X31: CL | Y31: 48 | Z31: C | AA31: SUR | AB31: 43 | AC31: A | AD31: 50 | AG31: 159 | AH31: =CONCATENATE(X31," ",Y31," ",Z31," ",AA31," ",AB31," ",AC31," ",AD31," ",AE31," ",AF31," ",AG31) -> CL 48 C SUR 43 A 50 159 | AI31: no reporta | AJ31: no reporta | AK31: Primavera | AP31: 8 | AQ31: 42012 | AR31: 42011 | AS31: =+AR31-AQ31 -> -1 | AT31: Acta de compromiso | AU31: Auto de archivo | AV31: Se remite a Parques y Arbolizacion | AW31: 42011 | AX31: J. Guzman | AY31: 42011
B32: 029-2015 | C32: 1316811 | E32: RESIDUOS SOLIDOS | H32: Escombros en espacio público | I32: De oficio | T32: No reporta | U32: No reporta | V32: no reporta | W32: Gloria Ines Arango Rozo | X32: CL | Y32: 38 | Z32: A | AA32: SUR | AB32: 43 | AD32: 67 | AG32: 81 | AH32: =CONCATENATE(X32," ",Y32," ",Z32," ",AA32," ",AB32," ",AC32," ",AD32," ",AE32," ",AF32," ",AG32) -> CL 38 A SUR 43 67 81 | AI32: 32336902 | AJ32: 3106057362 | AK32: Zona Centro | AP32: 9 | AQ32: 42010 | AR32: 42003 | AS32: =+AR32-AQ32 -> -7 | AT32: Acta de compromiso | AU32: Auto de archivo | AW32: 42003 | AX32: L. Garcia | AY32: 42003 | CF32: 42031
B33: 030-2015 | C33: 1317048 | D33: FAUNA DOMÉSTICA | G33: Urbanización Prados de Zuñiga | H33: Ataque de mascota a otra | I33: Martha Betancur | J33: CL | K33: 20 | M33: SUR | N33: 45 | P33: 70 | T33: =CONCATENATE(J33," ",K33," ",L33," ",M33," ",N33," ",O33," ",P33," ",Q33," ",R33," ",S33) -> CL 20 SUR 45 70 | U33: 43615314 | V33: 2709729 | W33: Jairo Alfonso Romero | X33: CL | Y33: 20 | AA33: SUR | AB33: 45 | AD33: 70 | AG33: 1303 | AH33: =CONCATENATE(X33," ",Y33," ",Z33," ",AA33," ",AB33," ",AC33," ",AD33," ",AE33," ",AF33," ",AG33) -> CL 20 SUR 45 70 1303 | AI33: no reporta | AJ33: 3122895370 - 5780468 | AK33: Zuñiga | AP33: 4 | AQ33: 42027 | AS33: =+AR33-AQ33 -> -42027 | AT33: Código de policia | AU33: Auto de archivo
B34: 031-2015 | C34: 1317047 | D34: FAUNA DOMÉSTICA | G34: Urbanización Prados de Zuñiga | H34: Ataque de mascota a otra | I34: Martha Betancur | J34: CL | K34: 20 | M34: SUR | N34: 45 | P34: 70 | T34: =CONCATENATE(J34," ",K34," ",L34," ",M34," ",N34," ",O34," ",P34," ",Q34," ",R34," ",S34) -> CL 20 SUR 45 70 | U34: 43615314 | V34: 2709729 | W34: Jairo Alfonso Romero | X34: CL | Y34: 20 | AA34: SUR | AB34: 45 | AD34: 70 | AG34: 1303 | AH34: =CONCATENATE(X34," ",Y34," ",Z34," ",AA34," ",AB34," ",AC34," ",AD34," ",AE34," ",AF34," ",AG34) -> CL 20 SUR 45 70 1303 | AI34: no reporta | AJ34: 3122895370 - 5780468 | AK34: Zuñiga | AP34: 4 | AQ34: 42027 | AS34: =+AR34-AQ34 -> -42027 | AT34: Código de policia | AU34: Auto de archivo
B35: 032-2015 | C35: 1316993 - 300676 | D35: FLORA | E35: RESIDUOS SOLIDOS | G35: Urbanización Cerrovento | H35: Quemas no autorizadas de material vegetal - contaminacion de la quebrada por sedimentacion de excavaciones. | I35: Comunidad | T35: No reporta | U35: No reporta | V35: no reporta | W35: Ramiro Pérez Duque | AH35: Cerrovento Sector El Vergel | AI35: 71626540 | AJ35: 4187774 | AL35: El Escobero | AP35: 10 | AQ35: 42025 | AR35: 42024 | AS35: =+AR35-AQ35 -> -1 | AT35: Acta de compromiso | AU35: Verificación | AV35: Presentan plan de contingencia para la situacion encontrada por contaminacion de la quebrada. | AW35: 42024 | AX35: L. Garcia | AY35: 42024 | CF35: 42031
B36: 033-2015 | C36: 130 SAE 1412-872 | D36: HÍDRICO | G36: Valle Hermoso S.A - Balcones de la Abadía | H36: Requerimiento por reforzamiento de estructura hidráulica | I36: Autoridad Ambiental Delegada | T36: No reporta | U36: No reporta | V36: no reporta | W36: Sociedad Valle Hermoso S.A - Comjunto Residencial Balcones de la Abadía | X36: CL | Y36: 27 | AA36: SUR | AB36: 28 | AD36: 181 | AH36: =CONCATENATE(X36," ",Y36," ",Z36," ",AA36," ",AB36," ",AC36," ",AD36," ",AE36," ",AF36," ",AG36) -> CL 27 SUR 28 181 | AI36: 811.035.342-7 | AJ36: 3136719 - 4485590 - 2777266 | AK36: El Esmeraldal | AP36: 4 | AQ36: 42020 | AS36: =+AR36-AQ36 -> -42020 | AT36: Pendiente de tramite | AU36: Auto de archivo
B37: 034-2015 | C37: 1317062 | D37: FAUNA DOMÉSTICA | G37: Urbanización Sendero Verde | H37: Envenenamiento de mascota | I37: Neinis Lida Quintero | J37: KR | K37: 27 | M37: SUR | N37: 38 | P37: 51 | R37: 4 | S37: 522 | T37: =CONCATENATE(J37," ",K37," ",L37," ",M37," ",N37," ",O37," ",P37," ",Q37," ",R37," ",S37) -> KR 27 SUR 38 51 4 522 | U37: 57431485 | V37: 3320639 | W37: Por determinar | X37: KR | Y37: 27 | AB37: 38 | AD37: 51 | AE37: SUR | AH37: =CONCATENATE(X37," ",Y37," ",Z37," ",AA37," ",AB37," ",AC37," ",AD37," ",AE37," ",AF37," ",AG37) -> KR 27 38 51 SUR | AI37: no reporta | AJ37: 2762869 - 3116303329 | AK37: San José | AP37: 6 | AQ37: 42027 | AS37: =+AR37-AQ37 -> -42027 | AT37: Código de policia | AU37: Auto de archivo
B38: 035-2015 | C38: 1317064 | E38: RESIDUOS SOLIDOS | H38: Residuos de remodelación en espacio público | I38: Comunidad | T38: No reporta | U38: No reporta | V38: no reporta | W38: Por determinar | X38: CL | Y38: 36 | Z38: E | AA38: SUR | AB38: 28 | AD38: 43 | AG38: 402 | AH38: =CONCATENATE(X38," ",Y38," ",Z38," ",AA38," ",AB38," ",AC38," ",AD38," ",AE38," ",AF38," ",AG38) -> CL 36 E SUR 28 43 402 | AI38: no reporta | AJ38: no reporta | AK38: La Pradera | AP38: 5 | AQ38: 42027 | AS38: =+AR38-AQ38 -> -42027 | AT38: Acta de compromiso | AU38: Auto de archivo
B39: 036-2015 | C39: 1317073 - 1316563 | E39: RESIDUOS SOLIDOS | H39: Afectaciones por escombros y equinaza | I39: Catalina Mejia | J39: KR | K39: 26 | N39: 41 | P39: 46 | Q39: SUR | S39: 126 - 127 | T39: =CONCATENATE(J39," ",K39," ",L39," ",M39," ",N39," ",O39," ",P39," ",Q39," ",R39," ",S39) -> KR 26 41 46 SUR 126 - 127 | U39: 43753613 | V39: 3318301 | W39: Javier Bolivar | X39: KR | Y39: 26 | AB39: 41 | AC39: A | AD39: 156 | AE39: SUR | AH39: =CONCATENATE(X39," ",Y39," ",Z39," ",AA39," ",AB39," ",AC39," ",AD39," ",AE39," ",AF39," ",AG39) -> KR 26 41 A 156 SUR | AI39: no reporta | AJ39: no reporta | AK39: San Rafael | AP39: 6 | AQ39: 42030 | AS39: =+AR39-AQ39 -> -42030 | AT39: Código de policia | AU39: Auto de archivo | AW39: 42032 | AX39: l. guzman | AY39: 42032 | AZ39: 42118 | BA39: l.guzman | BB39: 42118
B40: 037-2015 | C40: 1316996 | D40: HÍDRICO | H40: Retiro de rocas de una quebrada | I40: De oficio - Inspección Palmas | T40: No reporta | U40: No reporta | V40: no reporta | W40: Jorge Tirado | AH40: Finca Montichelo | AI40: no reporta | AJ40: 3188163407 | AL40: Las Palmas | AP40: 12 | AQ40: 42025 | AS40: =+AR40-AQ40 -> -42025 | AT40: Acta de compromiso | AU40: Auto de archivo
B41: 038-2015 | C41: 103769 | E41: RESIDUOS SOLIDOS | H41: Control de punto crítico | I41: Policia Nacional - Estación Envigado | J41: CL | K41: 43 | M41: SUR | N41: 48 | P41: 7 | T41: =CONCATENATE(J41," ",K41," ",L41," ",M41," ",N41," ",O41," ",P41," ",Q41," ",R41," ",S41) -> CL 43 SUR 48 7 | U41: No reporta | V41: 3391000 | W41: Varios usuarios | X41: KR | Y41: 50 | Z41: A | AB41: 40 | AC41: A | AE41: SUR | AH41: =CONCATENATE(X41," ",Y41," ",Z41," ",AA41," ",AB41," ",AC41," ",AD41," ",AE41," ",AF41," ",AG41) -> KR 50 A 40 A SUR | AI41: no reporta | AJ41: no reporta | AK41: Alcalá | AP41: 8 | AQ41: 42026 | AS41: =+AR41-AQ41 -> -42026 | AT41: Acta de compromiso | AU41: Auto de archivo
B42: 039-2015 | C42: 103771 | E42: RESIDUOS SOLIDOS | H42: Control de punto crítico | I42: Policia Nacional - Estación Envigado | J42: CL | K42: 43 | M42: SUR | N42: 48 | P42: 7 | T42: =CONCATENATE(J42," ",K42," ",L42," ",M42," ",N42," ",O42," ",P42," ",Q42," ",R42," ",S42) -> CL 43 SUR 48 7 | U42: No reporta | V42: 3391000 | W42: Varios usuarios | X42: TR | Y42: 34 | Z42: D | AA42: SUR | AB42: 32 | AC42: B | AH42: =CONCATENATE(X42," ",Y42," ",Z42," ",AA42," ",AB42," ",AC42," ",AD42," ",AE42," ",AF42," ",AG42) -> TR 34 D SUR 32 B | AI42: no reporta | AJ42: no reporta | AK42: Los Naranjos | AP42: 9 | AQ42: 42026 | AS42: =+AR42-AQ42 -> -42026 | AT42: Acta de compromiso | AU42: Auto de archivo
B43: 040-2015 | C43: 1317090 - 1317727 | E43: RESIDUOS SOLIDOS | G43: Unidad Residencial Valle Jardín | H43: Problemática por acumulación de tierras y escombros | I43: David Berrio | J43: KR | K43: 42 | L43: D | N43: 50 | P43: 40 | Q43: SUR | T43: =CONCATENATE(J43," ",K43," ",L43," ",M43," ",N43," ",O43," ",P43," ",Q43," ",R43," ",S43) -> KR 42 D 50 40 SUR | U43: No reporta | V43: 3006011095 | W43: Administración Copropiedad | X43: KR | Y43: 42 | Z43: D | AB43: 50 | AD43: 40 | AE43: SUR | AH43: =CONCATENATE(X43," ",Y43," ",Z43," ",AA43," ",AB43," ",AC43," ",AD43," ",AE43," ",AF43," ",AG43) -> KR 42 D 50 40 SUR | AI43: no reporta | AJ43: no reporta | AK43: Loma del Barro | AP43: 7 | AQ43: 42031 | AS43: =+AR43-AQ43 -> -42031 | AT43: Acta de compromiso | AU43: Auto de archivo
B44: 041-2015 | C44: 1317082 | D44: FAUNA DOMÉSTICA | H44: Retención de mascota peligrosa - incumplimiento de Ley 746 de 2002 | I44: Policia Nacional - Estación Envigado | J44: CL | K44: 43 | M44: SUR | N44: 48 | P44: 7 | T44: =CONCATENATE(J44," ",K44," ",L44," ",M44," ",N44," ",O44," ",P44," ",Q44," ",R44," ",S44) -> CL 43 SUR 48 7 | U44: No reporta | V44: 3391000 | W44: Daniel Alejandro Colorado Gutierrez - Felipe Colorado | X44: TR | Y44: 34 | Z44: B | AA44: SUR | AB44: 32 | AD44: 9 | AH44: =CONCATENATE(X44," ",Y44," ",Z44," ",AA44," ",AB44," ",AC44," ",AD44," ",AE44," ",AF44," ",AG44) -> TR 34 B SUR 32 9 | AI44: 1037624128 | AJ44: 2091372 - 3004303866 | AK44: Obrero | AP44: 9 | AQ44: 42030 | AR44: 42030 | AS44: =+AR44-AQ44 -> 0 | AT44: Remisión u otros | AU44: Auto de archivo | BL44: 42030 | BM44: 42030 | CF44: 42032
B45: 042-2015 | C45: 104885 | D45: LOTE-PREDIO | H45: Lote en condiciones inadecudas y con manejo inapropiado de residuos | I45: De oficio - Secretaria de Salud | T45: No reporta | U45: No reporta | V45: 3394000 | W45: Por determinar | X45: KR | Y45: 49 | Z45: A | AB45: 46 | AC45: A | AD45: 60 | AE45: SUR | AG45: lote | AH45: =CONCATENATE(X45," ",Y45," ",Z45," ",AA45," ",AB45," ",AC45," ",AD45," ",AE45," ",AF45," ",AG45) -> KR 49 A 46 A 60 SUR lote | AI45: no reporta | AJ45: no reporta | AK45: Las vegas | AP45: 1 | AQ45: 42030 | AS45: =+AR45-AQ45 -> -42030 | AT45: Acta de compromiso | AU45: Auto de archivo
B46: 043-2015 | C46: Es el mismo 77-2015 - 104042 - 295299 | E46: RESIDUOS SOLIDOS | H46: Afectaciones por residuos sólidos | I46: Ofelia Jaramillo - Secretaria de Salud | T46: No reporta | U46: No reporta | V46: no reporta | W46: Por determinar | X46: DG | Y46: 29 | AB46: 34 | AC46: B | AD46: 55 | AE46: SUR | AH46: =CONCATENATE(X46," ",Y46," ",Z46," ",AA46," ",AB46," ",AC46," ",AD46," ",AE46," ",AF46," ",AG46) -> DG 29 34 B 55 SUR | AI46: no reporta | AJ46: no reporta | AK46: Alto de Misael | AP46: 3 | AQ46: 42027 | AS46: =+AR46-AQ46 -> -42027 | AT46: Acta de compromiso | AU46: Auto de archivo
B47: 044-2015 | C47: 1317085 - 283099 | D47: FLORA | H47: Tala de arboles sin autorización | I47: De oficio | T47: No reporta | U47: No reporta | V47: 3394000 | W47: Carlos Ramirez Arias | X47: CL | Y47: 49 | Z47: D | AA47: SUR | AB47: 40 | AC47: A | AD47: 230 | AH47: =CONCATENATE(X47," ",Y47," ",Z47," ",AA47," ",AB47," ",AC47," ",AD47," ",AE47," ",AF47," ",AG47) -> CL 49 D SUR 40 A 230 | AI47: 71721852 | AJ47: 3003754121 | AK47: Loma del Barro | AP47: 7 | AQ47: 42031 | AR47: 42030 | AS47: =+AR47-AQ47 -> -1 | AT47: Acta de compromiso | AU47: Auto de archivo | AV47: Solicita prorroga con radicado 283099 y no se le da, se le informa via telefonica el dia 06-05-2015, trae carta del colegio Gimnacio Campestre el tesoro donde lo autorizan a sembrar los 5 Arboles. | AW47: 42030 | AX47: L. Garcia | AY47: 42030 | BL47: 42030 | BM47: 42030
B48: 045-2015 | C48: 1317114 | D48: AIRE | H48: Olores de una pasteleria o de la quebrada | I48: Luz Elena Zapata | J48: CL | K48: 32 | M48: SUR | N48: 43 | P48: 9 | T48: =CONCATENATE(J48," ",K48," ",L48," ",M48," ",N48," ",O48," ",P48," ",Q48," ",R48," ",S48) -> CL 32 SUR 43 9 | U48: 32518475 | V48: 2706566 | W48: Por determinar | AH48: No reporta | AI48: no reporta | AJ48: no reporta | AK48: San Marcos | AP48: 2 | AQ48: 42032 | AS48: =+AR48-AQ48 -> -42032 | AT48: Acta de compromiso | AU48: Auto de archivo | AW48: 42037 | AX48: L. Garcia
B49: 046-2015 | C49: 1317118 | E49: RESIDUOS SOLIDOS | H49: Inadecuado manejo de residuos sólidos | I49: Almacen Colchones Júbilo - Jorge Mora - Edgar Echavarria | J49: KR | K49: 42 | N49: 38 | O49: A | P49: 81 | Q49: SUR | T49: =CONCATENATE(J49," ",K49," ",L49," ",M49," ",N49," ",O49," ",P49," ",Q49," ",R49," ",S49) -> KR 42 38 A 81 SUR | V49: 4444779 - 3006524786 | W49: Por determinar | AH49: No reporta | AI49: no reporta | AJ49: no reporta | AK49: Zona Centro | AP49: 9 | AQ49: 42032 | AS49: =+AR49-AQ49 -> -42032 | AT49: Acta de compromiso | AU49: Auto de archivo | AV49: El sector ya fue socializado, igualmente se continuara con el seguimiento. | AW49: 42037 | AX49: L. Garcia
B50: 047-2015 | C50: 1317144 | E50: ESCOMBROS | H50: Escombros dispuesto en espacio público | I50: Diana Marcela Vanegas B | J50: KR | K50: 26 | N50: 41 | O50: B | P50: 25 | Q50: SUR | S50: 130 | T50: =CONCATENATE(J50," ",K50," ",L50," ",M50," ",N50," ",O50," ",P50," ",Q50," ",R50," ",S50) -> KR 26 41 B 25 SUR 130 | U50: No reporta | V50: 3316449 | W50: Olga Lucia Arias | X50: KR | Y50: 26 | AB50: 41 | AC50: B | AD50: 25 | AE50: SUR | AG50: 164 | AH50: =CONCATENATE(X50," ",Y50," ",Z50," ",AA50," ",AB50," ",AC50," ",AD50," ",AE50," ",AF50," ",AG50) -> KR 26 41 B 25 SUR 164 | AI50: no reporta | AJ50: no reporta | AK50: San Rafael | AP50: 6 | AQ50: 42033 | AS50: =+AR50-AQ50 -> -42033 | AT50: Comparendo ambiental | AU50: Auto de archivo | AW50: 42037 | AX50: L. Garcia
B51: 048-2015 | C51: 1317097 | E51: ESCOMBROS | H51: Escombros dispuesto en espacio público | I51: Comunidad | T51: No reporta | U51: No reporta | V51: no reporta | W51: Por determinar | X51: KR | Y51: 46 | Z51: C | AB51: 44 | AD51: 109 | AE51: SUR | AH51: =CONCATENATE(X51," ",Y51," ",Z51," ",AA51," ",AB51," ",AC51," ",AD51," ",AE51," ",AF51," ",AG51) -> KR 46 C 44 109 SUR | AI51: no reporta | AJ51: no reporta | AK51: Primavera | AP51: 8 | AQ51: 42031 | AR51: 42037 | AS51: =+AR51-AQ51 -> 6 | AT51: Comparendo ambiental | AU51: Auto de archivo | AW51: 42037 | AX51: L. Garcia | AY51: 42037
B52: 049-2015 | C52: 1317156 | E52: RESIDUOS SOLIDOS | H52: Lote donde depositan todo tipo de residuos | I52: De oficio | T52: No reporta | U52: No reporta | V52: no reporta | W52: Por determinar | X52: KR | Y52: 27 | Z52: A | AB52: 40 | AC52: E | AE52: SUR | AH52: =CONCATENATE(X52," ",Y52," ",Z52," ",AA52," ",AB52," ",AC52," ",AD52," ",AE52," ",AF52," ",AG52) -> KR 27 A 40 E SUR | AI52: no reporta | AJ52: no reporta | AK52: San José | AP52: 6 | AQ52: 42033 | AS52: =+AR52-AQ52 -> -42033 | AT52: Acta de compromiso | AU52: Auto de archivo | AW52: 42037 | AX52: L. Garcia
B53: 050-2015 | C53: 1317153 | D53: FLORA | H53: Afectación a arboles y a zona verde | I53: Comunidad | T53: No reporta | U53: No reporta | V53: no reporta | W53: Jairo Bolivar | X53: CL | Y53: 41 | AA53: SUR | AB53: 25 | AC53: A | AD53: 119 | AH53: =CONCATENATE(X53," ",Y53," ",Z53," ",AA53," ",AB53," ",AC53," ",AD53," ",AE53," ",AF53," ",AG53) -> CL 41 SUR 25 A 119 | AI53: no reporta | AJ53: no reporta | AK53: San Rafael | AP53: 6 | AQ53: 42033 | AS53: =+AR53-AQ53 -> -42033 | AT53: Acta de compromiso | AU53: Auto de archivo | AW53: 42037 | AX53: L. Garcia
B54: 051-2015 | C54: 1317154 | D54: FLORA | H54: Tala de arboles sin autorización - olores en la quebrada | I54: Anonimo | T54: No reporta | U54: No reporta | V54: no reporta | W54: Por determinar | X54: CL | Y54: 24 | AA54: SUR | AB54: 38 | AD54: 5 | AH54: =CONCATENATE(X54," ",Y54," ",Z54," ",AA54," ",AB54," ",AC54," ",AD54," ",AE54," ",AF54," ",AG54) -> CL 24 SUR 38 5 | AI54: no reporta | AJ54: no reporta | AK54: Zuñiga | AP54: 4 | AQ54: 42033 | AS54: =+AR54-AQ54 -> -42033 | AT54: Acta de compromiso | AU54: Auto de archivo | AW54: 42037 | AX54: L. Garcia
B55: 052-2015 | C55: 1317258 | E55: RESIDUOS SOLIDOS | H55: Sacan las basuras en dias y horas no autorizadas - solicitan colocación de señal | I55: Comunidad | T55: No reporta | U55: No reporta | V55: no reporta | W55: Por determinar | X55: CL | Y55: 39 | Z55: B | AA55: SUR | AB55: 34 | AC55: A | AD55: 81 | AH55: =CONCATENATE(X55," ",Y55," ",Z55," ",AA55," ",AB55," ",AC55," ",AD55," ",AE55," ",AF55," ",AG55) -> CL 39 B SUR 34 A 81 | AI55: no reporta | AJ55: no reporta | AK55: Mesa | AP55: 9 | AQ55: 42038 | AS55: =+AR55-AQ55 -> -42038 | AT55: Acta de compromiso | AU55: Visitas patrulleros
B56: 053-2015 | C56: 1317081 | E56: RESIDUOS SOLIDOS | G56: Urbanización Envigado Campestre | H56: Incumplimiento PMIRS | I56: De oficio - Gestión Ambiental | T56: No reporta | U56: No reporta | V56: no reporta | W56: Urbanización Envigado Campestre | X56: CL | Y56: 40 | Z56: F | AA56: SUR | AB56: 24 | AC56: B | AD56: 200 | AH56: =CONCATENATE(X56," ",Y56," ",Z56," ",AA56," ",AB56," ",AC56," ",AD56," ",AE56," ",AF56," ",AG56) -> CL 40 F SUR 24 B 200 | AI56: no reporta | AJ56: 3060087 | AK56: La Mina | AP56: 6 | AQ56: 42030 | AS56: =+AR56-AQ56 -> -42030 | AT56: Comparendo ambiental | AU56: Auto de archivo
B57: 054-2015 | C57: 1317293 | D57: FLORA | G57: Urbanización Tierra Blanca | H57: Tala de dos arboles pequeños y poda de dos arboles | I57: John Jairo Osorio G. | J57: KR | K57: 43 | L57: A | N57: 49 | O57: D | P57: 82 | Q57: SUR | R57: 2 | S57: 1111 | T57: =CONCATENATE(J57," ",K57," ",L57," ",M57," ",N57," ",O57," ",P57," ",Q57," ",R57," ",S57) -> KR 43 A 49 D 82 SUR 2 1111 | U57: 71616682 | V57: 3065670 | W57: Administración Copropiedad | X57: KR | Y57: 43 | Z57: A | AB57: 49 | AC57: D | AD57: 82 | AE57: SUR | AH57: =CONCATENATE(X57," ",Y57," ",Z57," ",AA57," ",AB57," ",AC57," ",AD57," ",AE57," ",AF57," ",AG57) -> KR 43 A 49 D 82 SUR | AI57: no reporta | AJ57: 3335100 | AK57: Las Casitas | AP57: 8 | AQ57: 42039 | AS57: =+AR57-AQ57 -> -42039 | AT57: Acta de compromiso | AU57: Visitas patrulleros
B58: 055-2015 | C58: 1317254 | D58: FAUNA DOMÉSTICA | H58: Ataque de mascota a otra | I58: Ivan Dario Escobar | J58: KR | K58: 24 | L58: D | N58: 40 | P58: 160 | Q58: SUR | S58: 7000 | T58: =CONCATENATE(J58," ",K58," ",L58," ",M58," ",N58," ",O58," ",P58," ",Q58," ",R58," ",S58) -> KR 24 D 40 160 SUR 7000 | U58: 71490435 | V58: 3113193352 | W58: Hector Muñoz | AH58: Finca Villa Angela | AI58: no reporta | AJ58: 3104637321 | AL58: El Vallano | AP58: 11 | AQ58: 42037 | AS58: =+AR58-AQ58 -> -42037 | AT58: Código de policia | AU58: Auto de inicio
B59: 056-2015 | C59: 1317313 | D59: FLORA | G59: Urbanización Las Cometas | H59: Daño a jardin y a palmas | I59: Martha Nelly Henao Guarin | J59: KR | K59: 24 | L59: F | N59: 34 | O59: DD | P59: 11 | Q59: SUR | S59: 104 | T59: =CONCATENATE(J59," ",K59," ",L59," ",M59," ",N59," ",O59," ",P59," ",Q59," ",R59," ",S59) -> KR 24 F 34 DD 11 SUR 104 | U59: 42865923 | V59: 2063613 | W59: Santiago Calle | X59: KR | Y59: 27 | Z59: F | AF59: G | AH59: =CONCATENATE(X59," ",Y59," ",Z59," ",AA59," ",AB59," ",AC59," ",AD59," ",AE59," ",AF59," ",AG59) -> KR 27 F G | AI59: no reporta | AJ59: no reporta | AK59: Inmaculada | AP59: 5 | AQ59: 42040 | AR59: 42040 | AS59: =+AR59-AQ59 -> 0 | AT59: Remisión u otros | AU59: Auto de archivo | AW59: 42040 | AX59: L. Garcia | AY59: 42040
B60: 057-2015 | C60: 1317315 | E60: ESCOMBROS | H60: Escombros en un lote que generan perjuicios | I60: Comunidad | T60: No reporta | U60: No reporta | V60: no reporta | W60: Eucaris Arcila | X60: CL | Y60: 40 | AA60: SUR | AB60: 25 | AC60: A | AD60: 2 | AG60: 9703/02 | AH60: =CONCATENATE(X60," ",Y60," ",Z60," ",AA60," ",AB60," ",AC60," ",AD60," ",AE60," ",AF60," ",AG60) -> CL 40 SUR 25 A 2 9703/02 | AI60: no reporta | AJ60: no reporta | AK60: El Salado | AP60: 6 | AQ60: 42040 | AS60: =+AR60-AQ60 -> -42040 | AT60: Acta de compromiso | AU60: Auto de archivo | AV60: Los escombros ya fueron retirados
B61: 058-2015 | C61: 1317329 | D61: FAUNA DOMÉSTICA | H61: Accidente a una mascota generado por un menor de edad | I61: Diego Fernando Marulanda Santamaria | J61: CL | K61: 45 | L61: B | M61: SUR | N61: 36 | P61: 122 | T61: =CONCATENATE(J61," ",K61," ",L61," ",M61," ",N61," ",O61," ",P61," ",Q61," ",R61," ",S61) -> CL 45 B SUR 36 122 | U61: 3399671 | V61: 3002373282 | W61: Luz Stella Marulanda Santamaria - David Marulanda Muñoz | X61: CL | Y61: 45 | Z61: B | AA61: SUR | AB61: 36 | AD61: 134 | AH61: =CONCATENATE(X61," ",Y61," ",Z61," ",AA61," ",AB61," ",AC61," ",AD61," ",AE61," ",AF61," ",AG61) -> CL 45 B SUR 36 134 | AI61: no reporta | AJ61: no reporta | AK61: Las antillas | AP61: 7 | AQ61: 42040 | AS61: =+AR61-AQ61 -> -42040 | AT61: Acta de compromiso | AU61: Citaciones
B62: 059-2015 | C62: 1317326 | E62: RESIDUOS SOLIDOS | H62: Disposición de residuos en dias y horas no autorizadas | I62: De oficio - Enviaseo | T62: No reporta | U62: No reporta | V62: 4032000 | W62: Supermercado Baratillo | AH62: No reporta | AI62: no reporta | AJ62: no reporta | AK62: La Paz | AP62: 7 | AQ62: 42040 | AS62: =+AR62-AQ62 -> -42040 | AT62: Acta de compromiso | AU62: Auto de archivo
B63: 060-2015 | C63: 1317311 - 274541 (mismo 364-2015) | D63: HÍDRICO | G63: Urbanización Balcones del Trianon | H63: Disposición de aguas grises al humedal del Trianon | I63: Camilo | J63: CL | K63: 46 | L63: D | M63: SUR | N63: 37 | P63: 94 | T63: =CONCATENATE(J63," ",K63," ",L63," ",M63," ",N63," ",O63," ",P63," ",Q63," ",R63," ",S63) -> CL 46 D SUR 37 94 | U63: No reporta | V63: 2709288 | W63: Balcones del Trianon - Adm. Nubia Bedoya | X63: KR | Y63: 38 | AB63: 46 | AD63: 16 | AE63: SUR | AH63: =CONCATENATE(X63," ",Y63," ",Z63," ",AA63," ",AB63," ",AC63," ",AD63," ",AE63," ",AF63," ",AG63) -> KR 38 46 16 SUR | AI63: no reporta | AJ63: no reporta | AK63: El Trianón | AP63: 7 | AQ63: 42040 | AR63: 42036 | AS63: =+AR63-AQ63 -> -4 | AT63: Acta de compromiso | AU63: Auto de archivo | AW63: 42036 | AX63: L. Garcia | AY63: 42339
B64: 061-2015 | C64: 1317198 | D64: HÍDRICO | G64: Conjunto Residencial Sepia | H64: Presencia de obreros en el retiro de la quebrada la Hondita | I64: Conjunto Residenciaol Sepia | J64: KR | K64: 27 | N64: 28 | P64: 23 | Q64: SUR | T64: =CONCATENATE(J64," ",K64," ",L64," ",M64," ",N64," ",O64," ",P64," ",Q64," ",R64," ",S64) -> KR 27 28 23 SUR | U64: 900.397.631-6 | V64: 3206968211 | W64: Por determinar | AH64: No reporta | AI64: no reporta | AJ64: no reporta | AK64: El Esmeraldal | AP64: 4 | AQ64: 42037 | AR64: 42037 | AS64: =+AR64-AQ64 -> 0 | AT64: Remisión u otros | AU64: Auto de archivo | AW64: 42037 | AX64: J. Guzman | AY64: 42037 | CF64: 42054
B65: 062-2015 | C65: 1317451 - 3357 | D65: HÍDRICO | G65: Parcelación Fuente Clara | H65: Contaminación de fuente hídrica con sólidos | I65: Jairo Hernan Mejia | J65: CL | K65: 36 | M65: SUR | N65: 23 | P65: 68 | S65: 115 | T65: =CONCATENATE(J65," ",K65," ",L65," ",M65," ",N65," ",O65," ",P65," ",Q65," ",R65," ",S65) -> CL 36 SUR 23 68 115 | U65: No reporta | V65: 3134204 - 3153692278 | W65: Ivan Villegas - James Rodriguez y otro | X65: CL | Y65: 36 | AA65: SUR | AB65: 22 | AD65: 138 | AG65: 9-10-13-14 | AH65: =CONCATENATE(X65," ",Y65," ",Z65," ",AA65," ",AB65," ",AC65," ",AD65," ",AE65," ",AF65," ",AG65) -> CL 36 SUR 22 138 9-10-13-14 | AI65: no reporta | AJ65: 4484361 | AK65: El Chocho | AP65: 5 | AQ65: 42045 | AR65: 42045 | AS65: =+AR65-AQ65 -> 0 | AT65: Acta de compromiso | AU65: Auto de archivo | AW65: 42045 | AX65: J. Guzman | AY65: 42045 | AZ65: 42079 | BA65: J. Guzman | BB65: 42080
B66: 063-2015 | C66: 1317455 - 371942 | D66: HÍDRICO | G66: Pacelación Chaparral - Finca Romanza | H66: Afectaciones a fuente hidrica por proyecto urbanístico | I66: De oficio | T66: No reporta | U66: No reporta | V66: 3394072 | W66: Horacio Perez | AH66: Finca Romanza | AI66: no reporta | AJ66: 3861763 | AL66: Las Palmas | AP66: 12 | AQ66: 42046 | AR66: 42046 | AS66: =+AR66-AQ66 -> 0 | AT66: Ley 1333 de 2009 | AU66: Auto de archivo | AV66: Recurso de reposicion | AW66: 42046 | AX66: J. Guzman | AY66: 42046
B67: 064-2015 | C67: 1316931 | E67: RESIDUOS SOLIDOS | G67: Urbanización Molino de Piedra | H67: Inadecuado manejo de residuos sólidos en cuarto de reciclaje | I67: Comunidad | T67: No reporta | U67: No reporta | V67: no reporta | W67: Administración Copropiedad | X67: CL | Y67: 36 | AA67: SUR | AB67: 27 | AC67: D | AD67: 50 | AH67: =CONCATENATE(X67," ",Y67," ",Z67," ",AA67," ",AB67," ",AC67," ",AD67," ",AE67," ",AF67," ",AG67) -> CL 36 SUR 27 D 50 | AI67: no reporta | AJ67: 6003988 | AK67: Inmaculada | AP67: 5 | AQ67: 42050 | AR67: 42051 | AS67: =+AR67-AQ67 -> 1 | AT67: Acta de compromiso | AU67: Auto de archivo | AW67: 42051 | AX67: A. Espinoza | AY67: 42051
B68: 065-2015 | C68: 1317338 | G68: Urbanización Luminares del Bosque | H68: Atención por arbol en riesgo. | I68: Yiseth Velez Giraldo | J68: CL | K68: 48 | L68: C | M68: SUR | N68: 42 | O68: D | P68: 47 | T68: =CONCATENATE(J68," ",K68," ",L68," ",M68," ",N68," ",O68," ",P68," ",Q68," ",R68," ",S68) -> CL 48 C SUR 42 D 47 | U68: 24348368 | V68: 3342242 - 3116300920 | W68: Concejo de Administración | X68: CL | Y68: 48 | Z68: C | AA68: SUR | AB68: 42 | AC68: D | AD68: 47 | AH68: =CONCATENATE(X68," ",Y68," ",Z68," ",AA68," ",AB68," ",AC68," ",AD68," ",AE68," ",AF68," ",AG68) -> CL 48 C SUR 42 D 47 | AI68: 800073670 | AJ68: 3342242 | AK68: Loma del Barro | AP68: 7 | AQ68: 42040 | AR68: 42047 | AS68: =+AR68-AQ68 -> 7 | AT68: Remisión u otros | AU68: Auto de archivo | AW68: 42041 | AX68: J. Guzman | AY68: 42041 | BV68: 42047
B69: 066-2015 | C69: 110778 | E69: RESIDUOS SOLIDOS | H69: Acumulación permanente en de basuras en espacio público | I69: De oficio - Secretaria de Salud | T69: No reporta | U69: No reporta | V69: 3394041 | W69: Por determinar | X69: KR | Y69: 46 | AB69: 46 | AC69: A | AE69: SUR | AH69: =CONCATENATE(X69," ",Y69," ",Z69," ",AA69," ",AB69," ",AC69," ",AD69," ",AE69," ",AF69," ",AG69) -> KR 46 46 A SUR | AI69: no reporta | AJ69: no reporta | AK69: Primavera | AP69: 8 | AQ69: 42040 | AS69: =+AR69-AQ69 -> -42040 | AT69: Acta de compromiso | AU69: Auto de archivo
B70: 067-2015 | C70: 1317460 - 3358 | E70: RESIDUOS SOLIDOS | H70: Residuos dejados en carrera atlética | I70: Gabriel Jaime Alzate | T70: No reporta | U70: No reporta | V70: 3007866409 | W70: Organizadores carrera atletica | AH70: No reporta | AI70: no reporta | AJ70: no reporta | AL70: El Vallano | AP70: 11 | AQ70: 42046 | AS70: =+AR70-AQ70 -> -42046 | AT70: Remisión u otros | AU70: Auto de archivo
B71: 068-2015 | C71: 1317375 | D71: FAUNA DOMÉSTICA | H71: Ataque de mascota a otra | I71: Paola Alzate | J71: CL | K71: 48 | L71: E | M71: SUR | N71: 42 | P71: 10 | R71: 3.5 | S71: 102 | T71: =CONCATENATE(J71," ",K71," ",L71," ",M71," ",N71," ",O71," ",P71," ",Q71," ",R71," ",S71) -> CL 48 E SUR 42 10 3,5 102 | U71: 43755089 | V71: 3343930 | W71: Por determinar | X71: CL | Y71: 48 | Z71: C | AA71: SUR | AB71: 40 | AD71: 19 | AH71: =CONCATENATE(X71," ",Y71," ",Z71," ",AA71," ",AB71," ",AC71," ",AD71," ",AE71," ",AF71," ",AG71) -> CL 48 C SUR 40 19 | AI71: no reporta | AJ71: no reporta | AK71: Loma del Barro | AP71: 7 | AQ71: 42044 | AS71: =+AR71-AQ71 -> -42044 | AT71: Código de policia | AU71: Auto de inicio
B72: 069-2015 | C72: 1317152 | D72: AIRE | G72: Arrendamientos Survivienda - Cooperativa Belen | H72: Afectaciones a la calidad del aire por construcción | I72: Olga Ramirez | J72: KR | K72: 42 | N72: 35 | P72: 55 | Q72: SUR | S72: 207 | T72: =CONCATENATE(J72," ",K72," ",L72," ",M72," ",N72," ",O72," ",P72," ",Q72," ",R72," ",S72) -> KR 42 35 55 SUR 207 | U72: No reporta | V72: 3313850 | W72: Cooperativa Belen | X72: KR | Y72: 42 | AB72: 35 | AD72: 59 | AE72: SUR | AG72: 1 | AH72: =CONCATENATE(X72," ",Y72," ",Z72," ",AA72," ",AB72," ",AC72," ",AD72," ",AE72," ",AF72," ",AG72) -> KR 42 35 59 SUR 1 | AI72: 8663890 | AJ72: 3005742015 | AK72: Zona Centro | AP72: 9 | AQ72: 42033 | AR72: 42039 | AS72: =+AR72-AQ72 -> 6 | AT72: Acta de compromiso | AU72: Auto de archivo | AW72: 42039 | AX72: L. Garcia | AY72: 42039 | CF72: 42047
B73: 070-2015 | C73: 110696 - 134391 - (13-4391) | D73: LOTE-PREDIO | G73: Edificio Ambar | H73: Desalojo de personas que ocupan un lote | I73: Marta Valencia O. | J73: CL | K73: 32 | L73: A | M73: SUR | N73: 28 | P73: 21 | T73: =CONCATENATE(J73," ",K73," ",L73," ",M73," ",N73," ",O73," ",P73," ",Q73," ",R73," ",S73) -> CL 32 A SUR 28 21 | U73: 32481062 | V73: 3335594 | W73: Por determinar | AH73: No reporta | AI73: no reporta | AJ73: no reporta | AK73: Alto de Misael | AP73: 3 | AQ73: 42040 | AR73: 42047 | AS73: =+AR73-AQ73 -> 7 | AT73: Remisión u otros | AU73: Auto de archivo | AV73: Se da respuesta a la quejosa. | BV73: 42047
B74: 071-2015 | C74: 1317143 | E74: RESIDUOS SOLIDOS | H74: Lote en condiciones inadecuadas y con manejo inapropiado de residuos | I74: Edison Torres | T74: No reporta | U74: No reporta | V74: no reporta | W74: Por determinar | X74: CL | Y74: 40 | Z74: E | AA74: SUR | AB74: 27 | AD74: 80 | AH74: =CONCATENATE(X74," ",Y74," ",Z74," ",AA74," ",AB74," ",AC74," ",AD74," ",AE74," ",AF74," ",AG74) -> CL 40 E SUR 27 80 | AI74: no reporta | AJ74: no reporta | AK74: La Mina | AP74: 6 | AQ74: 42033 | AR74: 42027 | AS74: =+AR74-AQ74 -> -6 | AT74: Remisión u otros | AU74: Auto de archivo | AW74: 42027 | AX74: L. Garcia | AY74: 42027 | CF74: 42016
B75: 072-2015 | C75: 1317304 | E75: ESCOMBROS | H75: Escombros en espacio público | I75: De oficio - Espacio público | T75: No reporta | U75: No reporta | V75: no reporta | W75: Felix Correa | X75: KR | Y75: 46 | Z75: AA | AB75: 46 | AD75: 55 | AE75: SUR | AH75: =CONCATENATE(X75," ",Y75," ",Z75," ",AA75," ",AB75," ",AC75," ",AD75," ",AE75," ",AF75," ",AG75) -> KR 46 AA 46 55 SUR | AI75: no reporta | AJ75: no reporta | AK75: Primavera | AP75: 8 | AQ75: 42039 | AS75: =+AR75-AQ75 -> -42039 | AT75: Acta de compromiso | AU75: Auto de archivo | AW75: 42051 | AX75: L. Garcia | AY75: 42051 | AZ75: 42067 | BA75: A. Arbelaez | BB75: 42067
B76: 073-2015 | C76: 112246 - 1300515 | D76: LOTE-PREDIO | G76: Lote 16 Parcelación Serranía | H76: Seguimiento a obras del lote 16 | I76: De oficio - Autoridad Ambiental Delegada | T76: No reporta | U76: No reporta | V76: no reporta | W76: Propietario predio | AG76: Lote 16 | AH76: =CONCATENATE(X76," ",Y76," ",Z76," ",AA76," ",AB76," ",AC76," ",AD76," ",AE76," ",AF76," ",AG76) -> Lote 16 | AI76: no reporta | AJ76: no reporta | AL76: Las Palmas | AP76: 12 | AQ76: 42044 | AS76: =+AR76-AQ76 -> -42044 | AT76: Código de policia | AU76: Auto de archivo | AW76: 42024 | AX76: C. Calle - J. Uribe | AY76: 42044
B77: 074-2015 | C77: 1317353 | D77: FLORA | H77: Tala de arbol y afectación de jardin | I77: Anonimo | T77: No reporta | U77: No reporta | V77: no reporta | W77: Leobardo Medina | X77: KR | Y77: 30 | AB77: 41 | AE77: SUR | AH77: =CONCATENATE(X77," ",Y77," ",Z77," ",AA77," ",AB77," ",AC77," ",AD77," ",AE77," ",AF77," ",AG77) -> KR 30 41 SUR | AI77: no reporta | AJ77: no reporta | AK77: San Rafael | AP77: 6 | AQ77: 42041 | AS77: =+AR77-AQ77 -> -42041 | AT77: Acta de compromiso | AU77: Visitas patrulleros
B78: 075-2015 | C78: 1317255 - 268388 - 3301 | D78: HÍDRICO | G78: Parcelación La Loma | H78: Contaminación de fuente hídrica con vertimiento de alcantarillado | I78: Maria Paulina Mejia | J78: CL | K78: 27 | L78: D | M78: SUR | N78: 27 | O78: B | P78: 4 | S78: 160 | T78: =CONCATENATE(J78," ",K78," ",L78," ",M78," ",N78," ",O78," ",P78," ",Q78," ",R78," ",S78) -> CL 27 D SUR 27 B 4 160 | U78: No reporta | V78: 3361675 | W78: Urbanización Refugio del Esmerladal | X78: CL | Y78: 27 | Z78: C | AA78: SUR | AB78: 27 | AC78: B | AD78: 1 | AH78: =CONCATENATE(X78," ",Y78," ",Z78," ",AA78," ",AB78," ",AC78," ",AD78," ",AE78," ",AF78," ",AG78) -> CL 27 C SUR 27 B 1 | AI78: no reporta | AJ78: 3345551 | AK78: Inmaculada | AP78: 5 | AQ78: 42038 | AR78: 42033 | AS78: =+AR78-AQ78 -> -5 | AT78: Remisión u otros | AU78: Auto de archivo | AV78: Reapertura del caso, envian informe sobre la casa (130) responsable el 21-04-2015. | AW78: 42033 | AX78: L. Garcia | AY78: 42033 | AZ78: 42101 | BA78: J. Guzman | BB78: 42113 | CF78: 42054
B79: 076-2015 | C79: 1317257 | E79: ESCOMBROS | F79: 3 | H79: Disposición de escombros en sitio no autorizado | I79: De oficio | T79: No reporta | U79: No reporta | V79: 3394072 | W79: Tomas Arango Echavarria | X79: CL | Y79: 37 | Z79: A | AA79: SUR | AB79: 28 | AC79: C | AD79: 64 | AH79: =CONCATENATE(X79," ",Y79," ",Z79," ",AA79," ",AB79," ",AC79," ",AD79," ",AE79," ",AF79," ",AG79) -> CL 37 A SUR 28 C 64 | AI79: no reporta | AJ79: 2702258 - 3168313935 | AK79: La Pradera | AP79: 5 | AQ79: 42038 | AR79: 42032 | AS79: =+AR79-AQ79 -> -6 | AT79: Comparendo ambiental | AU79: Auto de archivo | AW79: 42032 | AX79: F. Villarraga | AY79: 42032
B80: 077-2015 | C80: mismo 43-2015 * 1317155 - 104042 - 295299 - 353339 | E80: RESIDUOS SOLIDOS | H80: Casa desocupada usada para disposición y acumulación de residuos | I80: Comunidad | T80: No reporta | U80: No reporta | V80: no reporta | W80: Por determinar | X80: DG | Y80: 29 | AB80: 34 | AC80: B | AD80: 55 | AE80: SUR | AH80: =CONCATENATE(X80," ",Y80," ",Z80," ",AA80," ",AB80," ",AC80," ",AD80," ",AE80," ",AF80," ",AG80) -> DG 29 34 B 55 SUR | AI80: no reporta | AJ80: no reporta | AK80: Uribe Angel | AP80: 3 | AQ80: 42033 | AS80: =+AR80-AQ80 -> -42033 | AT80: Acta de compromiso | AU80: Citaciones
B81: 078-2015 | C81: 1317163 | E81: RESIDUOS SOLIDOS | H81: Solicitan sensibilización e instlación de señal en este sector por manjeo inadecuado de residuos | I81: Comunidad | J81: CL | K81: 45 | M81: SUR | N81: 42 | O81: D | P81: 48 | T81: =CONCATENATE(J81," ",K81," ",L81," ",M81," ",N81," ",O81," ",P81," ",Q81," ",R81," ",S81) -> CL 45 SUR 42 D 48 | U81: No reporta | V81: no reporta | W81: Por determinar | AH81: No reporta | AI81: no reporta | AJ81: no reporta | AK81: La Paz | AP81: 7 | AQ81: 42033 | AS81: =+AR81-AQ81 -> -42033 | AT81: Acta de compromiso | AU81: Visitas patrulleros
B82: 079-2015 | C82: 1317176 | E82: RESIDUOS SOLIDOS | H82: Arrojar residuos solidos en un lote | I82: De oficio - Secretaria de Salud | T82: No reporta | U82: No reporta | V82: 3394000 | W82: Por determinar | X82: KR | Y82: 26 | AB82: 41 | AE82: SUR | AH82: =CONCATENATE(X82," ",Y82," ",Z82," ",AA82," ",AB82," ",AC82," ",AD82," ",AE82," ",AF82," ",AG82) -> KR 26 41 SUR | AI82: no reporta | AJ82: no reporta | AK82: San Rafael | AP82: 6 | AQ82: 42034 | AS82: =+AR82-AQ82 -> -42034 | AT82: Acta de compromiso | AU82: Visitas patrulleros
B83: 080-2015 | C83: 638 | D83: AIRE | G83: Finca la Mariposa | H83: Quemas no autorizadas de material vegetal | I83: De oficio - OGR | T83: No reporta | U83: No reporta | V83: 3394065 | W83: Propietario predio | X83: CL | Y83: 45 | Z83: B | AA83: SUR | AB83: 30 | AD83: 165 | AH83: =CONCATENATE(X83," ",Y83," ",Z83," ",AA83," ",AB83," ",AC83," ",AD83," ",AE83," ",AF83," ",AG83) -> CL 45 B SUR 30 165 | AI83: no reporta | AJ83: 6001749 | AK83: Las antillas | AP83: 7 | AQ83: 42037 | AR83: 42038 | AS83: =+AR83-AQ83 -> 1 | AT83: Código de policia | AU83: Auto de archivo | AW83: 42038 | AX83: J. Guzman | AY83: 42038
B84: 081-2015 | C84: 1317171 | D84: FAUNA DOMÉSTICA | H84: Ataque de un perro de la calle a un niño de dos años | I84: Jorge Albeiro Moreno Gonzalez | J84: DG | K84: 29 | N84: 34 | O84: B | P84: 16 | Q84: SUR | S84: 116 | T84: =CONCATENATE(J84," ",K84," ",L84," ",M84," ",N84," ",O84," ",P84," ",Q84," ",R84," ",S84) -> DG 29 34 B 16 SUR 116 | U84: No reporta | V84: 2068067 | W84: Por determinar | AH84: No reporta | AI84: no reporta | AJ84: no reporta | AK84: Inmaculada | AP84: 5 | AQ84: 42034 | AS84: =+AR84-AQ84 -> -42034 | AT84: Remisión u otros | AU84: Auto de archivo
B85: 082-2015 | C85: 1317192 | E85: RESIDUOS SOLIDOS | G85: Urbanizacion Señorial | H85: Acumulación de residuos en dias y horas no autorizadas por diferentes vecinos | I85: Alvaro Agudelo Sanchez | J85: CL | K85: 48 | L85: D | M85: SUR | N85: 42 | O85: BB | P85: 17 | R85: 4.5 | S85: 402 | T85: =CONCATENATE(J85," ",K85," ",L85," ",M85," ",N85," ",O85," ",P85," ",Q85," ",R85," ",S85) -> CL 48 D SUR 42 BB 17 4,5 402 | U85: 71675700 | V85: no reporta | W85: Por determinar | AH85: No reporta | AI85: no reporta | AJ85: no reporta | AK85: Loma del Barro | AP85: 7 | AQ85: 42037 | AS85: =+AR85-AQ85 -> -42037 | AT85: Acta de compromiso | AU85: Auto de archivo | AV85: Sencibilizaron
B86: 083-2015 | C86: 1317197 | E86: RESIDUOS SOLIDOS | H86: Acumulación de residuos especiales en espacio público | I86: Comunidad | T86: No reporta | U86: No reporta | V86: no reporta | W86: Raul Antonio Berrio | X86: KR | Y86: 42 | Z86: A | AB86: 26 | AC86: A | AD86: 4 | AE86: SUR | AG86: 205 | AH86: =CONCATENATE(X86," ",Y86," ",Z86," ",AA86," ",AB86," ",AC86," ",AD86," ",AE86," ",AF86," ",AG86) -> KR 42 A 26 A 4 SUR 205 | AI86: no reporta | AJ86: no reporta | AK86: Las orquideas | AP86: 3 | AQ86: 42037 | AS86: =+AR86-AQ86 -> -42037 | AT86: Acta de compromiso | AU86: Auto de archivo | AV86: Sencibilizaron
B87: 084-2015 | C87: 1317467 - (R/DP. 0120031) | E87: RESIDUOS SOLIDOS | F87: 5 | G87: Proyecto Tierra Grata del Esmerladal | H87: Descarga de aguas sedimentadas en fuente hídrica | I87: De oficio | T87: No reporta | U87: No reporta | V87: 3394072 | W87: Constructora Javier Londoño S.A | X87: CL | Y87: 6 | AB87: 43 | AC87: C | AD87: 8 | AH87: =CONCATENATE(X87," ",Y87," ",Z87," ",AA87," ",AB87," ",AC87," ",AD87," ",AE87," ",AF87," ",AG87) -> CL 6 43 C 8 | AI87: 890909034 | AJ87: 3224740 | AK87: El Esmeraldal | AP87: 4 | AQ87: 42046 | AR87: 42046 | AS87: =+AR87-AQ87 -> 0 | AT87: Comparendo ambiental | AU87: Auto de archivo | AW87: 42046 | AX87: F. Villarraga | AY87: 42046
B88: 085-2015 | C88: 114000 - 103444 mismo 394-2015 | D88: FAUNA DOMÉSTICA | H88: Tenencia y manejo inadecuado de mascotas | I88: De oficio - Secretaria de Salud | T88: No reporta | U88: No reporta | V88: 3394041 | W88: Carlos Arbelaez | X88: KR | Y88: 32 | AB88: 40 | AC88: E | AD88: 14 | AE88: SUR | AH88: =CONCATENATE(X88," ",Y88," ",Z88," ",AA88," ",AB88," ",AC88," ",AD88," ",AE88," ",AF88," ",AG88) -> KR 32 40 E 14 SUR | AI88: no reporta | AJ88: no reporta | AK88: San José | AP88: 6 | AQ88: 42046 | AS88: =+AR88-AQ88 -> -42046 | AT88: Acta de compromiso | AU88: Auto de archivo | AW88: 42066 | AX88: L. Garcia | AY88: 42067
B89: 086-2015 | C89: 1317476 | D89: FAUNA DOMÉSTICA | H89: Ataque de una mascota a una persona y a otra mascota | I89: Ana Cecilia Henao | J89: CL | K89: 26 | M89: SUR | N89: 22 | P89: 6 | S89: 101 | T89: =CONCATENATE(J89," ",K89," ",L89," ",M89," ",N89," ",O89," ",P89," ",Q89," ",R89," ",S89) -> CL 26 SUR 22 6 101 | U89: 43731484 | V89: 3360652 - 3360539 | W89: Por determinar | X89: CL | Y89: 38 | Z89: A | AA89: SUR | AB89: 32 | AD89: 28 | AG89: 2 | AH89: =CONCATENATE(X89," ",Y89," ",Z89," ",AA89," ",AB89," ",AC89," ",AD89," ",AE89," ",AF89," ",AG89) -> CL 38 A SUR 32 28 2 | AI89: no reporta | AJ89: no reporta | AK89: Mesa | AP89: 9 | AQ89: 42046 | AS89: =+AR89-AQ89 -> -42046 | AT89: Código de policia | AU89: Auto de archivo
